Workbook
Name _10000: [1]Регион!#REF!
Name _1080: [2]Регион!#REF!
Name _1090: [2]Регион!#REF!
Name _1100: [2]Регион!#REF!
Name _1110: [2]Регион!#REF!
Name _2: [1]Регион!#REF!
Name _2010: #REF!
Name _2080: [2]Регион!#REF!
Name _2090: [2]Регион!#REF!
Name _2100: [2]Регион!#REF!
Name _2110: [2]Регион!#REF!
Name _3080: [2]Регион!#REF!
Name _3090: [2]Регион!#REF!
Name _3100: [2]Регион!#REF!
Name _3110: [2]Регион!#REF!
Name _4080: [2]Регион!#REF!
Name _4090: [2]Регион!#REF!
Name _4100: [2]Регион!#REF!
Name _4110: [2]Регион!#REF!
Name _5080: [2]Регион!#REF!
Name _5090: [2]Регион!#REF!
Name _5100: [2]Регион!#REF!
Name _5110: [2]Регион!#REF!
Name _6080: [2]Регион!#REF!
Name _6090: [2]Регион!#REF!
Name _6100: [2]Регион!#REF!
Name _6110: [2]Регион!#REF!
Name _7031_1: [2]Регион!#REF!
Name _7031_2: [2]Регион!#REF!
Name _7032_1: [2]Регион!#REF!
Name _7032_2: [2]Регион!#REF!
Name _7033_1: [2]Регион!#REF!
Name _7033_2: [2]Регион!#REF!
Name _7034_1: [2]Регион!#REF!
Name _7034_2: [2]Регион!#REF!
Name A2298668K: [3]AustralianNA2!$DF$1:$DF$10,[3]AustralianNA2!$DF$12:$DF$244
Name A2302665R_Latest: [3]AustralianNA!$CB$243
Name A2302667V: [3]AustralianNA!$CD$1:$CD$10,[3]AustralianNA!$CD$11:$CD$243
Name A2303329W_Latest: [3]AustralianNA!$S$244
Name A2303331J: [3]AustralianNA!$T$1:$T$10,[3]AustralianNA!$T$12:$T$244
Name A2303331J_Data: [3]AustralianNA!$T$12:$T$244
Name A2303331J_Latest: [3]AustralianNA!$T$244
Name A2303335T: [3]AustralianNA!$V$1:$V$10,[3]AustralianNA!$V$12:$V$244
Name A2303335T_Data: [3]AustralianNA!$V$12:$V$244
Name A2303335T_Latest: [3]AustralianNA!$V$244
Name A2303337W: [3]AustralianNA!$W$1:$W$10,[3]AustralianNA!$W$12:$W$244
Name A2303337W_Data: [3]AustralianNA!$W$12:$W$244
Name A2303339A: [3]AustralianNA!$X$1:$X$10,[3]AustralianNA!$X$12:$X$244
Name A2303339A_Data: [3]AustralianNA!$X$12:$X$244
Name A2303339A_Latest: [3]AustralianNA!$X$244
Name A2303341L: [3]AustralianNA!$Y$1:$Y$10,[3]AustralianNA!$Y$12:$Y$244
Name A2303341L_Latest: [3]AustralianNA!$Y$244
Name A2303345W: [3]AustralianNA!$AA$1:$AA$10,[3]AustralianNA!$AA$12:$AA$244
Name A2303345W_Data: [3]AustralianNA!$AA$12:$AA$244
Name A2303347A: [3]AustralianNA!$AB$1:$AB$10,[3]AustralianNA!$AB$12:$AB$244
Name A2303347A_Data: [3]AustralianNA!$AB$12:$AB$244
Name A2303347A_Latest: [3]AustralianNA!$AB$244
Name A2303349F_Data: [3]AustralianNA!$AC$12:$AC$244
Name A2303349F_Latest: [3]AustralianNA!$AC$244
Name A2303351T: [3]AustralianNA!$AD$1:$AD$10,[3]AustralianNA!$AD$12:$AD$244

Sheet F2

Sheet DataF3
A1: year | B1: High income | C1: Middle and low income
A2: 2001 | B2: 0.7738202 | C2: =1-B2 -> 0.2261798
A3: 2002 | B3: 0.7694009 | C3: =1-B3 -> 0.2305991
A4: 2003 | B4: 0.7719812 | C4: =1-B4 -> 0.2280188
A5: 2004 | B5: 0.775029 | C5: =1-B5 -> 0.224971
A6: 2005 | B6: 0.7631019 | C6: =1-B6 -> 0.2368981
A7: 2006 | B7: 0.7487888 | C7: =1-B7 -> 0.2512112
A8: 2007 | B8: 0.7574551 | C8: =1-B8 -> 0.2425449
A9: 2008 | B9: 0.7638805 | C9: =1-B9 -> 0.2361195
A10: 2009 | B10: 0.759133 | C10: =1-B10 -> 0.240867
A11: 2010 | B11: 0.747589 | C11: =1-B11 -> 0.252411
A12: 2011 | B12: 0.7583146 | C12: =1-B12 -> 0.2416854
A13: 2012 | B13: 0.7677397 | C13: =1-B13 -> 0.2322603
... A23: 2022 | B23: 0.7018187 | C23: =1-B23 -> 0.2981813

Sheet DataF4
C1: GDP 2022 | D1: Offshore wealth bn | E1: Offshore wealth /GDP
A2: Iran | B2: Iran (Islamic Republic of) | C2: 352.21301 | D2: 2.4288454 | E2: 0.0068959561
A3: India | B3: India | C3: 3386.4029 | D3: 26.021391 | E3: 0.0076840799
A4: Indonesia | B4: Indonesia | C4: 1318.807 | D4: 28.966833 | E4: 0.021964421
A5: Brazil | B5: Brazil | C5: 1924.1339 | D5: 77.173401 | E5: 0.040108122
A6: USA | B6: United States of America | C6: 25464.475 | D6: 1499.2886 | E6: 0.058877654
A7: Korea | B7: Korea (the Republic of) | C7: 1665.2455 | D7: 102.27711 | E7: 0.061418634
A8: Nigeria | B8: Nigeria | C8: =477375987712/1000000000 -> 477.37599 | D8: 31.087618 | E8: 0.06512187
A9: Japan | B9: Japan | C9: 4233.538 | D9: 317.54413 | E9: 0.075006798
A10: Argentina | B10: Argentina | C10: 632.77027 | D10: 47.721878 | E10: 0.075417385
A11: Norway | B11: Norway | C11: 579.267 | D11: 45.811775 | E11: 0.079085767
A12: Germany | B12: Germany | C12: 4075.395 | D12: 353.02353 | E12: 0.086623147
A13: Colombia | B13: Colombia | C13: 343.93899 | D13: 31.195257 | E13: 0.090699971
A14: Finland | B14: Finland | C14: 281.04701 | D14: 25.806553 | E14: 0.091822907
A15: Italy | B15: Italy | C15: 2012.013 | D15: 187.30733 | E15: 0.09309449
A16: Sweden | B16: Sweden | C16: 585.93903 | D16: 56.709248 | E16: 0.096783534
A17: Spain | B17: Spain | C17: 1400.52 | D17: 139.83559 | E17: 0.099845476
A18: China | B18: China | C18: 18100.045 | D18: 1949.3284 | E18: 0.10769743
A19: Australia | B19: Australia | C19: 1701.893 | D19: 190.87227 | E19: 0.11215292
A20: Russia | B20: Russian Federation | C20: 2240.4223 | D20: 253.9256 | E20: 0.11333827
... A39: UAE | B39: United Arab Emirates | C39: 507.53493 | D39: 545.35034 | E39: 1.074508

Sheet DataF5
B1: Offshore wealth, % of world GDP
B2: Offshore wealth | C2: Untaxed offshore wealth: high-end | D2: Untaxed offshore wealth: main | E2: Untaxed offshore wealth: low end | F2: Fraction taxed (high evasion scenario) | G2: Fraction taxed (central scenario) | H2: Fraction taxed (low evasion scenario) | J2: World GDP | K2: Offshore wealth
A3: 2000
A4: 2001 | B4: =K4/J4 -> 0.094147315 | C4: =(1-F4)*$B4 -> 0.089439949 | D4: =(1-G4)*$B4 -> 0.089439949 | E4: =(1-H4)*$B4 -> 0.089439949 | F4: =G4-(H4-G4) -> 0.05 | G4: 0.05 | H4: =G4 -> 0.05 | J4: 34810 | K4: 3277.268
A5: 2002 | B5: =K5/J5 -> 0.093125253 | C5: =(1-F5)*$B5 -> 0.08846899 | D5: =(1-G5)*$B5 -> 0.08846899 | E5: =(1-H5)*$B5 -> 0.08846899 | F5: =G5-(H5-G5) -> 0.05 | G5: 0.05 | H5: =G5 -> 0.05 | J5: 35600 | K5: 3315.259
A6: 2003 | B6: =K6/J6 -> 0.088196412 | C6: =(1-F6)*$B6 -> 0.083786591 | D6: =(1-G6)*$B6 -> 0.083786591 | E6: =(1-H6)*$B6 -> 0.083786591 | F6: =G6-(H6-G6) -> 0.05 | G6: 0.05 | H6: =G6 -> 0.05 | J6: 39890 | K6: 3518.1549
A7: 2004 | B7: =K7/J7 -> 0.094836885 | C7: =(1-F7)*$B7 -> 0.09009504 | D7: =(1-G7)*$B7 -> 0.09009504 | E7: =(1-H7)*$B7 -> 0.09009504 | F7: =G7-(H7-G7) -> 0.05 | G7: 0.05 | H7: =G7 -> 0.05 | J7: 44810 | K7: 4249.6408
A8: 2005 | B8: =K8/J8 -> 0.093891775 | C8: =(1-F8)*$B8 -> 0.089197186 | D8: =(1-G8)*$B8 -> 0.089197186 | E8: =(1-H8)*$B8 -> 0.089197186 | F8: =G8-(H8-G8) -> 0.05 | G8: 0.05 | H8: =G8 -> 0.05 | J8: 48520 | K8: 4555.6289
A9: 2006 | B9: =K9/J9 -> 0.097116227 | C9: =(1-F9)*$B9 -> 0.092260416 | D9: =(1-G9)*$B9 -> 0.092260416 | E9: =(1-H9)*$B9 -> 0.092260416 | F9: =G9-(H9-G9) -> 0.05 | G9: 0.05 | H9: =G9 -> 0.05 | J9: 51690 | K9: 5019.9378
A10: 2007 | B10: =K10/J10 -> 0.11545814 | C10: =(1-F10)*$B10 -> 0.10968523 | D10: =(1-G10)*$B10 -> 0.10968523 | E10: =(1-H10)*$B10 -> 0.10968523 | F10: =G10-(H10-G10) -> 0.05 | G10: 0.05 | H10: =G10 -> 0.05 | J10: 58340 | K10: 6735.8279
A11: 2008 | B11: =K11/J11 -> 0.087654372 | C11: =(1-F11)*$B11 -> 0.078888935 | D11: =(1-G11)*$B11 -> 0.078888935 | E11: =(1-H11)*$B11 -> 0.078888935 | F11: =G11-(H11-G11) -> 0.1 | G11: 0.1 | H11: =G11 -> 0.1 | J11: 64000 | K11: 5609.8798
A12: 2009 | B12: =K12/J12 -> 0.10331268 | C12: =(1-F12)*$B12 -> 0.092981409 | D12: =(1-G12)*$B12 -> 0.092981409 | E12: =(1-H12)*$B12 -> 0.092981409 | F12: =G12-(H12-G12) -> 0.1 | G12: 0.1 | H12: =G12 -> 0.1 | J12: 60690 | K12: 6270.0463
A13: 2010 | B13: =K13/J13 -> 0.087030188 | C13: =(1-F13)*$B13 -> 0.07832717 | D13: =(1-G13)*$B13 -> 0.07832717 | E13: =(1-H13)*$B13 -> 0.07832717 | F13: =G13-(H13-G13) -> 0.1 | G13: 0.1 | H13: =G13 -> 0.1 | J13: 66400 | K13: 5778.8045
A14: 2011 | B14: =K14/J14 -> 0.087952976 | C14: =(1-F14)*$B14 -> 0.079157678 | D14: =(1-G14)*$B14 -> 0.079157678 | E14: =(1-H14)*$B14 -> 0.079157678 | F14: =G14-(H14-G14) -> 0.1 | G14: 0.1 | H14: =G14 -> 0.1 | J14: 73900 | K14: 6499.7249
A15: 2012 | B15: =K15/J15 -> 0.10895288 | C15: =(1-F15)*$B15 -> 0.092609951 | D15: =(1-G15)*$B15 -> 0.092609951 | E15: =(1-H15)*$B15 -> 0.092609951 | F15: =G15-(H15-G15) -> 0.15 | G15: 0.15 | H15: =G15 -> 0.15 | J15: 75230 | K15: 8196.5254
... A18: 2015 | B18: =K18/J18 -> 0.12379781 | C18: =(1-F18)*$B18 -> 0.099038251 | D18: =(1-G18)*$B18 -> 0.099038251 | E18: =(1-H18)*$B18 -> 0.099038251 | F18: =G18-(H18-G18) -> 0.2 | G18: 0.2 | H18: =G18 -> 0.2 | J18: 75120 | K18: 9299.6918
A19: 2016 | B19: =K19/J19 -> 0.10117812 | C19: =(1-F19)*$B19 -> 0.080942494 | D19: =(1-G19)*$B19 -> 0.075883588 | E19: =(1-H19)*$B19 -> 0.070824682 | F19: =G19-(H19-G19) -> 0.2 | G19: 0.25 | H19: 0.3 | J19: 76440 | K19: 7734.0553
A20: 2017 | B20: =K20/J20 -> 0.11351652 | C20: =(1-F20)*$B20 -> 0.068109913 | D20: =(1-G20)*$B20 -> 0.056758261 | E20: =(1-H20)*$B20 -> 0.045406609 | F20: =G20-(H20-G20) -> 0.4 | G20: 0.5 | H20: 0.6 | J20: 81200 | K20: 9217.5416
A21: 2018 | B21: =K21/J21 -> 0.10018927 | C21: =(1-F21)*$B21 -> 0.050094633 | D21: =(1-G21)*$B21 -> 0.040075707 | E21: =(1-H21)*$B21 -> 0.03005678 | F21: =G21-(H21-G21) -> 0.5 | G21: 0.6 | H21: 0.7 | J21: 86030 | K21: 8619.2826
A22: 2019 | B22: =K22/J22 -> 0.12025419 | C22: =(1-F22)*$B22 -> 0.057120739 | D22: =(1-G22)*$B22 -> 0.042088966 | E22: =(1-H22)*$B22 -> 0.027057192 | F22: =G22-(H22-G22) -> 0.525 | G22: 0.65 | H22: 0.775 | J22: 87330 | K22: 10501.798
A23: 2020 | B23: =K23/J23 -> 0.1474475 | C23: =(1-F23)*$B23 -> 0.054555575 | D23: =(1-G23)*$B23 -> 0.039810825 | E23: =(1-H23)*$B23 -> 0.022117125 | F23: =0.9*70% -> 0.63 | G23: =70%+0.1*0.3 -> 0.73 | H23: =70%+0.5*0.3 -> 0.85 | J23: 85050 | K23: 12540.41
A24: 2021 | B24: =K24/J24 -> 0.14187061 | C24: =(1-F24)*$B24 -> 0.052492125 | D24: =(1-G24)*$B24 -> 0.038305064 | E24: =(1-H24)*$B24 -> 0.021280591 | F24: =0.9*70%+0*0.3 -> 0.63 | G24: =70%+0.1*0.3 -> 0.73 | H24: =70%+0.5*0.3 -> 0.85 | J24: 96590 | K24: 13703.282
A25: 2022 | B25: =K25/J25 -> 0.11941856 | C25: =(1-F25)*$B25 -> 0.044184866 | D25: =(1-G25)*$B25 -> 0.03224301 | E25: =(1-H25)*$B25 -> 0.017912784 | F25: =0.9*70%+0*0.3 -> 0.63 | G25: =70%+0.1*0.3 -> 0.73 | H25: =70%+0.5*0.3 -> 0.85 | J25: 101100 | K25: 12073.216

Sheet AppendixTables

Sheet T.A1
B3: Table A1: The world's offshore household financial wealth
C4: Billions current US$ | J4: % of world GDP
B5: World GDP | C5: Offshore wealth | D5: Of which: portfolio securities | E5: Of which: bank deposits | F5: Of which: Switzerland | G5: % declared | H5: Offshore wealth, BCG | I5: Offshore wealth, TJN | J5: Offshore wealth | K5: Of which: portfolio securities | L5: Of which: bank deposits | M5: Of which: Switzerland | N5: Offshore wealth, BCG | O5: Offshore wealth, TJN | Q5: Switzerland securities | R5: Switzerland deposits | S5: Switzerland total | U5: BIS deposits in bank havens | W5: Deposits/total | X5: Switzerland/total
A6: 1999 | F6: 1231.6908 | Q6: 928.14763 | R6: 303.54321 | T6: =R6/Q6 -> 0.32704195
A7: 2000 | B7: 33276.21 | F7: 1197.4418 | G7: 0.05 | M7: =F7/$B7 -> 0.03598492 | Q7: 878.46998 | R7: 318.97179 | T7: =R7/Q7 -> 0.36309925 | U7: 1105.5885
A8: 2001 | B8: 34810 | C8: =D8+E8 -> 3311.5496 | D8: 2792.1756 | E8: =E9*U8/U9 -> 519.37393 | F8: 1271.2507 | G8: 0.05 | J8: =C8/$B8 -> 0.095132134 | K8: =D8/$B8 -> 0.080211883 | L8: =E8/$B8 -> 0.014920251 | M8: =F8/$B8 -> 0.036519698 | Q8: 940.97611 | R8: 330.27458 | T8: =R8/Q8 -> 0.35099146 | U8: 1197.1868 | W8: =E8/C8 -> 0.15683713 | X8: =F8/C8 -> 0.38388394
A9: 2002 | B9: 35600 | C9: =D9+E9 -> 3326.7462 | D9: 2743.2189 | E9: =E10*U9/U10 -> 583.52732 | F9: 1282.4401 | G9: 0.05 | J9: =C9/$B9 -> 0.093447928 | K9: =D9/$B9 -> 0.077056711 | L9: =E9/$B9 -> 0.016391217 | M9: =F9/$B9 -> 0.0360236 | P9: =AVERAGE(C8:C9)/B9 -> 0.093234491 | Q9: 964.52758 | R9: 317.91256 | T9: =R9/Q9 -> 0.32960443 | U9: 1345.064 | W9: =E9/C9 -> 0.17540482 | X9: =F9/C9 -> 0.38549383
A10: 2003 | B10: 39890 | C10: =D10+E10 -> 3569.3503 | D10: 2899.6006 | E10: =E11*U10/U11 -> 669.74968 | F10: 1556.1789 | G10: 0.05 | J10: =C10/$B10 -> 0.089479827 | K10: =D10/$B10 -> 0.072689913 | L10: =E10/$B10 -> 0.016789914 | M10: =F10/$B10 -> 0.039011754 | P10: =AVERAGE(C9:C10)/B10 -> 0.086438913 | Q10: 1238.5359 | R10: 317.64292 | T10: =R10/Q10 -> 0.25646646 | U10: 1543.8115 | W10: =E10/C10 -> 0.1876391 | X10: =F10/C10 -> 0.43598379
A11: 2004 | B11: 44810 | C11: =D11+E11 -> 4266.8114 | D11: 3530.2039 | E11: =E12*U11/U12 -> 736.60745 | F11: 1819.919 | G11: 0.05 | I11: 11500 | J11: =C11/$B11 -> 0.095220071 | K11: =D11/$B11 -> 0.07878161 | L11: =E11/$B11 -> 0.016438461 | M11: =F11/$B11 -> 0.040614126 | O11: =I11/$B11 -> 0.25663914 | P11: =AVERAGE(C10:C11)/B11 -> 0.087437644 | Q11: 1459.017 | R11: 360.90195 | T11: =R11/Q11 -> 0.24735965 | U11: 1697.9225 | W11: =E11/C11 -> 0.17263652 | X11: =F11/C11 -> 0.42652904
A12: 2005 | B12: 48520 | C12: =D12+E12 -> 4566.7319 | D12: 3780.1073 | E12: =E13*U12/U13 -> 786.62464 | F12: 2019.5016 | G12: 0.05 | H12: =H13/1.107 -> 6052.3939 | J12: =C12/$B12 -> 0.094120609 | K12: =D12/$B12 -> 0.077908229 | L12: =E12/$B12 -> 0.016212379 | M12: =F12/$B12 -> 0.041622044 | N12: =H12/$B12 -> 0.12474019 | P12: =AVERAGE(C11:C12)/B12 -> 0.091029919 | Q12: 1626.7653 | R12: 392.73626 | T12: =R12/Q12 -> 0.24142159 | U12: 1813.215 | W12: =E12/C12 -> 0.17225111 | X12: =F12/C12 -> 0.4422203
A13: 2006 | B13: 51690 | C13: =D13+E13 -> 5052.61 | D13: 4147.6764 | E13: =E14*U13/U14 -> 904.93363 | F13: 2422.1622 | G13: 0.05 | H13: 6700 | J13: =C13/$B13 -> 0.097748308 | K13: =D13/$B13 -> 0.08024137 | L13: =E13/$B13 -> 0.017506938 | M13: =F13/$B13 -> 0.046859396 | N13: =H13/$B13 -> 0.12961888 | P13: =AVERAGE(C12:C13)/B13 -> 0.093048384 | Q13: 1920.9335 | R13: 501.22868 | T13: =R13/Q13 -> 0.26092974 | U13: 2085.924 | W13: =E13/C13 -> 0.17910221 | X13: =F13/C13 -> 0.47938831
A14: 2007 | B14: 58340 | C14: =D14+E14 -> 6795.0723 | D14: 5658.8352 | E14: =E15*U14/U15 -> 1136.2371 | F14: 2911.7417 | G14: 0.05 | H14: 7300 | J14: =C14/$B14 -> 0.11647364 | K14: =D14/$B14 -> 0.096997518 | L14: =E14/$B14 -> 0.019476124 | M14: =F14/$B14 -> 0.049909869 | N14: =H14/$B14 -> 0.12512856 | P14: =AVERAGE(C13:C14)/B14 -> 0.10153996 | Q14: 2289.6137 | R14: 622.128 | T14: =R14/Q14 -> 0.27171745 | U14: 2619.0918 | W14: =E14/C14 -> 0.16721486 | X14: =F14/C14 -> 0.42850784
A15: 2008 | B15: 64000 | C15: =D15+E15 -> 5644.1316 | D15: 4384.1029 | E15: =E16*U15/U16 -> 1260.0287 | F15: 2135.3864 | G15: 0.1 | H15: 6700 | J15: =C15/$B15 -> 0.088189556 | K15: =D15/$B15 -> 0.068501608 | L15: =E15/$B15 -> 0.019687948 | M15: =F15/$B15 -> 0.033365412 | N15: =H15/$B15 -> 0.1046875 | P15: =AVERAGE(C14:C15)/B15 -> 0.09718128 | Q15: 1649.7491 | R15: 485.63727 | T15: =R15/Q15 -> 0.29437037 | U15: 2904.4385 | W15: =E15/C15 -> 0.2232458 | X15: =F15/C15 -> 0.37833746
A16: 2009 | B16: 60690 | C16: =D16+E16 -> 6305.3213 | D16: 5145.125 | E16: =E17*U16/U17 -> 1160.1962 | F16: 2358.6086 | G16: 0.1 | H16: 7400 | J16: =C16/$B16 -> 0.10389391 | K16: =D16/$B16 -> 0.084777147 | L16: =E16/$B16 -> 0.019116761 | M16: =F16/$B16 -> 0.038863216 | N16: =H16/$B16 -> 0.12193113 | P16: =AVERAGE(C15:C16)/B16 -> 0.098446637 | Q16: 2006.2416 | R16: 352.36701 | T16: =R16/Q16 -> 0.17563539 | U16: 2674.319 | W16: =E16/C16 -> 0.18400272 | X16: =F16/C16 -> 0.37406636
A17: 2010 | B17: 66400 | C17: =D17+E17 -> 5844.8574 | D17: 4702.0421 | E17: =E18*U17/U18 -> 1142.8153 | F17: 2301.2504 | G17: 0.1 | H17: 7800 | I17: 21000 | J17: =C17/$B17 -> 0.088024961 | K17: =D17/$B17 -> 0.070813887 | L17: =E17/$B17 -> 0.017211074 | M17: =F17/$B17 -> 0.034657385 | N17: =H17/$B17 -> 0.11746988 | O17: =I17/$B17 -> 0.31626506 | P17: =AVERAGE(C16:C17)/B17 -> 0.091492309 | Q17: 2004.4518 | R17: 296.79851 | T17: =R17/Q17 -> 0.14806966 | U17: 2634.255 | W17: =E17/C17 -> 0.19552493 | X17: =F17/C17 -> 0.39372224
A18: 2011 | B18: 73900 | C18: =D18+E18 -> 6563.066 | D18: 5401.5733 | E18: =E19*D18/D19 -> 1161.4927 | F18: 2251.6964 | G18: 0.1 | H18: 7800 | J18: =C18/$B18 -> 0.088810095 | K18: =D18/$B18 -> 0.073093008 | L18: =E18/$B18 -> 0.015717087 | M18: =F18/$B18 -> 0.030469505 | N18: =H18/$B18 -> 0.10554804 | P18: =AVERAGE(C17:C18)/B18 -> 0.083950768 | Q18: 1970.7454 | R18: 280.95105 | T18: =R18/Q18 -> 0.14256081 | U18: 2677.3075 | W18: =E18/C18 -> 0.17697411 | X18: =F18/C18 -> 0.34308605
A19: 2012 | B19: 75230 | C19: =D19+E19 -> 8219.9757 | D19: 6765.2528 | E19: =E20*D19/D20 -> 1454.7228 | F19: 2369.8748 | G19: 0.15 | H19: 8500 | J19: =C19/$B19 -> 0.1092646 | K19: =D19/$B19 -> 0.089927593 | L19: =E19/$B19 -> 0.019337004 | M19: =F19/$B19 -> 0.031501726 | N19: =H19/$B19 -> 0.11298684 | P19: =AVERAGE(C18:C19)/B19 -> 0.098252304 | Q19: 2149.3225 | R19: 220.5523 | T19: =R19/Q19 -> 0.1026148 | U19: 2677.3075 | W19: =E19/C19 -> 0.17697411 | X19: =F19/C19 -> 0.28830679
A20: 2013 | B20: 77380 | C20: =D20+E20 -> 8475.8163 | D20: 6975.8163 | E20: 1500 | F20: 2423.484 | G20: 0.2 | H20: 8900 | J20: =C20/$B20 -> 0.10953497 | K20: =D20/$B20 -> 0.09015012 | L20: =E20/$B20 -> 0.019384854 | M20: =F20/$B20 -> 0.031319256 | N20: =H20/$B20 -> 0.1150168 | P20: =AVERAGE(C19:C20)/B20 -> 0.10788183 | Q20: 2226.1948 | R20: 197.2892 | T20: =R20/Q20 -> 0.088621712 | W20: =E20/C20 -> 0.17697411 | X20: =F20/C20 -> 0.28592928
A21: 2014 | B21: 79420 | C21: =J21*B21 -> 9523.3891 | D21: 7714.0513 | E21: =C21-D21 -> 1809.3377 | F21: 2341.8949 | G21: 0.2 | H21: 10000 | J21: =J20*N21/N20 -> 0.11991172 | K21: =D21/$B21 -> 0.097129833 | L21: =E21/$B21 -> 0.022781891 | M21: =F21/$B21 -> 0.029487471 | N21: =H21/$B21 -> 0.12591287 | P21: =AVERAGE(C20:C21)/B21 -> 0.11331658 | Q21: 2174.4505 | R21: 167.44441 | T21: =R21/Q21 -> 0.077005391 | W21: =E21/C21 -> 0.18998885 | X21: =F21/C21 -> 0.24590982
A22: 2015 | B22: 75120 | C22: =C21*H22/H21 -> 9523.3891 | D22: 7107.907 | E22: =$C22*E21/$C21 -> 1809.3377 | F22: 2216.8993 | G22: 0.2 | H22: 10000 | J22: =J21*N22/N21 -> 0.12677568 | K22: =D22/$B22 -> 0.0946207 | L22: =E22/$B22 -> 0.024085966 | M22: =F22/$B22 -> 0.029511439 | N22: =H22/$B22 -> 0.13312034 | P22: =AVERAGE(C21:C22)/B22 -> 0.12677568 | Q22: 2020.828 | R22: 143.00458 | T22: =R22/Q22 -> 0.070765339 | W22: =E22/C22 -> 0.18998885 | X22: =F22/C22 -> 0.2327847
A23: 2016 | B23: 76440 | C23: =D23+E23 -> 7905.564 | D23: 6301.4995 | E23: =E22*$D23/$D22 -> 1604.0645 | F23: =Q23+R23 -> 2128.9411 | H23: 10300 | J23: =C23/$B23 -> 0.10342182 | K23: =D23/$B23 -> 0.082437199 | L23: =E23/$B23 -> 0.020984621 | M23: =F23/$B23 -> 0.027851139 | N23: =H23/$B23 -> 0.13474621 | P23: =AVERAGE(C22:C23)/B23 -> 0.11400414 | Q23: 1984.3516 | R23: 144.58946 | T23: =R23/Q23 -> 0.072864839 | W23: =E23/C23 -> 0.20290323 | X23: =F23/C23 -> 0.26929655
A24: 2017 | B24: 81200 | C24: =D24+E24 -> 9429.1896 | D24: 7515.9766 | E24: =E23*$D24/$D23 -> 1913.213 | F24: =Q24+R24 -> 2444.343 | H24: 8200 | J24: =C24/$B24 -> 0.11612302 | K24: =D24/$B24 -> 0.092561288 | L24: =E24/$B24 -> 0.023561737 | M24: =F24/$B24 -> 0.030102747 | N24: =H24/$B24 -> 0.10098522 | P24: =AVERAGE(C23:C24)/B24 -> 0.10674109 | Q24: 2268.1587 | R24: 176.18438 | T24: =R24/Q24 -> 0.077677275 | W24: =E24/C24 -> 0.20290323 | X24: =F24/C24 -> 0.25923151
A25: 2018 | B25: 86030 | C25: =D25+E25 -> 8765.7848 | D25: 6987.1787 | E25: =E24*$D25/$D24 -> 1778.606 | F25: =Q25+R25 -> 2281.5676 | H25: 8700 | I25: 9900 | J25: =C25/$B25 -> 0.10189219 | K25: =D25/$B25 -> 0.081217932 | L25: =E25/$B25 -> 0.020674254 | M25: =F25/$B25 -> 0.026520604 | N25: =H25/$B25 -> 0.10112751 | P25: =AVERAGE(C24:C25)/B25 -> 0.10574785 | Q25: 2076.2713 | R25: 205.29628 | T25: =R25/Q25 -> 0.098877387 | W25: =E25/C25 -> 0.20290323 | X25: =F25/C25 -> 0.26028104
A26: 2019 | B26: 87330 | C26: =D26+E26 -> 10740.665 | D26: 8561.3498 | E26: =E25*$D26/$D25 -> 2179.3157 | F26: =Q26+R26 -> 2594.5729 | H26: 9600 | J26: =C26/$B26 -> 0.12298941 | K26: =D26/$B26 -> 0.098034464 | L26: =E26/$B26 -> 0.024954949 | M26: =F26/$B26 -> 0.029709984 | N26: =H26/$B26 -> 0.10992786 | P26: =AVERAGE(C25:C26)/B26 -> 0.11168241 | Q26: 2339.1093 | R26: 255.46357 | T26: =R26/Q26 -> 0.10921404 | W26: =E26/C26 -> 0.20290323 | X26: =F26/C26 -> 0.24156538
A27: 2020 | B27: 85050 | C27: =D27+E27 -> 12856.722 | D27: 10248.052 | E27: =E26*$D27/$D26 -> 2608.6705 | F27: =Q27+R27 -> 2761.3611 | J27: =C27/$B27 -> 0.15116663 | K27: =D27/$B27 -> 0.12049444 | L27: =E27/$B27 -> 0.030672198 | M27: =F27/$B27 -> 0.032467503 | P27: =AVERAGE(C26:C27)/B27 -> 0.13872656 | Q27: 2587.9467 | R27: 173.41445 | T27: =R27/Q27 -> 0.067008508 | W27: =E27/C27 -> 0.20290323 | X27: =F27/C27 -> 0.21477956
A28: 2021 | B28: 96590 | C28: =D28+E28 -> 14033.606 | D28: 11186.142 | E28: =E27*$D28/$D27 -> 2847.464 | F28: =Q28+R28 -> 3026.4719 | J28: =C28/$B28 -> 0.14529047 | K28: =D28/$B28 -> 0.11581056 | L28: =E28/$B28 -> 0.029479905 | M28: =F28/$B28 -> 0.03133318 | P28: =AVERAGE(C27:C28)/B28 -> 0.1391983 | Q28: 2863.4094 | R28: 163.06251 | T28: =R28/Q28 -> 0.056946979 | W28: =E28/C28 -> 0.20290323 | X28: =F28/C28 -> 0.21565889
A29: 2022 | B29: 101100 | C29: =D29+E29 -> 12387.728 | D29: =D28-0.177*7412 -> 9874.2181 | E29: =E28*$D29/$D28 -> 2513.5101 | F29: =Q29+R29 -> 2655.1 | H29: 12000 | J29: =C29/$B29 -> 0.12252946 | K29: =D29/$B29 -> 0.097667835 | L29: =E29/$B29 -> 0.024861623 | M29: =F29/$B29 -> 0.026262117 | N29: =H29/$B29 -> 0.11869436 | P29: =AVERAGE(C28:C29)/B29 -> 0.13066931 | Q29: 2383.1 | R29: 272 | T29: =R29/Q29 -> 0.11413705
A31: Notes: Stocks are as at December 31st of each year. Source: Portfolio securities from Zucman (2015), file "Global offshore wealth" available at http://gabriel-zucman.eu/files/Zucman2015MissingWealth.xlsx, Table A.3, which updated the Appendix of Zucman (QJE 2013). The series in Zucman (2015) are very close to those in the QJE article, except in 2008 (latest data point in the QJE article) and 2006, where the updated series are about 5% lower. The 2008 decline was due to the availability of updated IIP data; but the 2006 revision is not consistent with the Swiss data (it implies an implausibly high Swiss share of 55%), therefore we correct the 2006 data point. Bank deposits: we use Zucman's (2015) number for end-2013, $1500 billion, and assume that bank deposits follow the total amount of BIS deposits in banking havens.
A34: Notes on BCG: The 2017 global wealth report indicates $10.3T in global offshore wealth in 2016 (exhibit 5). The 2018 report indicates that "global offshore wealth in 2017 was around $8.2 trillion, 6% higher than in the previous year in US dollar terms" (p. 11), implying $7.7 trillion in 2016, 25% less than estimated in the 2017 report. Thus it seems the methodology changed in the 2018 report. The 2018 report writes that offshore wealth is estimated based on "data published by financial centers and by the Bank of (sic) International Settlements, as well as from data generated by BCG project experience." (p. 4). Earlier editions of the report did not mention the BIS. AJZ paper "Who owns the wealth in tax havens?" was released as an NBER working paper in September 2017. Source for BCG reports: https://www.bcg.com/publications/2023/global-wealth-report-resetting-the-course

Sheet T.A2
AS1: Share household deposit
A2: Table A2: Where is the world's offshore wealth located? | P2: BIS liabilities to non-banks
B3: Share of offshore wealth | I3: billion of current US$ | P3: Non-CH havens | Q3: American havens | R3: Asian havens | S3: European havens | U3: AN | V3: AT | W3: BE | X3: BH | Y3: BM | Z3: BS | AA3: CH | AB3: CL | AC3: CW | AD3: CY | AE3: GB | AF3: GG | AG3: HK | AH3: IM | AI3: JE | AJ3: KY | AK3: LU | AL3: MO | AM3: MY | AN3: PA | AO3: SG | AP3: US | AR3: AN | AS3: AT | AT3: BE | AU3: BH | AV3: BM | AW3: BS | AX3: CH | AY3: CL | AZ3: CW | BA3: CY | BB3: GB | BC3: GG | BD3: HK | BE3: IM | BF3: JE | BG3: KY | BH3: LU | BI3: MO | BJ3: MY | BK3: PA | BL3: SG | BM3: US
B4: Total offshore wealth | C4: Switzerland | D4: Tax havens other than Switzerland | E4: Of which: American tax havens | F4: Of which: Asian tax havens | G4: Of which: European tax havens | I4: Total offshore wealth | J4: Switzerland | K4: Tax havens other than Switzerland | L4: Of which: American tax havens | M4: Of which: Asian tax havens | N4: Of which: European tax havens
A5: 2001 | B5: =T.A1!C8/T.A1!$C8 -> 1 | C5: =T.A1!F8/T.A1!$C8 -> 0.38388394 | D5: =1-C5 -> 0.61611606 | E5: =$D5*Q5/$P5 -> 0.098106889 | F5: =$D5*R5/$P5 -> 0.19368153 | G5: =$D5*S5/$P5 -> 0.32432764 | H5: 2001 | I5: =T.A1!C8 -> 3311.5496 | J5: =T.A1!F8 -> 1271.2507 | K5: =I5-J5 -> 2040.2989 | L5: =E5*$I5 -> 324.88583 | M5: =F5*$I5 -> 641.38599 | N5: =G5*$I5 -> 1074.0271 | P5: =Q5+R5+S5 -> 685.88496 | Q5: =AJ5+AN5+AB5+AP5 -> 109.2165 | R5: =X5+Y5+Z5+AG5+AL5+AM5+AO5+U5+AC5 -> 215.614 | S5: =V5+W5+AE5+AF5+AH5+AI5+AK5+AD5 -> 361.05446 | U5: =AR5*bisdepbyhaven!B26/1000 -> 5.369 | V5: =AS5*bisdepbyhaven!C26/1000 -> 2.8488 | W5: =AT5*bisdepbyhaven!D26/1000 -> 33.4125 | X5: =AU5*bisdepbyhaven!E26/1000 -> 16.968 | Y5: =AV5*bisdepbyhaven!F26/1000 -> 0 | Z5: =AW5*bisdepbyhaven!G26/1000 -> 62.7375 | AA5: =AX5*bisdepbyhaven!H26/1000 -> 290.169 | AB5: =AY5*bisdepbyhaven!I26/1000 -> 0 | AC5: =AZ5*bisdepbyhaven!J26/1000 -> 0 | AD5: =AD6*(V5+W5+AE5+AF5+AH5+AI5+AK5)/(V6+W6+AE6+AF6+AH6+AI6+AK6) -> 12.624761 | AE5: =BB5*bisdepbyhaven!L26/1000 -> 46.4094 | AF5: =BC5*bisdepbyhaven!M26/1000 -> 46.278 | AG5: =BD5*bisdepbyhaven!N26/1000 -> 51.3513 | AH5: =BE5*bisdepbyhaven!O26/1000 -> 22.052 | AI5: =BF5*bisdepbyhaven!P26/1000 -> 70.476 | AJ5: =BG5*bisdepbyhaven!Q26/1000 -> 90.8799 | AK5: =BH5*bisdepbyhaven!R26/1000 -> 126.953 | AL5: =BI5*bisdepbyhaven!S26/1000 -> 0 | ... AP5: =BM5*bisdepbyhaven!W26/1000 -> 18.3366 | AR5: 0.7 | AS5: 0.3 | AT5: 0.3 | AU5: 0.7 | AV5: 0.7 | AW5: 0.7 | AX5: 1 | AY5: 0 | AZ5: 0.7 | BA5: 1 | BB5: 0.1 | BC5: 1 | BD5: 0.7 | BE5: 1 | BF5: 1 | BG5: 0.3 | BH5: 1 | BI5: 0.7 | BJ5: 0.7 | BK5: 1 | BL5: 0.7 | BM5: 0.1
A6: 2002 | B6: =T.A1!C9/T.A1!$C9 -> 1 | C6: =T.A1!F9/T.A1!$C9 -> 0.38549383 | D6: =1-C6 -> 0.61450617 | E6: =$D6*Q6/$P6 -> 0.12822556 | F6: =$D6*R6/$P6 -> 0.16095221 | G6: =$D6*S6/$P6 -> 0.32532841 | H6: 2002 | I6: =T.A1!C9 -> 3326.7462 | J6: =T.A1!F9 -> 1282.4401 | K6: =I6-J6 -> 2044.3061 | L6: =E6*$I6 -> 426.57388 | M6: =F6*$I6 -> 535.44714 | N6: =G6*$I6 -> 1082.2851 | P6: =Q6+R6+S6 -> 741.40537 | Q6: =AJ6+AN6+AB6+AP6 -> 154.7049 | R6: =X6+Y6+Z6+AG6+AL6+AM6+AO6+U6+AC6 -> 194.1898 | S6: =V6+W6+AE6+AF6+AH6+AI6+AK6+AD6 -> 392.51067 | U6: =AR6*bisdepbyhaven!B27/1000 -> 6.0984 | V6: =AS6*bisdepbyhaven!C27/1000 -> 4.0722 | W6: =AT6*bisdepbyhaven!D27/1000 -> 43.392 | X6: =AU6*bisdepbyhaven!E27/1000 -> 14.0749 | Y6: =AV6*bisdepbyhaven!F27/1000 -> 1.2432 | Z6: =AW6*bisdepbyhaven!G27/1000 -> 48.0662 | AA6: =AX6*bisdepbyhaven!H27/1000 -> 305.081 | AB6: =AY6*bisdepbyhaven!I27/1000 -> 0 | AC6: =AZ6*bisdepbyhaven!J27/1000 -> 0 | AD6: =AD7*(V6+W6+AE6+AF6+AH6+AI6+AK6)/(V7+W7+AE7+AF7+AH7+AI7+AK7) -> 13.72467 | AE6: =BB6*bisdepbyhaven!L27/1000 -> 55.7498 | AF6: =BC6*bisdepbyhaven!M27/1000 -> 35.534 | AG6: =BD6*bisdepbyhaven!N27/1000 -> 42.6601 | AH6: =BE6*bisdepbyhaven!O27/1000 -> 25.227 | AI6: =BF6*bisdepbyhaven!P27/1000 -> 81.424 | AJ6: =BG6*bisdepbyhaven!Q27/1000 -> 133.6629 | AK6: =BH6*bisdepbyhaven!R27/1000 -> 133.387 | AL6: =BI6*bisdepbyhaven!S27/1000 -> 0 | ... AP6: =BM6*bisdepbyhaven!W27/1000 -> 21.029 | AR6: 0.7 | AS6: 0.3 | AT6: 0.3 | AU6: 0.7 | AV6: 0.7 | AW6: 0.7 | AX6: 1 | AY6: 0 | AZ6: 0.7 | BA6: 1 | BB6: 0.1 | BC6: 1 | BD6: 0.7 | BE6: 1 | BF6: 1 | BG6: 0.3 | BH6: 1 | BI6: 0.7 | BJ6: 0.7 | BK6: 1 | BL6: 0.7 | BM6: 0.1
A7: 2003 | B7: =T.A1!C10/T.A1!$C10 -> 1 | C7: =T.A1!F10/T.A1!$C10 -> 0.43598379 | D7: =1-C7 -> 0.56401621 | E7: =$D7*Q7/$P7 -> 0.11505808 | F7: =$D7*R7/$P7 -> 0.13861401 | G7: =$D7*S7/$P7 -> 0.31034412 | H7: 2003 | I7: =T.A1!C10 -> 3569.3503 | J7: =T.A1!F10 -> 1556.1789 | K7: =I7-J7 -> 2013.1714 | L7: =E7*$I7 -> 410.6826 | M7: =F7*$I7 -> 494.76194 | N7: =G7*$I7 -> 1107.7269 | P7: =Q7+R7+S7 -> 911.65432 | Q7: =AJ7+AN7+AB7+AP7 -> 185.9755 | R7: =X7+Y7+Z7+AG7+AL7+AM7+AO7+U7+AC7 -> 224.0504 | S7: =V7+W7+AE7+AF7+AH7+AI7+AK7+AD7 -> 501.62842 | U7: =AR7*bisdepbyhaven!B28/1000 -> 6.8446 | V7: =AS7*bisdepbyhaven!C28/1000 -> 5.3745 | W7: =AT7*bisdepbyhaven!D28/1000 -> 53.5794 | X7: =AU7*bisdepbyhaven!E28/1000 -> 14.777 | Y7: =AV7*bisdepbyhaven!F28/1000 -> 1.4469 | Z7: =AW7*bisdepbyhaven!G28/1000 -> 60.1426 | AA7: =AX7*bisdepbyhaven!H28/1000 -> 323.752 | AB7: =AY7*bisdepbyhaven!I28/1000 -> 0 | AC7: =AZ7*bisdepbyhaven!J28/1000 -> 0 | AD7: =AD8*(V7+W7+AE7+AF7+AH7+AI7+AK7)/(V8+W8+AE8+AF8+AH8+AI8+AK8) -> 17.54012 | AE7: =BB7*bisdepbyhaven!L28/1000 -> 75.6394 | AF7: =BC7*bisdepbyhaven!M28/1000 -> 43.687 | AG7: =BD7*bisdepbyhaven!N28/1000 -> 50.8753 | AH7: =BE7*bisdepbyhaven!O28/1000 -> 28.919 | AI7: =BF7*bisdepbyhaven!P28/1000 -> 114.642 | AJ7: =BG7*bisdepbyhaven!Q28/1000 -> 138.0483 | AK7: =BH7*bisdepbyhaven!R28/1000 -> 162.247 | AL7: =BI7*bisdepbyhaven!S28/1000 -> 1.4371 | ... AP7: =BM7*bisdepbyhaven!W28/1000 -> 42.9252 | AR7: 0.7 | AS7: 0.3 | AT7: 0.3 | AU7: 0.7 | AV7: 0.7 | AW7: 0.7 | AX7: 1 | AY7: 0 | AZ7: 0.7 | BA7: 1 | BB7: 0.1 | BC7: 1 | BD7: 0.7 | BE7: 1 | BF7: 1 | BG7: 0.3 | BH7: 1 | BI7: 0.7 | BJ7: 0.7 | BK7: 1 | BL7: 0.7 | BM7: 0.1
A8: 2004 | B8: =T.A1!C11/T.A1!$C11 -> 1 | C8: =T.A1!F11/T.A1!$C11 -> 0.42652904 | D8: =1-C8 -> 0.57347096 | E8: =$D8*Q8/$P8 -> 0.12259008 | F8: =$D8*R8/$P8 -> 0.13626942 | G8: =$D8*S8/$P8 -> 0.31461146 | H8: 2004 | I8: =T.A1!C11 -> 4266.8114 | J8: =T.A1!F11 -> 1819.919 | K8: =I8-J8 -> 2446.8924 | L8: =E8*$I8 -> 523.06875 | M8: =F8*$I8 -> 581.43592 | N8: =G8*$I8 -> 1342.3877 | P8: =Q8+R8+S8 -> 1004.1381 | Q8: =AJ8+AN8+AB8+AP8 -> 214.6532 | R8: =X8+Y8+Z8+AG8+AL8+AM8+AO8+U8+AC8 -> 238.6055 | S8: =V8+W8+AE8+AF8+AH8+AI8+AK8+AD8 -> 550.87945 | U8: =AR8*bisdepbyhaven!B29/1000 -> 7.8841 | V8: =AS8*bisdepbyhaven!C29/1000 -> 6.078 | W8: =AT8*bisdepbyhaven!D29/1000 -> 65.0436 | X8: =AU8*bisdepbyhaven!E29/1000 -> 18.2238 | Y8: =AV8*bisdepbyhaven!F29/1000 -> 1.841 | Z8: =AW8*bisdepbyhaven!G29/1000 -> 62.1999 | AA8: =AX8*bisdepbyhaven!H29/1000 -> 354.136 | AB8: =AY8*bisdepbyhaven!I29/1000 -> 0 | AC8: =AZ8*bisdepbyhaven!J29/1000 -> 0 | AD8: =AD9*(V8+W8+AE8+AF8+AH8+AI8+AK8)/(V9+W9+AE9+AF9+AH9+AI9+AK9) -> 19.26225 | AE8: =BB8*bisdepbyhaven!L29/1000 -> 96.7606 | AF8: =BC8*bisdepbyhaven!M29/1000 -> 48.533 | AG8: =BD8*bisdepbyhaven!N29/1000 -> 59.5882 | AH8: =BE8*bisdepbyhaven!O29/1000 -> 33.334 | AI8: =BF8*bisdepbyhaven!P29/1000 -> 103.779 | AJ8: =BG8*bisdepbyhaven!Q29/1000 -> 145.9701 | AK8: =BH8*bisdepbyhaven!R29/1000 -> 178.089 | AL8: =BI8*bisdepbyhaven!S29/1000 -> 1.6443 | ... AP8: =BM8*bisdepbyhaven!W29/1000 -> 62.7821 | AR8: 0.7 | AS8: 0.3 | AT8: 0.3 | AU8: 0.7 | AV8: 0.7 | AW8: 0.7 | AX8: 1 | AY8: 0 | AZ8: 0.7 | BA8: 1 | BB8: 0.1 | BC8: 1 | BD8: 0.7 | BE8: 1 | BF8: 1 | BG8: 0.3 | BH8: 1 | BI8: 0.7 | BJ8: 0.7 | BK8: 1 | BL8: 0.7 | BM8: 0.1
A9: 2005 | B9: =T.A1!C12/T.A1!$C12 -> 1 | C9: =T.A1!F12/T.A1!$C12 -> 0.4422203 | D9: =1-C9 -> 0.5577797 | E9: =$D9*Q9/$P9 -> 0.10903351 | F9: =$D9*R9/$P9 -> 0.14660505 | G9: =$D9*S9/$P9 -> 0.30214114 | H9: 2005 | I9: =T.A1!C12 -> 4566.7319 | J9: =T.A1!F12 -> 2019.5016 | K9: =I9-J9 -> 2547.2304 | L9: =E9*$I9 -> 497.92682 | M9: =F9*$I9 -> 669.50597 | N9: =G9*$I9 -> 1379.7976 | P9: =Q9+R9+S9 -> 1068.8578 | Q9: =AJ9+AN9+AB9+AP9 -> 208.9379 | R9: =X9+Y9+Z9+AG9+AL9+AM9+AO9+U9+AC9 -> 280.9352 | S9: =V9+W9+AE9+AF9+AH9+AI9+AK9+AD9 -> 578.98469 | U9: =AR9*bisdepbyhaven!B30/1000 -> 7.9989 | V9: =AS9*bisdepbyhaven!C30/1000 -> 12.0786 | W9: =AT9*bisdepbyhaven!D30/1000 -> 69.8061 | X9: =AU9*bisdepbyhaven!E30/1000 -> 23.6726 | Y9: =AV9*bisdepbyhaven!F30/1000 -> 2.0244 | Z9: =AW9*bisdepbyhaven!G30/1000 -> 78.9026 | AA9: =AX9*bisdepbyhaven!H30/1000 -> 355.416 | AB9: =AY9*bisdepbyhaven!I30/1000 -> 0 | AC9: =AZ9*bisdepbyhaven!J30/1000 -> 0 | AD9: =AD10*(V9+W9+AE9+AF9+AH9+AI9+AK9)/(V10+W10+AE10+AF10+AH10+AI10+AK10) -> 20.244988 | AE9: =BB9*bisdepbyhaven!L30/1000 -> 102.784 | AF9: =BC9*bisdepbyhaven!M30/1000 -> 50.342 | AG9: =BD9*bisdepbyhaven!N30/1000 -> 67.2504 | AH9: =BE9*bisdepbyhaven!O30/1000 -> 40.409 | AI9: =BF9*bisdepbyhaven!P30/1000 -> 129.167 | AJ9: =BG9*bisdepbyhaven!Q30/1000 -> 143.0043 | AK9: =BH9*bisdepbyhaven!R30/1000 -> 154.153 | AL9: =BI9*bisdepbyhaven!S30/1000 -> 3.9613 | ... AP9: =BM9*bisdepbyhaven!W30/1000 -> 59.5646 | AR9: 0.7 | AS9: 0.3 | AT9: 0.3 | AU9: 0.7 | AV9: 0.7 | AW9: 0.7 | AX9: 1 | AY9: 0 | AZ9: 0.7 | BA9: 1 | BB9: 0.1 | BC9: 1 | BD9: 0.7 | BE9: 1 | BF9: 1 | BG9: 0.3 | BH9: 1 | BI9: 0.7 | BJ9: 0.7 | BK9: 1 | BL9: 0.7 | BM9: 0.1
A10: 2006 | B10: =T.A1!C13/T.A1!$C13 -> 1 | C10: =T.A1!F13/T.A1!$C13 -> 0.47938831 | D10: =1-C10 -> 0.52061169 | E10: =$D10*Q10/$P10 -> 0.10650635 | F10: =$D10*R10/$P10 -> 0.13786515 | G10: =$D10*S10/$P10 -> 0.27624019 | H10: 2006 | I10: =T.A1!C13 -> 5052.61 | J10: =T.A1!F13 -> 2422.1622 | K10: =I10-J10 -> 2630.4479 | L10: =E10*$I10 -> 538.13506 | M10: =F10*$I10 -> 696.57885 | N10: =G10*$I10 -> 1395.734 | P10: =Q10+R10+S10 -> 1329.299 | Q10: =AJ10+AN10+AB10+AP10 -> 271.947 | R10: =X10+Y10+Z10+AG10+AL10+AM10+AO10+U10+AC10 -> 352.0167 | S10: =V10+W10+AE10+AF10+AH10+AI10+AK10+AD10 -> 705.33531 | U10: =AR10*bisdepbyhaven!B31/1000 -> 7.0784 | V10: =AS10*bisdepbyhaven!C31/1000 -> 15.7653 | W10: =AT10*bisdepbyhaven!D31/1000 -> 72.528 | X10: =AU10*bisdepbyhaven!E31/1000 -> 36.4105 | Y10: =AV10*bisdepbyhaven!F31/1000 -> 1.8382 | Z10: =AW10*bisdepbyhaven!G31/1000 -> 99.6772 | AA10: =AX10*bisdepbyhaven!H31/1000 -> 443.017 | AB10: =AY10*bisdepbyhaven!I31/1000 -> 0 | AC10: =AZ10*bisdepbyhaven!J31/1000 -> 0 | AD10: =AD11*(V10+W10+AE10+AF10+AH10+AI10+AK10)/(V11+W11+AE11+AF11+AH11+AI11+AK11) -> 24.663009 | AE10: =BB10*bisdepbyhaven!L31/1000 -> 125.996 | AF10: =BC10*bisdepbyhaven!M31/1000 -> 57.573 | AG10: =BD10*bisdepbyhaven!N31/1000 -> 82.3326 | AH10: =BE10*bisdepbyhaven!O31/1000 -> 47.213 | AI10: =BF10*bisdepbyhaven!P31/1000 -> 161.061 | AJ10: =BG10*bisdepbyhaven!Q31/1000 -> 174.1125 | AK10: =BH10*bisdepbyhaven!R31/1000 -> 200.536 | AL10: =BI10*bisdepbyhaven!S31/1000 -> 5.0281 | ... AP10: =BM10*bisdepbyhaven!W31/1000 -> 90.0635 | AR10: 0.7 | AS10: 0.3 | AT10: 0.3 | AU10: 0.7 | AV10: 0.7 | AW10: 0.7 | AX10: 1 | AY10: 0 | AZ10: 0.7 | BA10: 1 | BB10: 0.1 | BC10: 1 | BD10: 0.7 | BE10: 1 | BF10: 1 | BG10: 0.3 | BH10: 1 | BI10: 0.7 | BJ10: 0.7 | BK10: 1 | BL10: 0.7 | BM10: 0.1
A11: 2007 | B11: =T.A1!C14/T.A1!$C14 -> 1 | C11: =T.A1!F14/T.A1!$C14 -> 0.42850784 | D11: =1-C11 -> 0.57149216 | E11: =$D11*Q11/$P11 -> 0.11839624 | F11: =$D11*R11/$P11 -> 0.15765433 | G11: =$D11*S11/$P11 -> 0.29544159 | H11: 2007 | I11: =T.A1!C14 -> 6795.0723 | J11: =T.A1!F14 -> 2911.7417 | K11: =I11-J11 -> 3883.3306 | L11: =E11*$I11 -> 804.51101 | M11: =F11*$I11 -> 1071.2726 | N11: =G11*$I11 -> 2007.547 | P11: =Q11+R11+S11 -> 1684.825 | Q11: =AJ11+AN11+AB11+AP11 -> 349.0458 | R11: =X11+Y11+Z11+AG11+AL11+AM11+AO11+U11+AC11 -> 464.7832 | S11: =V11+W11+AE11+AF11+AH11+AI11+AK11+AD11 -> 870.99596 | U11: =AR11*bisdepbyhaven!B32/1000 -> 8.5862 | V11: =AS11*bisdepbyhaven!C32/1000 -> 19.4778 | W11: =AT11*bisdepbyhaven!D32/1000 -> 97.3302 | X11: =AU11*bisdepbyhaven!E32/1000 -> 45.591 | Y11: =AV11*bisdepbyhaven!F32/1000 -> 1.4553 | Z11: =AW11*bisdepbyhaven!G32/1000 -> 119.6041 | AA11: =AX11*bisdepbyhaven!H32/1000 -> 547.651 | AB11: =AY11*bisdepbyhaven!I32/1000 -> 0 | AC11: =AZ11*bisdepbyhaven!J32/1000 -> 0 | AD11: =AD12*(V11+W11+AE11+AF11+AH11+AI11+AK11)/(V12+W12+AE12+AF12+AH12+AI12+AK12) -> 30.455559 | AE11: =BB11*bisdepbyhaven!L32/1000 -> 168.6244 | AF11: =BC11*bisdepbyhaven!M32/1000 -> 69.15 | AG11: =BD11*bisdepbyhaven!N32/1000 -> 113.1438 | AH11: =BE11*bisdepbyhaven!O32/1000 -> 57.917 | AI11: =BF11*bisdepbyhaven!P32/1000 -> 220.415 | AJ11: =BG11*bisdepbyhaven!Q32/1000 -> 231.1692 | AK11: =BH11*bisdepbyhaven!R32/1000 -> 207.626 | AL11: =BI11*bisdepbyhaven!S32/1000 -> 6.6045 | ... AP11: =BM11*bisdepbyhaven!W32/1000 -> 107.7556 | AR11: 0.7 | AS11: 0.3 | AT11: 0.3 | AU11: 0.7 | AV11: 0.7 | AW11: 0.7 | AX11: 1 | AY11: 0 | AZ11: 0.7 | BA11: 1 | BB11: 0.1 | BC11: 1 | BD11: 0.7 | BE11: 1 | BF11: 1 | BG11: 0.3 | BH11: 1 | BI11: 0.7 | BJ11: 0.7 | BK11: 1 | BL11: 0.7 | BM11: 0.1
A12: 2008 | B12: =T.A1!C15/T.A1!$C15 -> 1 | C12: =T.A1!F15/T.A1!$C15 -> 0.37833746 | D12: =1-C12 -> 0.62166254 | E12: =$D12*Q12/$P12 -> 0.16097127 | F12: =$D12*R12/$P12 -> 0.18710504 | G12: =$D12*S12/$P12 -> 0.27358623 | H12: 2008 | I12: =T.A1!C15 -> 5644.1316 | J12: =T.A1!F15 -> 2135.3864 | K12: =I12-J12 -> 3508.7452 | L12: =E12*$I12 -> 908.54305 | M12: =F12*$I12 -> 1056.0455 | N12: =G12*$I12 -> 1544.1567 | P12: =Q12+R12+S12 -> 1515.8293 | Q12: =AJ12+AN12+AB12+AP12 -> 392.5039 | R12: =X12+Y12+Z12+AG12+AL12+AM12+AO12+U12+AC12 -> 456.2271 | S12: =V12+W12+AE12+AF12+AH12+AI12+AK12+AD12 -> 667.0983 | U12: =AR12*bisdepbyhaven!B33/1000 -> 8.0871 | V12: =AS12*bisdepbyhaven!C33/1000 -> 12.9142 | W12: =AT12*bisdepbyhaven!D33/1000 -> 70.9866 | X12: =AU12*bisdepbyhaven!E33/1000 -> 43.0899 | Y12: =AV12*bisdepbyhaven!F33/1000 -> 1.1396 | Z12: =AW12*bisdepbyhaven!G33/1000 -> 125.8656 | AA12: =AX12*bisdepbyhaven!H33/1000 -> 509.691 | AB12: =AY12*bisdepbyhaven!I33/1000 -> 0 | ... AP12: =BM12*bisdepbyhaven!W33/1000 -> 100.4023 | AR12: 0.7 | AS12: 0.2 | AT12: 0.2 | AU12: 0.7 | AV12: 0.7 | AW12: 0.7 | AX12: 1 | AY12: 0 | AZ12: 0.7 | BA12: 1 | BB12: 0.1 | BC12: 1 | BD12: 0.7 | BE12: 1 | BF12: 1 | BG12: 0.3 | BH12: 1 | BI12: 0.7 | BJ12: 0.7 | BK12: 1 | BL12: 0.7 | BM12: 0.1
A13: 2009 | B13: =T.A1!C16/T.A1!$C16 -> 1 | C13: =T.A1!F16/T.A1!$C16 -> 0.37406636 | D13: =1-C13 -> 0.62593364 | E13: =$D13*Q13/$P13 -> 0.15787685 | F13: =$D13*R13/$P13 -> 0.20113498 | G13: =$D13*S13/$P13 -> 0.26692181 | H13: 2009 | I13: =T.A1!C16 -> 6305.3213 | J13: =T.A1!F16 -> 2358.6086 | K13: =I13-J13 -> 3946.7127 | L13: =E13*$I13 -> 995.46424 | M13: =F13*$I13 -> 1268.2207 | N13: =G13*$I13 -> 1683.0277 | P13: =Q13+R13+S13 -> 1397.0093 | Q13: =AJ13+AN13+AB13+AP13 -> 352.3623 | R13: =X13+Y13+Z13+AG13+AL13+AM13+AO13+U13+AC13 -> 448.9093 | S13: =V13+W13+AE13+AF13+AH13+AI13+AK13+AD13 -> 595.73765 | U13: =AR13*bisdepbyhaven!B34/1000 -> 8.1851 | V13: =AS13*bisdepbyhaven!C34/1000 -> 9.98745 | W13: =AT13*bisdepbyhaven!D34/1000 -> 47.8659 | X13: =AU13*bisdepbyhaven!E34/1000 -> 40.7064 | Y13: =AV13*bisdepbyhaven!F34/1000 -> 1.2488 | Z13: =AW13*bisdepbyhaven!G34/1000 -> 100.9134 | AA13: =AX13*bisdepbyhaven!H34/1000 -> 482.995 | AB13: =AY13*bisdepbyhaven!I34/1000 -> 0 | ... AP13: =BM13*bisdepbyhaven!W34/1000 -> 86.0459 | AR13: 0.7 | AS13: 0.15 | AT13: 0.15 | AU13: 0.7 | AV13: 0.7 | AW13: 0.7 | AX13: 1 | AY13: 0 | AZ13: 0.7 | BA13: 1 | BB13: 0.1 | BC13: 0.95 | BD13: 0.7 | BE13: =BE12-0.05 -> 0.95 | BF13: =BF12-0.05 -> 0.95 | BG13: 0.3 | BH13: 1 | BI13: 0.7 | BJ13: 0.7 | BK13: 1 | BL13: 0.7 | BM13: 0.1
A14: 2010 | B14: =T.A1!C17/T.A1!$C17 -> 1 | C14: =T.A1!F17/T.A1!$C17 -> 0.39372224 | D14: =1-C14 -> 0.60627776 | E14: =$D14*Q14/$P14 -> 0.16436941 | F14: =$D14*R14/$P14 -> 0.20557825 | G14: =$D14*S14/$P14 -> 0.23633009 | H14: 2010 | I14: =T.A1!C17 -> 5844.8574 | J14: =T.A1!F17 -> 2301.2504 | K14: =I14-J14 -> 3543.607 | L14: =E14*$I14 -> 960.71579 | M14: =F14*$I14 -> 1201.5756 | N14: =G14*$I14 -> 1381.3157 | P14: =Q14+R14+S14 -> 1388.1313 | Q14: =AJ14+AN14+AB14+AP14 -> 376.3396 | R14: =X14+Y14+Z14+AG14+AL14+AM14+AO14+U14+AC14 -> 470.6912 | S14: =V14+W14+AE14+AF14+AH14+AI14+AK14+AD14 -> 541.1005 | U14: =AR14*bisdepbyhaven!B35/1000 -> 0 | V14: =AS14*bisdepbyhaven!C35/1000 -> 6.2575 | W14: =AT14*bisdepbyhaven!D35/1000 -> 28.9305 | X14: =AU14*bisdepbyhaven!E35/1000 -> 44.9421 | Y14: =AV14*bisdepbyhaven!F35/1000 -> 1.3398 | Z14: =AW14*bisdepbyhaven!G35/1000 -> 107.4283 | AA14: =AX14*bisdepbyhaven!H35/1000 -> 457.894 | AB14: =AY14*bisdepbyhaven!I35/1000 -> 0 | ... AP14: =BM14*bisdepbyhaven!W35/1000 -> 88.5824 | AR14: 0.7 | AS14: 0.1 | AT14: 0.1 | AU14: 0.7 | AV14: 0.7 | AW14: 0.7 | AX14: 1 | AY14: 0 | AZ14: 0.7 | BA14: 1 | BB14: 0.1 | BC14: 0.9 | BD14: 0.7 | BE14: =BE13-0.05 -> 0.9 | BF14: =BF13-0.05 -> 0.9 | BG14: 0.3 | BH14: 1 | BI14: 0.7 | BJ14: 0.7 | BK14: 1 | BL14: 0.7 | BM14: 0.1
A15: 2011 | B15: =T.A1!C18/T.A1!$C18 -> 1 | C15: =T.A1!F18/T.A1!$C18 -> 0.34308605 | D15: =1-C15 -> 0.65691395 | E15: =$D15*Q15/$P15 -> 0.15925788 | F15: =$D15*R15/$P15 -> 0.2444979 | G15: =$D15*S15/$P15 -> 0.25315818 | H15: 2011 | I15: =T.A1!C18 -> 6563.066 | J15: =T.A1!F18 -> 2251.6964 | K15: =I15-J15 -> 4311.3696 | L15: =E15*$I15 -> 1045.22 | M15: =F15*$I15 -> 1604.6558 | N15: =G15*$I15 -> 1661.4938 | P15: =Q15+R15+S15 -> 1293.2856 | Q15: =AJ15+AN15+AB15+AP15 -> 313.5356 | R15: =X15+Y15+Z15+AG15+AL15+AM15+AO15+U15+AC15 -> 481.3501 | S15: =V15+W15+AE15+AF15+AH15+AI15+AK15+AD15 -> 498.39985 | U15: =AR15*bisdepbyhaven!B36/1000 -> 0 | V15: =AS15*bisdepbyhaven!C36/1000 -> 3.5673 | W15: =AT15*bisdepbyhaven!D36/1000 -> 15.80405 | X15: =AU15*bisdepbyhaven!E36/1000 -> 37.3527 | Y15: =AV15*bisdepbyhaven!F36/1000 -> 1.8403 | Z15: =AW15*bisdepbyhaven!G36/1000 -> 94.6337 | AA15: =AX15*bisdepbyhaven!H36/1000 -> 462.85 | AB15: =AY15*bisdepbyhaven!I36/1000 -> 0 | ... AP15: =BM15*bisdepbyhaven!W36/1000 -> 99.7919 | AR15: 0.7 | AS15: 0.05 | AT15: 0.05 | AU15: 0.7 | AV15: 0.7 | AW15: 0.7 | AX15: 1 | AY15: 0 | AZ15: 0.7 | BA15: 1 | BB15: 0.1 | BC15: 0.85 | BD15: 0.7 | BE15: =BE14-0.05 -> 0.85 | BF15: =BF14-0.05 -> 0.85 | BG15: 0.3 | BH15: 1 | BI15: 0.7 | BJ15: 0.7 | BK15: 1 | BL15: 0.7 | BM15: 0.1
A16: 2012 | B16: =T.A1!C19/T.A1!$C19 -> 1 | C16: =T.A1!F19/T.A1!$C19 -> 0.28830679 | D16: =1-C16 -> 0.71169321 | E16: =$D16*Q16/$P16 -> 0.15702695 | F16: =$D16*R16/$P16 -> 0.26696813 | G16: =$D16*S16/$P16 -> 0.28769813 | H16: 2012 | I16: =T.A1!C19 -> 8219.9757 | J16: =T.A1!F19 -> 2369.8748 | K16: =I16-J16 -> 5850.1009 | L16: =E16*$I16 -> 1290.7577 | M16: =F16*$I16 -> 2194.4715 | N16: =G16*$I16 -> 2364.8717 | P16: =Q16+R16+S16 -> 1298.3847 | Q16: =AJ16+AN16+AB16+AP16 -> 286.4737 | R16: =X16+Y16+Z16+AG16+AL16+AM16+AO16+U16+AC16 -> 487.046 | S16: =V16+W16+AE16+AF16+AH16+AI16+AK16+AD16 -> 524.865 | U16: =AR16*bisdepbyhaven!B37/1000 -> 0 | V16: =AS16*bisdepbyhaven!C37/1000 -> 3.3664132 | W16: =AT16*bisdepbyhaven!D37/1000 -> 14.77225 | X16: =AU16*bisdepbyhaven!E37/1000 -> 38.7485 | Y16: =AV16*bisdepbyhaven!F37/1000 -> 1.4707 | Z16: =AW16*bisdepbyhaven!G37/1000 -> 86.499 | AA16: =AX16*bisdepbyhaven!H37/1000 -> 478.287 | AB16: =AY16*bisdepbyhaven!I37/1000 -> 0 | ... AP16: =BM16*bisdepbyhaven!W37/1000 -> 101.3683 | AR16: 0.7 | AS16: 0.05 | AT16: 0.05 | AU16: 0.7 | AV16: 0.7 | AW16: 0.7 | AX16: 1 | AY16: 0 | AZ16: 0.7 | BA16: 1 | BB16: 0.1 | BC16: 0.8 | BD16: 0.7 | BE16: =BE15-0.05 -> 0.8 | BF16: =BF15-0.05 -> 0.8 | BG16: 0.3 | BH16: 1 | BI16: 0.7 | BJ16: 0.7 | BK16: 1 | BL16: 0.7 | BM16: 0.1
A17: 2013 | B17: =T.A1!C20/T.A1!$C20 -> 1 | C17: =T.A1!F20/T.A1!$C20 -> 0.28592928 | D17: =1-C17 -> 0.71407072 | E17: =$D17*Q17/$P17 -> 0.16774675 | F17: =$D17*R17/$P17 -> 0.28725154 | G17: =$D17*S17/$P17 -> 0.25907243 | H17: 2013 | I17: =T.A1!C20 -> 8475.8163 | J17: =T.A1!F20 -> 2423.484 | K17: =I17-J17 -> 6052.3322 | L17: =E17*$I17 -> 1421.7906 | M17: =F17*$I17 -> 2434.6913 | N17: =G17*$I17 -> 2195.8503 | P17: =Q17+R17+S17 -> 1345.7865 | Q17: =AJ17+AN17+AB17+AP17 -> 316.147 | R17: =X17+Y17+Z17+AG17+AL17+AM17+AO17+U17+AC17 -> 541.3739 | S17: =V17+W17+AE17+AF17+AH17+AI17+AK17+AD17 -> 488.26562 | U17: =AR17*bisdepbyhaven!B38/1000 -> 0 | V17: =AS17*bisdepbyhaven!C38/1000 -> 3.5344301 | W17: =AT17*bisdepbyhaven!D38/1000 -> 12.139987 | X17: =AU17*bisdepbyhaven!E38/1000 -> 41.7767 | Y17: =AV17*bisdepbyhaven!F38/1000 -> 1.68 | Z17: =AW17*bisdepbyhaven!G38/1000 -> 85.7178 | AA17: =AX17*bisdepbyhaven!H38/1000 -> 517.49461 | AB17: =AY17*bisdepbyhaven!I38/1000 -> 0 | ... AP17: =BM17*bisdepbyhaven!W38/1000 -> 120.5587 | AR17: 0.7 | AS17: 0.05 | AT17: 0.05 | AU17: 0.7 | AV17: 0.7 | AW17: 0.7 | AX17: 1 | AY17: 0 | AZ17: 0.7 | BA17: 1 | BB17: 0.1 | BC17: 0.75 | BD17: 0.7 | BE17: =BE16-0.05 -> 0.75 | BF17: =BF16-0.05 -> 0.75 | BG17: 0.3 | BH17: 1 | BI17: 0.7 | BJ17: 0.7 | BK17: 1 | BL17: 0.7 | BM17: 0.1
A18: 2014 | B18: =T.A1!C21/T.A1!$C21 -> 1 | C18: =T.A1!F21/T.A1!$C21 -> 0.24590982 | D18: =1-C18 -> 0.75409018 | E18: =$D18*Q18/$P18 -> 0.18225754 | F18: =$D18*R18/$P18 -> 0.32415016 | G18: =$D18*S18/$P18 -> 0.24768247 | H18: 2014 | I18: =T.A1!C21 -> 9523.3891 | J18: =T.A1!F21 -> 2341.8949 | K18: =I18-J18 -> 7181.4942 | L18: =E18*$I18 -> 1735.7095 | M18: =F18*$I18 -> 3087.0081 | N18: =G18*$I18 -> 2358.7766 | P18: =Q18+R18+S18 -> 1309.6533 | Q18: =AJ18+AN18+AB18+AP18 -> 316.5327 | R18: =X18+Y18+Z18+AG18+AL18+AM18+AO18+U18+AC18 -> 562.9623 | S18: =V18+W18+AE18+AF18+AH18+AI18+AK18+AD18 -> 430.15834 | U18: =AR18*bisdepbyhaven!B39/1000 -> 0 | V18: =AS18*bisdepbyhaven!C39/1000 -> 3.1057203 | W18: =AT18*bisdepbyhaven!D39/1000 -> 12.747183 | X18: =AU18*bisdepbyhaven!E39/1000 -> 40.5503 | Y18: =AV18*bisdepbyhaven!F39/1000 -> 1.6028537 | Z18: =AW18*bisdepbyhaven!G39/1000 -> 57.8872 | AA18: =AX18*bisdepbyhaven!H39/1000 -> 484.68843 | AB18: =AY18*bisdepbyhaven!I39/1000 -> 0 | ... AP18: =BM18*bisdepbyhaven!W39/1000 -> 132.4104 | AR18: 0.7 | AS18: 0.05 | AT18: 0.05 | AU18: 0.7 | AV18: 0.7 | AW18: 0.7 | AX18: 1 | AY18: 0 | AZ18: 0.7 | BA18: 1 | BB18: 0.1 | BC18: 0.7 | BD18: 0.7 | BE18: =BE17-0.05 -> 0.7 | BF18: =BF17-0.05 -> 0.7 | BG18: 0.3 | BH18: 1 | BI18: 0.7 | BJ18: 0.7 | BK18: 1 | BL18: 0.7 | BM18: 0.1
A19: 2015 | B19: =T.A1!C22/T.A1!$C22 -> 1 | C19: =T.A1!F22/T.A1!$C22 -> 0.2327847 | D19: =1-C19 -> 0.7672153 | E19: =$D19*Q19/$P19 -> 0.17471822 | F19: =$D19*R19/$P19 -> 0.35056471 | G19: =$D19*S19/$P19 -> 0.24193237 | H19: 2015 | I19: =T.A1!C22 -> 9523.3891 | J19: =T.A1!F22 -> 2216.8993 | K19: =I19-J19 -> 7306.4898 | L19: =E19*$I19 -> 1663.9096 | M19: =F19*$I19 -> 3338.5641 | N19: =G19*$I19 -> 2304.0161 | P19: =Q19+R19+S19 -> 1220.2527 | Q19: =AJ19+AN19+AB19+AP19 -> 277.8886 | R19: =X19+Y19+Z19+AG19+AL19+AM19+AO19+U19+AC19 -> 557.57169 | S19: =V19+W19+AE19+AF19+AH19+AI19+AK19+AD19 -> 384.79241 | U19: =AR19*bisdepbyhaven!B40/1000 -> 0 | V19: =AS19*bisdepbyhaven!C40/1000 -> 2.5159079 | W19: =AT19*bisdepbyhaven!D40/1000 -> 10.102155 | X19: =AU19*bisdepbyhaven!E40/1000 -> 41.0592 | Y19: =AV19*bisdepbyhaven!F40/1000 -> 1.7873135 | Z19: =AW19*bisdepbyhaven!G40/1000 -> 42.813497 | AA19: =AX19*bisdepbyhaven!H40/1000 -> 459.14778 | AB19: =AY19*bisdepbyhaven!I40/1000 -> 0 | ... AP19: =BM19*bisdepbyhaven!W40/1000 -> 124.0718 | AR19: 0.7 | AS19: 0.05 | AT19: 0.05 | AU19: 0.7 | AV19: 0.7 | AW19: 0.7 | AX19: 1 | AY19: 0 | AZ19: 0.7 | BA19: 1 | BB19: 0.1 | BC19: 0.65 | BD19: 0.7 | BE19: =BE18-0.05 -> 0.65 | BF19: =BF18-0.05 -> 0.65 | BG19: 0.3 | BH19: 1 | BI19: 0.7 | BJ19: 0.7 | BK19: 1 | BL19: 0.7 | BM19: 0.1
A20: 2016 | B20: =T.A1!C23/T.A1!$C23 -> 1 | C20: =T.A1!F23/T.A1!$C23 -> 0.26929655 | D20: =1-C20 -> 0.73070345 | E20: =$D20*Q20/$P20 -> 0.16058325 | F20: =$D20*R20/$P20 -> 0.34553954 | G20: =$D20*S20/$P20 -> 0.22458067 | H20: 2016 | I20: =T.A1!C23 -> 7905.564 | J20: =T.A1!F23 -> 2128.9411 | K20: =I20-J20 -> 5776.6229 | L20: =E20*$I20 -> 1269.5011 | M20: =F20*$I20 -> 2731.685 | N20: =G20*$I20 -> 1775.4368 | P20: =Q20+R20+S20 -> 1182.8866 | Q20: =AJ20+AN20+AB20+AP20 -> 259.9574 | R20: =X20+Y20+Z20+AG20+AL20+AM20+AO20+U20+AC20 -> 559.37069 | S20: =V20+W20+AE20+AF20+AH20+AI20+AK20+AD20 -> 363.55852 | U20: =AR20*bisdepbyhaven!B41/1000 -> 0 | V20: =AS20*bisdepbyhaven!C41/1000 -> 3.5439351 | W20: =AT20*bisdepbyhaven!D41/1000 -> 8.3067271 | X20: =AU20*bisdepbyhaven!E41/1000 -> 38.71 | Y20: =AV20*bisdepbyhaven!F41/1000 -> 1.5422512 | Z20: =AW20*bisdepbyhaven!G41/1000 -> 31.416636 | AA20: =AX20*bisdepbyhaven!H41/1000 -> 439.54459 | AB20: =AY20*bisdepbyhaven!I41/1000 -> 0 | ... AP20: =BM20*bisdepbyhaven!W41/1000 -> 138.6039 | AR20: 0.7 | AS20: 0.05 | AT20: 0.05 | AU20: 0.7 | AV20: 0.7 | AW20: 0.7 | AX20: 1 | AY20: 0 | AZ20: 0.7 | BA20: 1 | BB20: 0.1 | BC20: 0.65 | BD20: 0.7 | BE20: 0.65 | BF20: 0.65 | BG20: 0.3 | BH20: 0.9 | BI20: 0.5 | BJ20: 0.5 | BK20: 1 | BL20: 0.7 | BM20: 0.1
A21: 2017 | B21: =T.A1!C24/T.A1!$C24 -> 1 | C21: =T.A1!F24/T.A1!$C24 -> 0.25923151 | D21: =1-C21 -> 0.74076849 | E21: =$D21*Q21/$P21 -> 0.14503237 | F21: =$D21*R21/$P21 -> 0.35648831 | G21: =$D21*S21/$P21 -> 0.23924781 | H21: 2017 | I21: =T.A1!C24 -> 9429.1896 | J21: =T.A1!F24 -> 2444.343 | K21: =I21-J21 -> 6984.8465 | L21: =E21*$I21 -> 1367.5377 | M21: =F21*$I21 -> 3361.3958 | N21: =G21*$I21 -> 2255.913 | P21: =Q21+R21+S21 -> 1230.8761 | Q21: =AJ21+AN21+AB21+AP21 -> 240.98876 | R21: =X21+Y21+Z21+AG21+AL21+AM21+AO21+U21+AC21 -> 592.34827 | S21: =V21+W21+AE21+AF21+AH21+AI21+AK21+AD21 -> 397.53906 | U21: =AR21*bisdepbyhaven!B42/1000 -> 0 | V21: =AS21*bisdepbyhaven!C42/1000 -> 3.6098005 | W21: =AT21*bisdepbyhaven!D42/1000 -> 5.1572729 | X21: =AU21*bisdepbyhaven!E42/1000 -> 38.0058 | Y21: =AV21*bisdepbyhaven!F42/1000 -> 1.1317635 | Z21: =AW21*bisdepbyhaven!G42/1000 -> 24.74946 | AA21: =AX21*bisdepbyhaven!H42/1000 -> 453.83133 | AB21: =AY21*bisdepbyhaven!I42/1000 -> 0 | ... AP21: =BM21*bisdepbyhaven!W42/1000 -> 139.4132 | AR21: 0.7 | AS21: 0.05 | AT21: 0.05 | AU21: 0.7 | AV21: 0.7 | AW21: 0.7 | AX21: 1 | AY21: 0 | AZ21: 0.7 | BA21: 1 | BB21: 0.1 | BC21: 0.65 | BD21: 0.7 | BE21: 0.65 | BF21: 0.65 | BG21: 0.3 | BH21: 0.8 | BI21: 0.5 | BJ21: 0.5 | BK21: 1 | BL21: 0.7 | BM21: 0.1
A22: 2018 | B22: =T.A1!C25/T.A1!$C25 -> 1 | C22: =T.A1!F25/T.A1!$C25 -> 0.26028104 | D22: =1-C22 -> 0.73971896 | E22: =$D22*Q22/$P22 -> 0.13606096 | F22: =$D22*R22/$P22 -> 0.3758178 | G22: =$D22*S22/$P22 -> 0.2278402 | H22: 2018 | I22: =T.A1!C25 -> 8765.7848 | J22: =T.A1!F25 -> 2281.5676 | K22: =I22-J22 -> 6484.2172 | L22: =E22*$I22 -> 1192.6811 | M22: =F22*$I22 -> 3294.3379 | N22: =G22*$I22 -> 1997.1982 | P22: =Q22+R22+S22 -> 1214.7796 | Q22: =AJ22+AN22+AB22+AP22 -> 223.44172 | R22: =X22+Y22+Z22+AG22+AL22+AM22+AO22+U22+AC22 -> 617.17465 | S22: =V22+W22+AE22+AF22+AH22+AI22+AK22+AD22 -> 374.16322 | U22: =AR22*bisdepbyhaven!B43/1000 -> 0 | V22: =AS22*bisdepbyhaven!C43/1000 -> 3.9148084 | W22: =AT22*bisdepbyhaven!D43/1000 -> 4.142212 | X22: =AU22*bisdepbyhaven!E43/1000 -> 38.64 | Y22: =AV22*bisdepbyhaven!F43/1000 -> 0.8083628 | Z22: =AW22*bisdepbyhaven!G43/1000 -> 23.743168 | AA22: =AX22*bisdepbyhaven!H43/1000 -> 453.33616 | AB22: =AY22*bisdepbyhaven!I43/1000 -> 0 | ... AP22: =BM22*bisdepbyhaven!W43/1000 -> 147.7495 | AR22: 0.7 | AS22: 0.05 | AT22: 0.05 | AU22: 0.7 | AV22: 0.7 | AW22: 0.7 | AX22: 1 | AY22: 0 | AZ22: 0.7 | BA22: 1 | BB22: 0.1 | BC22: 0.65 | BD22: 0.7 | BE22: 0.65 | BF22: 0.65 | BG22: 0.3 | BH22: 0.7 | BI22: 0.5 | BJ22: 0.5 | BK22: 1 | BL22: 0.7 | BM22: 0.1
A23: 2019 | B23: =T.A1!C26/T.A1!$C26 -> 1 | C23: =T.A1!F26/T.A1!$C26 -> 0.24156538 | D23: =1-C23 -> 0.75843462 | E23: =$D23*Q23/$P23 -> 0.13881687 | F23: =$D23*R23/$P23 -> 0.39183617 | G23: =$D23*S23/$P23 -> 0.22778159 | H23: 2019 | I23: =T.A1!C26 -> 10740.665 | J23: =T.A1!F26 -> 2594.5729 | K23: =I23-J23 -> 8146.0926 | L23: =E23*$I23 -> 1490.9855 | M23: =F23*$I23 -> 4208.5812 | N23: =G23*$I23 -> 2446.5259 | P23: =Q23+R23+S23 -> 1195.9527 | Q23: =AJ23+AN23+AB23+AP23 -> 218.89613 | R23: =X23+Y23+Z23+AG23+AL23+AM23+AO23+U23+AC23 -> 617.87463 | S23: =V23+W23+AE23+AF23+AH23+AI23+AK23+AD23 -> 359.18192 | U23: =AR23*bisdepbyhaven!B44/1000 -> 0 | V23: =AS23*bisdepbyhaven!C44/1000 -> 4.584365 | W23: =AT23*bisdepbyhaven!D44/1000 -> 3.4038886 | X23: =AU23*bisdepbyhaven!E44/1000 -> 37.9085 | Y23: =AV23*bisdepbyhaven!F44/1000 -> 0.948444 | Z23: =AW23*bisdepbyhaven!G44/1000 -> 27.281703 | AA23: =AX23*bisdepbyhaven!H44/1000 -> 461.05079 | AB23: =AY23*bisdepbyhaven!I44/1000 -> 0 | ... AP23: =BM23*bisdepbyhaven!W44/1000 -> 152.0242 | AR23: 0.7 | AS23: 0.05 | AT23: 0.05 | AU23: 0.7 | AV23: 0.7 | AW23: 0.7 | AX23: 1 | AY23: 0 | AZ23: 0.7 | BA23: 1 | BB23: 0.1 | BC23: 0.65 | BD23: 0.7 | BE23: 0.65 | BF23: 0.65 | BG23: 0.3 | BH23: 0.6 | BI23: 0.5 | BJ23: 0.5 | BK23: 1 | BL23: 0.7 | BM23: 0.1
A24: 2020 | B24: =T.A1!C27/T.A1!$C27 -> 1 | C24: =T.A1!F27/T.A1!$C27 -> 0.21477956 | D24: =1-C24 -> 0.78522044 | E24: =$D24*Q24/$P24 -> 0.14655107 | F24: =$D24*R24/$P24 -> 0.40358536 | G24: =$D24*S24/$P24 -> 0.23508402 | H24: 2020 | I24: =T.A1!C27 -> 12856.722 | J24: =T.A1!F27 -> 2761.3611 | K24: =I24-J24 -> 10095.361 | L24: =E24*$I24 -> 1884.1664 | M24: =F24*$I24 -> 5188.7848 | N24: =G24*$I24 -> 3022.4099 | P24: =Q24+R24+S24 -> 1289.2841 | Q24: =AJ24+AN24+AB24+AP24 -> 240.62793 | R24: =X24+Y24+Z24+AG24+AL24+AM24+AO24+U24+AC24 -> 662.66256 | S24: =V24+W24+AE24+AF24+AH24+AI24+AK24+AD24 -> 385.99363 | U24: =AR24*bisdepbyhaven!B45/1000 -> 0 | V24: =AS24*bisdepbyhaven!C45/1000 -> 5.1919287 | W24: =AT24*bisdepbyhaven!D45/1000 -> 3.5636416 | X24: =AU24*bisdepbyhaven!E45/1000 -> 32.9028 | Y24: =AV24*bisdepbyhaven!F45/1000 -> 0.8630181 | Z24: =AW24*bisdepbyhaven!G45/1000 -> 23.289931 | AA24: =AX24*bisdepbyhaven!H45/1000 -> 528.96184 | AB24: =AY24*bisdepbyhaven!I45/1000 -> 0 | ... AP24: =BM24*bisdepbyhaven!W45/1000 -> 172.115 | AR24: 0.7 | AS24: 0.05 | AT24: 0.05 | AU24: 0.7 | AV24: 0.7 | AW24: 0.7 | AX24: 1 | AY24: 0 | AZ24: 0.7 | BA24: 1 | BB24: 0.1 | BC24: 0.65 | BD24: 0.7 | BE24: 0.65 | BF24: 0.65 | BG24: 0.3 | BH24: 0.5 | BI24: 0.5 | BJ24: 0.5 | BK24: 1 | BL24: 0.7 | BM24: 0.1
A25: 2021 | B25: =T.A1!C28/T.A1!$C28 -> 1 | C25: =T.A1!F28/T.A1!$C28 -> 0.21565889 | D25: =1-C25 -> 0.78434111 | E25: =$D25*Q25/$P25 -> 0.15250814 | F25: =$D25*R25/$P25 -> 0.40575862 | G25: =$D25*S25/$P25 -> 0.22607435 | H25: 2021 | I25: =T.A1!C28 -> 14033.606 | J25: =T.A1!F28 -> 3026.4719 | K25: =I25-J25 -> 11007.134 | L25: =E25*$I25 -> 2140.2392 | M25: =F25*$I25 -> 5694.2566 | N25: =G25*$I25 -> 3172.6384 | P25: =Q25+R25+S25 -> 1334.0237 | Q25: =AJ25+AN25+AB25+AP25 -> 259.38902 | R25: =X25+Y25+Z25+AG25+AL25+AM25+AO25+U25+AC25 -> 690.12269 | S25: =V25+W25+AE25+AF25+AH25+AI25+AK25+AD25 -> 384.51195 | U25: =AR25*bisdepbyhaven!B46/1000 -> 0 | V25: =AS25*bisdepbyhaven!C46/1000 -> 4.5852696 | W25: =AT25*bisdepbyhaven!D46/1000 -> 3.4418327 | X25: =AU25*bisdepbyhaven!E46/1000 -> 35.1995 | Y25: =AV25*bisdepbyhaven!F46/1000 -> 0.808871 | Z25: =AW25*bisdepbyhaven!G46/1000 -> 24.052909 | AA25: =AX25*bisdepbyhaven!H46/1000 -> 555.02971 | AB25: =AY25*bisdepbyhaven!I46/1000 -> 0 | ... AP25: =BM25*bisdepbyhaven!W46/1000 -> 197.4 | AR25: 0.7 | AS25: 0.05 | AT25: 0.05 | AU25: 0.7 | AV25: 0.7 | AW25: 0.7 | AX25: 1 | AY25: 0 | AZ25: 0.7 | BA25: 1 | BB25: 0.1 | BC25: 0.65 | BD25: 0.7 | BE25: 0.65 | BF25: 0.65 | BG25: 0.3 | BH25: 0.4 | BI25: 0.5 | BJ25: 0.5 | BK25: 1 | BL25: 0.7 | BM25: 0.1
A26: 2022 | B26: =T.A1!C29/T.A1!$C29 -> 1 | C26: =T.A1!F29/T.A1!$C29 -> 0.21433309 | D26: =1-C26 -> 0.78566691 | E26: =$D26*Q26/$P26 -> 0.15423036 | F26: =$D26*R26/$P26 -> 0.41178046 | G26: =$D26*S26/$P26 -> 0.21965609 | H26: 2022 | I26: =T.A1!C29 -> 12387.728 | J26: =T.A1!F29 -> 2655.1 | K26: =I26-J26 -> 9732.6282 | L26: =E26*$I26 -> 1910.5637 | M26: =F26*$I26 -> 5101.0245 | N26: =G26*$I26 -> 2721.04 | P26: =Q26+R26+S26 -> 1326.1075 | Q26: =AJ26+AN26+AB26+AP26 -> 260.32155 | R26: =X26+Y26+Z26+AG26+AL26+AM26+AO26+U26+AC26 -> 695.03391 | S26: =V26+W26+AE26+AF26+AH26+AI26+AK26+AD26 -> 370.75201 | U26: =AR26*bisdepbyhaven!B47/1000 -> 0 | V26: =AS26*bisdepbyhaven!C47/1000 -> 5.291047 | W26: =AT26*bisdepbyhaven!D47/1000 -> 3.4298594 | X26: =AU26*bisdepbyhaven!E47/1000 -> 36.827 | Y26: =AV26*bisdepbyhaven!F47/1000 -> 1.1743438 | Z26: =AW26*bisdepbyhaven!G47/1000 -> 14.763034 | AA26: =AX26*bisdepbyhaven!H47/1000 -> 506.78177 | AB26: =AY26*bisdepbyhaven!I47/1000 -> 0 | ... AP26: =BM26*bisdepbyhaven!W47/1000 -> 202.2316 | AR26: 0.7 | AS26: 0.05 | AT26: 0.05 | AU26: 0.7 | AV26: 0.7 | AW26: 0.7 | AX26: 1 | AY26: 0 | AZ26: 0.7 | BA26: 1 | BB26: 0.1 | BC26: 0.65 | BD26: 0.7 | BE26: 0.65 | BF26: 0.65 | BG26: 0.3 | BH26: 0.4 | BI26: 0.5 | BJ26: 0.5 | BK26: 1 | BL26: 0.7 | BM26: 0.1
A27: AJZ 2006-07 | B27: 1 | C27: 0.47423739 | D27: 0.52576261 | E27: 0.1125643 | F27: 0.14571989 | G27: 0.26747843 | H27: 2006-07 | I27: 5623.6645 | J27: 2666.952 | K27: 2956.7125 | L27: 633.02386 | M27: 819.47976 | N27: 1504.2089
A30: Source: build_bis.do outsheets the "bisdepbyhaven" Excel sheet from which the share of each tax haven in non-Swiss offshore wealth is constructed
A32: American havens: Cayman Islands, Panama, part of US (see weights in this sheet col. AP sq., same as in build_offshore21)
A33: Asian havens: Hong Kong, Singapore, Macao, Malaysia, Bahrain, as well as Bahamas, Bermuda, Nethd Antilles. See weights.
A34: European havens: Cyprus, Guernesey, Jersey, Isle of Man, Luxembourg, part of Austria, Belgium & UK (see weights)

Sheet T.A2b
A2: Table A2b: Where is the world's offshore wealth located? (with details)
B3: Share of world's offshore wealth
B4: Total offshore wealth | C4: Switzerland | D4: Tax havens other than Switzerland | E4: Cayman Islands | F4: Panama | G4: US | H4: Hong Kong | I4: Singapore | J4: Macao | K4: Malaysia | L4: Bahrain | M4: Bahamas | N4: Bermuda | O4: Guernsey | P4: Jersey | Q4: Isle of Man | R4: Luxembourg | S4: Cyprus | T4: UK | U4: Netherlands Antilles (then Curaçao) | V4: Austria | W4: Belgium
A5: 2001 | B5: =T.A1!C8/T.A1!$C8 -> 1 | C5: =T.A1!F8/T.A1!$C8 -> 0.38388394 | D5: =1-C5 -> 0.61611606 | E5: =T.A2!E5*T.A2!AJ5/T.A2!Q5 -> 0.081635507 | F5: =T.A2!E5*T.A2!AN5/T.A2!Q5 -> 0 | G5: =T.A2!E5*T.A2!AP5/T.A2!Q5 -> 0.016471383 | H5: =T.A2!$F5*T.A2!AG5/T.A2!$R5 -> 0.046127795 | I5: =T.A2!$F5*T.A2!AO5/T.A2!$R5 -> 0.071133098 | J5: =T.A2!$F5*T.A2!AL5/T.A2!$R5 -> 0 | K5: =T.A2!$F5*T.A2!AM5/T.A2!$R5 -> 0 | L5: =T.A2!$F5*T.A2!X5/T.A2!$R5 -> 0.015241998 | M5: =T.A2!$F5*T.A2!Z5/T.A2!$R5 -> 0.056355779 | N5: =T.A2!$F5*T.A2!Y5/T.A2!$R5 -> 0 | O5: =T.A2!$G5*T.A2!AF5/T.A2!$S5 -> 0.041570556 | P5: =T.A2!$G5*T.A2!AI5/T.A2!$S5 -> 0.063307111 | Q5: =T.A2!$G5*T.A2!AH5/T.A2!$S5 -> 0.019808849 | R5: =T.A2!$G5*T.A2!AK5/T.A2!$S5 -> 0.11403922 | S5: =T.A2!$G5*T.A2!AD5/T.A2!$S5 -> 0.011340557 | T5: =T.A2!$G5*T.A2!AE5/T.A2!$S5 -> 0.04168859 | U5: =T.A2!$F5*T.A2!U5/T.A2!$R5 -> 0.00482286 | V5: =T.A2!$G5*T.A2!V5/T.A2!$S5 -> 0.0025590172 | W5: =T.A2!$G5*T.A2!W5/T.A2!$S5 -> 0.030013747
A6: 2002 | B6: =T.A1!C9/T.A1!$C9 -> 1 | C6: =T.A1!F9/T.A1!$C9 -> 0.38549383 | D6: =1-C6 -> 0.61450617 | E6: =T.A2!E6*T.A2!AJ6/T.A2!Q6 -> 0.11078511 | F6: =T.A2!E6*T.A2!AN6/T.A2!Q6 -> 1.0774915e-05 | G6: =T.A2!E6*T.A2!AP6/T.A2!Q6 -> 0.017429669 | H6: =T.A2!$F6*T.A2!AG6/T.A2!$R6 -> 0.035358383 | I6: =T.A2!$F6*T.A2!AO6/T.A2!$R6 -> 0.068003807 | J6: =T.A2!$F6*T.A2!AL6/T.A2!$R6 -> 0 | K6: =T.A2!$F6*T.A2!AM6/T.A2!$R6 -> 0 | L6: =T.A2!$F6*T.A2!X6/T.A2!$R6 -> 0.011665835 | M6: =T.A2!$F6*T.A2!Z6/T.A2!$R6 -> 0.039839173 | N6: =T.A2!$F6*T.A2!Y6/T.A2!$R6 -> 0.0010304135 | O6: =T.A2!$G6*T.A2!AF6/T.A2!$S6 -> 0.029451988 | P6: =T.A2!$G6*T.A2!AI6/T.A2!$S6 -> 0.06748744 | Q6: =T.A2!$G6*T.A2!AH6/T.A2!$S6 -> 0.020909138 | R6: =T.A2!$G6*T.A2!AK6/T.A2!$S6 -> 0.11055643 | S6: =T.A2!$G6*T.A2!AD6/T.A2!$S6 -> 0.011375551 | T6: =T.A2!$G6*T.A2!AE6/T.A2!$S6 -> 0.046207645 | U6: =T.A2!$F6*T.A2!U6/T.A2!$R6 -> 0.0050545957 | V6: =T.A2!$G6*T.A2!V6/T.A2!$S6 -> 0.0033752008 | W6: =T.A2!$G6*T.A2!W6/T.A2!$S6 -> 0.03596501
A7: 2003 | B7: =T.A1!C10/T.A1!$C10 -> 1 | C7: =T.A1!F10/T.A1!$C10 -> 0.43598379 | D7: =1-C7 -> 0.56401621 | E7: =T.A2!E7*T.A2!AJ7/T.A2!Q7 -> 0.085406801 | F7: =T.A2!E7*T.A2!AN7/T.A2!Q7 -> 0.003094604 | G7: =T.A2!E7*T.A2!AP7/T.A2!Q7 -> 0.026556676 | H7: =T.A2!$F7*T.A2!AG7/T.A2!$R7 -> 0.031475191 | I7: =T.A2!$F7*T.A2!AO7/T.A2!$R7 -> 0.054769232 | J7: =T.A2!$F7*T.A2!AL7/T.A2!$R7 -> 0.00088909544 | K7: =T.A2!$F7*T.A2!AM7/T.A2!$R7 -> 0 | L7: =T.A2!$F7*T.A2!X7/T.A2!$R7 -> 0.0091421357 | M7: =T.A2!$F7*T.A2!Z7/T.A2!$R7 -> 0.037208622 | N7: =T.A2!$F7*T.A2!Y7/T.A2!$R7 -> 0.00089515844 | O7: =T.A2!$G7*T.A2!AF7/T.A2!$S7 -> 0.027027982 | P7: =T.A2!$G7*T.A2!AI7/T.A2!$S7 -> 0.070925947 | Q7: =T.A2!$G7*T.A2!AH7/T.A2!$S7 -> 0.017891414 | R7: =T.A2!$G7*T.A2!AK7/T.A2!$S7 -> 0.10037789 | S7: =T.A2!$G7*T.A2!AD7/T.A2!$S7 -> 0.010851605 | T7: =T.A2!$G7*T.A2!AE7/T.A2!$S7 -> 0.046796079 | U7: =T.A2!$F7*T.A2!U7/T.A2!$R7 -> 0.0042345714 | V7: =T.A2!$G7*T.A2!V7/T.A2!$S7 -> 0.0033250598 | W7: =T.A2!$G7*T.A2!W7/T.A2!$S7 -> 0.033148146
A8: 2004 | B8: =T.A1!C11/T.A1!$C11 -> 1 | C8: =T.A1!F11/T.A1!$C11 -> 0.42652904 | D8: =1-C8 -> 0.57347096 | E8: =T.A2!E8*T.A2!AJ8/T.A2!Q8 -> 0.083364638 | F8: =T.A2!E8*T.A2!AN8/T.A2!Q8 -> 0.0033701061 | G8: =T.A2!E8*T.A2!AP8/T.A2!Q8 -> 0.035855336 | H8: =T.A2!$F8*T.A2!AG8/T.A2!$R8 -> 0.034031276 | I8: =T.A2!$F8*T.A2!AO8/T.A2!$R8 -> 0.049814406 | J8: =T.A2!$F8*T.A2!AL8/T.A2!$R8 -> 0.00093907227 | K8: =T.A2!$F8*T.A2!AM8/T.A2!$R8 -> 0 | L8: =T.A2!$F8*T.A2!X8/T.A2!$R8 -> 0.010407751 | M8: =T.A2!$F8*T.A2!Z8/T.A2!$R8 -> 0.035522837 | N8: =T.A2!$F8*T.A2!Y8/T.A2!$R8 -> 0.0010514091 | O8: =T.A2!$G8*T.A2!AF8/T.A2!$S8 -> 0.027717567 | P8: =T.A2!$G8*T.A2!AI8/T.A2!$S8 -> 0.059268979 | Q8: =T.A2!$G8*T.A2!AH8/T.A2!$S8 -> 0.019037302 | R8: =T.A2!$G8*T.A2!AK8/T.A2!$S8 -> 0.10170799 | S8: =T.A2!$G8*T.A2!AD8/T.A2!$S8 -> 0.011000818 | T8: =T.A2!$G8*T.A2!AE8/T.A2!$S8 -> 0.055260717 | U8: =T.A2!$F8*T.A2!U8/T.A2!$R8 -> 0.0045026697 | V8: =T.A2!$G8*T.A2!V8/T.A2!$S8 -> 0.0034711922 | W8: =T.A2!$G8*T.A2!W8/T.A2!$S8 -> 0.037146896
A9: 2005 | B9: =T.A1!C12/T.A1!$C12 -> 1 | C9: =T.A1!F12/T.A1!$C12 -> 0.4422203 | D9: =1-C9 -> 0.5577797 | E9: =T.A2!E9*T.A2!AJ9/T.A2!Q9 -> 0.074626294 | F9: =T.A2!E9*T.A2!AN9/T.A2!Q9 -> 0.0033236404 | G9: =T.A2!E9*T.A2!AP9/T.A2!Q9 -> 0.031083578 | H9: =T.A2!$F9*T.A2!AG9/T.A2!$R9 -> 0.035094386 | I9: =T.A2!$F9*T.A2!AO9/T.A2!$R9 -> 0.050684342 | J9: =T.A2!$F9*T.A2!AL9/T.A2!$R9 -> 0.0020671906 | K9: =T.A2!$F9*T.A2!AM9/T.A2!$R9 -> 0 | L9: =T.A2!$F9*T.A2!X9/T.A2!$R9 -> 0.012353464 | M9: =T.A2!$F9*T.A2!Z9/T.A2!$R9 -> 0.041175046 | N9: =T.A2!$F9*T.A2!Y9/T.A2!$R9 -> 0.0010564261 | O9: =T.A2!$G9*T.A2!AF9/T.A2!$S9 -> 0.026270797 | P9: =T.A2!$G9*T.A2!AI9/T.A2!$S9 -> 0.067405347 | Q9: =T.A2!$G9*T.A2!AH9/T.A2!$S9 -> 0.021087295 | R9: =T.A2!$G9*T.A2!AK9/T.A2!$S9 -> 0.080444204 | S9: =T.A2!$G9*T.A2!AD9/T.A2!$S9 -> 0.010564776 | T9: =T.A2!$G9*T.A2!AE9/T.A2!$S9 -> 0.053637471 | U9: =T.A2!$F9*T.A2!U9/T.A2!$R9 -> 0.004174198 | V9: =T.A2!$G9*T.A2!V9/T.A2!$S9 -> 0.0063031752 | W9: =T.A2!$G9*T.A2!W9/T.A2!$S9 -> 0.036428069
A10: 2006 | B10: =T.A1!C13/T.A1!$C13 -> 1 | C10: =T.A1!F13/T.A1!$C13 -> 0.47938831 | D10: =1-C10 -> 0.52061169 | E10: =T.A2!E10*T.A2!AJ10/T.A2!Q10 -> 0.068190078 | F10: =T.A2!E10*T.A2!AN10/T.A2!Q10 -> 0.0030434638 | G10: =T.A2!E10*T.A2!AP10/T.A2!Q10 -> 0.03527281 | H10: =T.A2!$F10*T.A2!AG10/T.A2!$R10 -> 0.032245051 | I10: =T.A2!$F10*T.A2!AO10/T.A2!$R10 -> 0.046860844 | J10: =T.A2!$F10*T.A2!AL10/T.A2!$R10 -> 0.0019692241 | K10: =T.A2!$F10*T.A2!AM10/T.A2!$R10 -> 0 | L10: =T.A2!$F10*T.A2!X10/T.A2!$R10 -> 0.014259946 | M10: =T.A2!$F10*T.A2!Z10/T.A2!$R10 -> 0.039037956 | N10: =T.A2!$F10*T.A2!Y10/T.A2!$R10 -> 0.0007199196 | O10: =T.A2!$G10*T.A2!AF10/T.A2!$S10 -> 0.022548108 | P10: =T.A2!$G10*T.A2!AI10/T.A2!$S10 -> 0.063078539 | Q10: =T.A2!$G10*T.A2!AH10/T.A2!$S10 -> 0.018490678 | R10: =T.A2!$G10*T.A2!AK10/T.A2!$S10 -> 0.078538678 | S10: =T.A2!$G10*T.A2!AD10/T.A2!$S10 -> 0.0096591142 | T10: =T.A2!$G10*T.A2!AE10/T.A2!$S10 -> 0.04934555 | U10: =T.A2!$F10*T.A2!U10/T.A2!$R10 -> 0.0027722114 | V10: =T.A2!$G10*T.A2!V10/T.A2!$S10 -> 0.0061743817 | W10: =T.A2!$G10*T.A2!W10/T.A2!$S10 -> 0.02840514
A11: 2007 | B11: =T.A1!C14/T.A1!$C14 -> 1 | C11: =T.A1!F14/T.A1!$C14 -> 0.42850784 | D11: =1-C11 -> 0.57149216 | E11: =T.A2!E11*T.A2!AJ11/T.A2!Q11 -> 0.078412529 | F11: =T.A2!E11*T.A2!AN11/T.A2!Q11 -> 0.0034330404 | G11: =T.A2!E11*T.A2!AP11/T.A2!Q11 -> 0.03655067 | H11: =T.A2!$F11*T.A2!AG11/T.A2!$R11 -> 0.038378346 | I11: =T.A2!$F11*T.A2!AO11/T.A2!$R11 -> 0.054819628 | J11: =T.A2!$F11*T.A2!AL11/T.A2!$R11 -> 0.0022402446 | K11: =T.A2!$F11*T.A2!AM11/T.A2!$R11 -> 0.0027759088 | L11: =T.A2!$F11*T.A2!X11/T.A2!$R11 -> 0.015464455 | M11: =T.A2!$F11*T.A2!Z11/T.A2!$R11 -> 0.040569678 | N11: =T.A2!$F11*T.A2!Y11/T.A2!$R11 -> 0.00049363736 | O11: =T.A2!$G11*T.A2!AF11/T.A2!$S11 -> 0.023455661 | P11: =T.A2!$G11*T.A2!AI11/T.A2!$S11 -> 0.074764707 | Q11: =T.A2!$G11*T.A2!AH11/T.A2!$S11 -> 0.01964543 | R11: =T.A2!$G11*T.A2!AK11/T.A2!$S11 -> 0.070426682 | S11: =T.A2!$G11*T.A2!AD11/T.A2!$S11 -> 0.010330517 | T11: =T.A2!$G11*T.A2!AE11/T.A2!$S11 -> 0.05719735 | U11: =T.A2!$F11*T.A2!U11/T.A2!$R11 -> 0.0029124367 | V11: =T.A2!$G11*T.A2!V11/T.A2!$S11 -> 0.0066068644 | W11: =T.A2!$G11*T.A2!W11/T.A2!$S11 -> 0.033014377
A12: 2008 | B12: =T.A1!C15/T.A1!$C15 -> 1 | C12: =T.A1!F15/T.A1!$C15 -> 0.37833746 | D12: =1-C12 -> 0.62166254 | E12: =T.A2!E12*T.A2!AJ12/T.A2!Q12 -> 0.11485016 | F12: =T.A2!E12*T.A2!AN12/T.A2!Q12 -> 0.0049447423 | G12: =T.A2!E12*T.A2!AP12/T.A2!Q12 -> 0.041176371 | H12: =T.A2!$F12*T.A2!AG12/T.A2!$R12 -> 0.04681724 | I12: =T.A2!$F12*T.A2!AO12/T.A2!$R12 -> 0.061648924 | J12: =T.A2!$F12*T.A2!AL12/T.A2!$R12 -> 0.0027878307 | K12: =T.A2!$F12*T.A2!AM12/T.A2!$R12 -> 0.0027760604 | L12: =T.A2!$F12*T.A2!X12/T.A2!$R12 -> 0.017671763 | M12: =T.A2!$F12*T.A2!Z12/T.A2!$R12 -> 0.051619222 | N12: =T.A2!$F12*T.A2!Y12/T.A2!$R12 -> 0.00046736571 | O12: =T.A2!$G12*T.A2!AF12/T.A2!$S12 -> 0.02583635 | P12: =T.A2!$G12*T.A2!AI12/T.A2!$S12 -> 0.05556181 | Q12: =T.A2!$G12*T.A2!AH12/T.A2!$S12 -> 0.020194004 | R12: =T.A2!$G12*T.A2!AK12/T.A2!$S12 -> 0.070106497 | S12: =T.A2!$G12*T.A2!AD12/T.A2!$S12 -> 0.0095663149 | T12: =T.A2!$G12*T.A2!AE12/T.A2!$S12 -> 0.057912377 | U12: =T.A2!$F12*T.A2!U12/T.A2!$R12 -> 0.0033166315 | V12: =T.A2!$G12*T.A2!V12/T.A2!$S12 -> 0.0052962919 | W12: =T.A2!$G12*T.A2!W12/T.A2!$S12 -> 0.029112586
A13: 2009 | B13: =T.A1!C16/T.A1!$C16 -> 1 | C13: =T.A1!F16/T.A1!$C16 -> 0.37406636 | D13: =1-C13 -> 0.62593364 | E13: =T.A2!E13*T.A2!AJ13/T.A2!Q13 -> 0.1122517 | F13: =T.A2!E13*T.A2!AN13/T.A2!Q13 -> 0.0070720624 | G13: =T.A2!E13*T.A2!AP13/T.A2!Q13 -> 0.03855309 | H13: =T.A2!$F13*T.A2!AG13/T.A2!$R13 -> 0.054730567 | I13: =T.A2!$F13*T.A2!AO13/T.A2!$R13 -> 0.071647196 | J13: =T.A2!$F13*T.A2!AL13/T.A2!$R13 -> 0.0032822094 | K13: =T.A2!$F13*T.A2!AM13/T.A2!$R13 -> 0.0037950056 | L13: =T.A2!$F13*T.A2!X13/T.A2!$R13 -> 0.018238609 | M13: =T.A2!$F13*T.A2!Z13/T.A2!$R13 -> 0.045214512 | N13: =T.A2!$F13*T.A2!Y13/T.A2!$R13 -> 0.0005595281 | O13: =T.A2!$G13*T.A2!AF13/T.A2!$S13 -> 0.023540998 | P13: =T.A2!$G13*T.A2!AI13/T.A2!$S13 -> 0.04537897 | Q13: =T.A2!$G13*T.A2!AH13/T.A2!$S13 -> 0.019749733 | R13: =T.A2!$G13*T.A2!AK13/T.A2!$S13 -> 0.077725926 | S13: =T.A2!$G13*T.A2!AD13/T.A2!$S13 -> 0.011074516 | T13: =T.A2!$G13*T.A2!AE13/T.A2!$S13 -> 0.06353032 | U13: =T.A2!$F13*T.A2!U13/T.A2!$R13 -> 0.0036673554 | V13: =T.A2!$G13*T.A2!V13/T.A2!$S13 -> 0.004474903 | W13: =T.A2!$G13*T.A2!W13/T.A2!$S13 -> 0.021446441
A14: 2010 | B14: =T.A1!C17/T.A1!$C17 -> 1 | C14: =T.A1!F17/T.A1!$C17 -> 0.39372224 | D14: =1-C14 -> 0.60627776 | E14: =T.A2!E14*T.A2!AJ14/T.A2!Q14 -> 0.11837991 | F14: =T.A2!E14*T.A2!AN14/T.A2!Q14 -> 0.0073004137 | G14: =T.A2!E14*T.A2!AP14/T.A2!Q14 -> 0.038689091 | H14: =T.A2!$F14*T.A2!AG14/T.A2!$R14 -> 0.057995901 | I14: =T.A2!$F14*T.A2!AO14/T.A2!$R14 -> 0.070771778 | J14: =T.A2!$F14*T.A2!AL14/T.A2!$R14 -> 0.0030325434 | K14: =T.A2!$F14*T.A2!AM14/T.A2!$R14 -> 0.0039775571 | L14: =T.A2!$F14*T.A2!X14/T.A2!$R14 -> 0.019628832 | M14: =T.A2!$F14*T.A2!Z14/T.A2!$R14 -> 0.046920193 | N14: =T.A2!$F14*T.A2!Y14/T.A2!$R14 -> 0.00058516867 | O14: =T.A2!$G14*T.A2!AF14/T.A2!$S14 -> 0.024494144 | P14: =T.A2!$G14*T.A2!AI14/T.A2!$S14 -> 0.03379919 | Q14: =T.A2!$G14*T.A2!AH14/T.A2!$S14 -> 0.016300734 | R14: =T.A2!$G14*T.A2!AK14/T.A2!$S14 -> 0.062612348 | S14: =T.A2!$G14*T.A2!AD14/T.A2!$S14 -> 0.014242249 | T14: =T.A2!$G14*T.A2!AE14/T.A2!$S14 -> 0.069512779 | U14: =T.A2!$F14*T.A2!AC14/T.A2!$R14 -> 0.0026662779 | V14: =T.A2!$G14*T.A2!V14/T.A2!$S14 -> 0.0027330146 | W14: =T.A2!$G14*T.A2!W14/T.A2!$S14 -> 0.012635634
A15: 2011 | B15: =T.A1!C18/T.A1!$C18 -> 1 | C15: =T.A1!F18/T.A1!$C18 -> 0.34308605 | D15: =1-C15 -> 0.65691395 | E15: =T.A2!E15*T.A2!AJ15/T.A2!Q15 -> 0.099179572 | F15: =T.A2!E15*T.A2!AN15/T.A2!Q15 -> 0.0093898144 | G15: =T.A2!E15*T.A2!AP15/T.A2!Q15 -> 0.05068849 | H15: =T.A2!$F15*T.A2!AG15/T.A2!$R15 -> 0.078492215 | I15: =T.A2!$F15*T.A2!AO15/T.A2!$R15 -> 0.086621368 | J15: =T.A2!$F15*T.A2!AL15/T.A2!$R15 -> 0.0041059993 | K15: =T.A2!$F15*T.A2!AM15/T.A2!$R15 -> 0.005137477 | L15: =T.A2!$F15*T.A2!X15/T.A2!$R15 -> 0.018973002 | M15: =T.A2!$F15*T.A2!Z15/T.A2!$R15 -> 0.048068424 | N15: =T.A2!$F15*T.A2!Y15/T.A2!$R15 -> 0.00093476552 | O15: =T.A2!$G15*T.A2!AF15/T.A2!$S15 -> 0.024791985 | P15: =T.A2!$G15*T.A2!AI15/T.A2!$S15 -> 0.034348353 | Q15: =T.A2!$G15*T.A2!AH15/T.A2!$S15 -> 0.016088756 | R15: =T.A2!$G15*T.A2!AK15/T.A2!$S15 -> 0.069856237 | S15: =T.A2!$G15*T.A2!AD15/T.A2!$S15 -> 0.016862148 | T15: =T.A2!$G15*T.A2!AE15/T.A2!$S15 -> 0.081371179 | U15: =T.A2!$F15*T.A2!AC15/T.A2!$R15 -> 0.0021646453 | V15: =T.A2!$G15*T.A2!V15/T.A2!$S15 -> 0.0018119812 | W15: =T.A2!$G15*T.A2!W15/T.A2!$S15 -> 0.0080275396
A16: 2012 | B16: =T.A1!C19/T.A1!$C19 -> 1 | C16: =T.A1!F19/T.A1!$C19 -> 0.28830679 | D16: =1-C16 -> 0.71169321 | E16: =T.A2!E16*T.A2!AJ16/T.A2!Q16 -> 0.090190746 | F16: =T.A2!E16*T.A2!AN16/T.A2!Q16 -> 0.011272446 | G16: =T.A2!E16*T.A2!AP16/T.A2!Q16 -> 0.055563756 | H16: =T.A2!$F16*T.A2!AG16/T.A2!$R16 -> 0.10257695 | I16: =T.A2!$F16*T.A2!AO16/T.A2!$R16 -> 0.078787022 | J16: =T.A2!$F16*T.A2!AL16/T.A2!$R16 -> 0.0061195703 | K16: =T.A2!$F16*T.A2!AM16/T.A2!$R16 -> 0.0074057199 | L16: =T.A2!$F16*T.A2!X16/T.A2!$R16 -> 0.021239502 | M16: =T.A2!$F16*T.A2!Z16/T.A2!$R16 -> 0.047413337 | N16: =T.A2!$F16*T.A2!Y16/T.A2!$R16 -> 0.00080614567 | O16: =T.A2!$G16*T.A2!AF16/T.A2!$S16 -> 0.023700145 | P16: =T.A2!$G16*T.A2!AI16/T.A2!$S16 -> 0.038141154 | Q16: =T.A2!$G16*T.A2!AH16/T.A2!$S16 -> 0.016853252 | R16: =T.A2!$G16*T.A2!AK16/T.A2!$S16 -> 0.087678305 | S16: =T.A2!$G16*T.A2!AD16/T.A2!$S16 -> 0.019497431 | T16: =T.A2!$G16*T.A2!AE16/T.A2!$S16 -> 0.091885368 | U16: =T.A2!$F16*T.A2!AC16/T.A2!$R16 -> 0.0026198775 | V16: =T.A2!$G16*T.A2!V16/T.A2!$S16 -> 0.0018452569 | W16: =T.A2!$G16*T.A2!W16/T.A2!$S16 -> 0.0080972226
A17: 2013 | B17: =T.A1!C20/T.A1!$C20 -> 1 | C17: =T.A1!F20/T.A1!$C20 -> 0.28592928 | D17: =1-C17 -> 0.71407072 | E17: =T.A2!E17*T.A2!AJ17/T.A2!Q17 -> 0.092714082 | F17: =T.A2!E17*T.A2!AN17/T.A2!Q17 -> 0.011064546 | G17: =T.A2!E17*T.A2!AP17/T.A2!Q17 -> 0.063968123 | H17: =T.A2!$F17*T.A2!AG17/T.A2!$R17 -> 0.11546758 | I17: =T.A2!$F17*T.A2!AO17/T.A2!$R17 -> 0.085427654 | J17: =T.A2!$F17*T.A2!AL17/T.A2!$R17 -> 0.0079436264 | K17: =T.A2!$F17*T.A2!AM17/T.A2!$R17 -> 0.0075966149 | L17: =T.A2!$F17*T.A2!X17/T.A2!$R17 -> 0.022166605 | M17: =T.A2!$F17*T.A2!Z17/T.A2!$R17 -> 0.045481635 | N17: =T.A2!$F17*T.A2!Y17/T.A2!$R17 -> 0.0008914035 | O17: =T.A2!$G17*T.A2!AF17/T.A2!$S17 -> 0.020691306 | P17: =T.A2!$G17*T.A2!AI17/T.A2!$S17 -> 0.032646459 | Q17: =T.A2!$G17*T.A2!AH17/T.A2!$S17 -> 0.013185212 | R17: =T.A2!$G17*T.A2!AK17/T.A2!$S17 -> 0.086144933 | S17: =T.A2!$G17*T.A2!AD17/T.A2!$S17 -> 0.010436645 | T17: =T.A2!$G17*T.A2!AE17/T.A2!$S17 -> 0.087651069 | U17: =T.A2!$F17*T.A2!AC17/T.A2!$R17 -> 0.0022764217 | V17: =T.A2!$G17*T.A2!V17/T.A2!$S17 -> 0.0018753592 | W17: =T.A2!$G17*T.A2!W17/T.A2!$S17 -> 0.0064414444
A18: 2014 | B18: =T.A1!C21/T.A1!$C21 -> 1 | C18: =T.A1!F21/T.A1!$C21 -> 0.24590982 | D18: =1-C18 -> 0.75409018 | E18: =T.A2!E18*T.A2!AJ18/T.A2!Q18 -> 0.091767298 | F18: =T.A2!E18*T.A2!AN18/T.A2!Q18 -> 0.014249167 | G18: =T.A2!E18*T.A2!AP18/T.A2!Q18 -> 0.076241078 | H18: =T.A2!$F18*T.A2!AG18/T.A2!$R18 -> 0.14593872 | I18: =T.A2!$F18*T.A2!AO18/T.A2!$R18 -> 0.096713999 | J18: =T.A2!$F18*T.A2!AL18/T.A2!$R18 -> 0.010778537 | K18: =T.A2!$F18*T.A2!AM18/T.A2!$R18 -> 0.0096419608 | L18: =T.A2!$F18*T.A2!X18/T.A2!$R18 -> 0.023348608 | M18: =T.A2!$F18*T.A2!Z18/T.A2!$R18 -> 0.033331087 | N18: =T.A2!$F18*T.A2!Y18/T.A2!$R18 -> 0.00092291311 | O18: =T.A2!$G18*T.A2!AF18/T.A2!$S18 -> 0.014796921 | P18: =T.A2!$G18*T.A2!AI18/T.A2!$S18 -> 0.025892292 | Q18: =T.A2!$G18*T.A2!AH18/T.A2!$S18 -> 0.012446275 | R18: =T.A2!$G18*T.A2!AK18/T.A2!$S18 -> 0.084398699 | S18: =T.A2!$G18*T.A2!AD18/T.A2!$S18 -> 0.0098444997 | T18: =T.A2!$G18*T.A2!AE18/T.A2!$S18 -> 0.091175785 | U18: =T.A2!$F18*T.A2!AC18/T.A2!$R18 -> 0.0034743393 | V18: =T.A2!$G18*T.A2!V18/T.A2!$S18 -> 0.0017882542 | W18: =T.A2!$G18*T.A2!W18/T.A2!$S18 -> 0.0073397482
A19: 2015 | B19: =T.A1!C22/T.A1!$C22 -> 1 | C19: =T.A1!F22/T.A1!$C22 -> 0.2327847 | D19: =1-C19 -> 0.7672153 | E19: =T.A2!E19*T.A2!AJ19/T.A2!Q19 -> 0.080570348 | F19: =T.A2!E19*T.A2!AN19/T.A2!Q19 -> 0.016139621 | G19: =T.A2!E19*T.A2!AP19/T.A2!Q19 -> 0.078008254 | H19: =T.A2!$F19*T.A2!AG19/T.A2!$R19 -> 0.16768563 | I19: =T.A2!$F19*T.A2!AO19/T.A2!$R19 -> 0.10157632 | J19: =T.A2!$F19*T.A2!AL19/T.A2!$R19 -> 0.014291839 | K19: =T.A2!$F19*T.A2!AM19/T.A2!$R19 -> 0.009316129 | L19: =T.A2!$F19*T.A2!X19/T.A2!$R19 -> 0.025815346 | M19: =T.A2!$F19*T.A2!Z19/T.A2!$R19 -> 0.026918334 | N19: =T.A2!$F19*T.A2!Y19/T.A2!$R19 -> 0.0011237461 | O19: =T.A2!$G19*T.A2!AF19/T.A2!$S19 -> 0.013762969 | P19: =T.A2!$G19*T.A2!AI19/T.A2!$S19 -> 0.024451181 | Q19: =T.A2!$G19*T.A2!AH19/T.A2!$S19 -> 0.012427743 | R19: =T.A2!$G19*T.A2!AK19/T.A2!$S19 -> 0.084172834 | S19: =T.A2!$G19*T.A2!AD19/T.A2!$S19 -> 0.0091898338 | T19: =T.A2!$G19*T.A2!AE19/T.A2!$S19 -> 0.089994391 | U19: =T.A2!$F19*T.A2!AC19/T.A2!$R19 -> 0.0038373569 | V19: =T.A2!$G19*T.A2!V19/T.A2!$S19 -> 0.0015818387 | W19: =T.A2!$G19*T.A2!W19/T.A2!$S19 -> 0.0063515758
A20: 2016 | B20: =T.A1!C23/T.A1!$C23 -> 1 | C20: =T.A1!F23/T.A1!$C23 -> 0.26929655 | D20: =1-C20 -> 0.73070345 | E20: =T.A2!E20*T.A2!AJ20/T.A2!Q20 -> 0.059923736 | F20: =T.A2!E20*T.A2!AN20/T.A2!Q20 -> 0.01503985 | G20: =T.A2!E20*T.A2!AP20/T.A2!Q20 -> 0.085619659 | H20: =T.A2!$F20*T.A2!AG20/T.A2!$R20 -> 0.18714976 | I20: =T.A2!$F20*T.A2!AO20/T.A2!$R20 -> 0.09541074 | J20: =T.A2!$F20*T.A2!AL20/T.A2!$R20 -> 0.0091326105 | K20: =T.A2!$F20*T.A2!AM20/T.A2!$R20 -> 0.0068438081 | L20: =T.A2!$F20*T.A2!X20/T.A2!$R20 -> 0.023912293 | M20: =T.A2!$F20*T.A2!Z20/T.A2!$R20 -> 0.01940697 | N20: =T.A2!$F20*T.A2!Y20/T.A2!$R20 -> 0.00095269341 | O20: =T.A2!$G20*T.A2!AF20/T.A2!$S20 -> 0.013423944 | P20: =T.A2!$G20*T.A2!AI20/T.A2!$S20 -> 0.022342797 | Q20: =T.A2!$G20*T.A2!AH20/T.A2!$S20 -> 0.010877037 | R20: =T.A2!$G20*T.A2!AK20/T.A2!$S20 -> 0.072707189 | S20: =T.A2!$G20*T.A2!AD20/T.A2!$S20 -> 0.0084042721 | T20: =T.A2!$G20*T.A2!AE20/T.A2!$S20 -> 0.089504928 | U20: =T.A2!$F20*T.A2!AC20/T.A2!$R20 -> 0.0027306714 | V20: =T.A2!$G20*T.A2!V20/T.A2!$S20 -> 0.0021891918 | W20: =T.A2!$G20*T.A2!W20/T.A2!$S20 -> 0.0051313069
A21: 2017 | B21: =T.A1!C24/T.A1!$C24 -> 1 | C21: =T.A1!F24/T.A1!$C24 -> 0.25923151 | D21: =1-C21 -> 0.74076849 | E21: =T.A2!E21*T.A2!AJ21/T.A2!Q21 -> 0.048404916 | F21: =T.A2!E21*T.A2!AN21/T.A2!Q21 -> 0.012725505 | G21: =T.A2!E21*T.A2!AP21/T.A2!Q21 -> 0.083901951 | H21: =T.A2!$F21*T.A2!AG21/T.A2!$R21 -> 0.19303114 | I21: =T.A2!$F21*T.A2!AO21/T.A2!$R21 -> 0.10721285 | J21: =T.A2!$F21*T.A2!AL21/T.A2!$R21 -> 0.0092942764 | K21: =T.A2!$F21*T.A2!AM21/T.A2!$R21 -> 0.008501417 | L21: =T.A2!$F21*T.A2!X21/T.A2!$R21 -> 0.022872732 | M21: =T.A2!$F21*T.A2!Z21/T.A2!$R21 -> 0.014894773 | N21: =T.A2!$F21*T.A2!Y21/T.A2!$R21 -> 0.00068112034 | O21: =T.A2!$G21*T.A2!AF21/T.A2!$S21 -> 0.012441653 | P21: =T.A2!$G21*T.A2!AI21/T.A2!$S21 -> 0.02338735 | Q21: =T.A2!$G21*T.A2!AH21/T.A2!$S21 -> 0.0099479807 | R21: =T.A2!$G21*T.A2!AK21/T.A2!$S21 -> 0.071682509 | S21: =T.A2!$G21*T.A2!AD21/T.A2!$S21 -> 0.0086638876 | T21: =T.A2!$G21*T.A2!AE21/T.A2!$S21 -> 0.10784821 | U21: =T.A2!$F21*T.A2!AC21/T.A2!$R21 -> 0 | V21: =T.A2!$G21*T.A2!V21/T.A2!$S21 -> 0.0021724579 | W21: =T.A2!$G21*T.A2!W21/T.A2!$S21 -> 0.003103761
A22: 2018 | B22: =T.A1!C25/T.A1!$C25 -> 1 | C22: =T.A1!F25/T.A1!$C25 -> 0.26028104 | D22: =1-C22 -> 0.73971896 | E22: =T.A2!E22*T.A2!AJ22/T.A2!Q22 -> 0.033782975 | F22: =T.A2!E22*T.A2!AN22/T.A2!Q22 -> 0.01230849 | G22: =T.A2!E22*T.A2!AP22/T.A2!Q22 -> 0.089969495 | H22: =T.A2!$F22*T.A2!AG22/T.A2!$R22 -> 0.21472626 | I22: =T.A2!$F22*T.A2!AO22/T.A2!$R22 -> 0.10501583 | J22: =T.A2!$F22*T.A2!AL22/T.A2!$R22 -> 0.008914792 | K22: =T.A2!$F22*T.A2!AM22/T.A2!$R22 -> 0.0086815257 | L22: =T.A2!$F22*T.A2!X22/T.A2!$R22 -> 0.023529158 | M22: =T.A2!$F22*T.A2!Z22/T.A2!$R22 -> 0.01445799 | N22: =T.A2!$F22*T.A2!Y22/T.A2!$R22 -> 0.0004922385 | O22: =T.A2!$G22*T.A2!AF22/T.A2!$S22 -> 0.0093982185 | P22: =T.A2!$G22*T.A2!AI22/T.A2!$S22 -> 0.021432907 | Q22: =T.A2!$G22*T.A2!AH22/T.A2!$S22 -> 0.0094814395 | R22: =T.A2!$G22*T.A2!AK22/T.A2!$S22 -> 0.063710894 | S22: =T.A2!$G22*T.A2!AD22/T.A2!$S22 -> 0.007180493 | T22: =T.A2!$G22*T.A2!AE22/T.A2!$S22 -> 0.11173007 | U22: =T.A2!$F22*T.A2!AC22/T.A2!$R22 -> 0 | V22: =T.A2!$G22*T.A2!V22/T.A2!$S22 -> 0.0023838546 | W22: =T.A2!$G22*T.A2!W22/T.A2!$S22 -> 0.0025223281
A23: 2019 | B23: =T.A1!C26/T.A1!$C26 -> 1 | C23: =T.A1!F26/T.A1!$C26 -> 0.24156538 | D23: =1-C23 -> 0.75843462 | E23: =T.A2!E23*T.A2!AJ23/T.A2!Q23 -> 0.029127325 | F23: =T.A2!E23*T.A2!AN23/T.A2!Q23 -> 0.013280696 | G23: =T.A2!E23*T.A2!AP23/T.A2!Q23 -> 0.096408846 | H23: =T.A2!$F23*T.A2!AG23/T.A2!$R23 -> 0.21048648 | I23: =T.A2!$F23*T.A2!AO23/T.A2!$R23 -> 0.1210336 | J23: =T.A2!$F23*T.A2!AL23/T.A2!$R23 -> 0.0094968638 | K23: =T.A2!$F23*T.A2!AM23/T.A2!$R23 -> 0.0088762298 | L23: =T.A2!$F23*T.A2!X23/T.A2!$R23 -> 0.024040348 | M23: =T.A2!$F23*T.A2!Z23/T.A2!$R23 -> 0.017301176 | N23: =T.A2!$F23*T.A2!Y23/T.A2!$R23 -> 0.0006014726 | O23: =T.A2!$G23*T.A2!AF23/T.A2!$S23 -> 0.0090877761 | P23: =T.A2!$G23*T.A2!AI23/T.A2!$S23 -> 0.023937391 | Q23: =T.A2!$G23*T.A2!AH23/T.A2!$S23 -> 0.0096889818 | R23: =T.A2!$G23*T.A2!AK23/T.A2!$S23 -> 0.060997858 | S23: =T.A2!$G23*T.A2!AD23/T.A2!$S23 -> 0.0067547313 | T23: =T.A2!$G23*T.A2!AE23/T.A2!$S23 -> 0.11224896 | U23: =T.A2!$F23*T.A2!AC23/T.A2!$R23 -> 0 | V23: =T.A2!$G23*T.A2!V23/T.A2!$S23 -> 0.0029072564 | W23: =T.A2!$G23*T.A2!W23/T.A2!$S23 -> 0.0021586364
A24: 2020 | B24: =T.A1!C27/T.A1!$C27 -> 1 | C24: =T.A1!F27/T.A1!$C27 -> 0.21477956 | D24: =1-C24 -> 0.78522044 | E24: =T.A2!E24*T.A2!AJ24/T.A2!Q24 -> 0.028560256 | F24: =T.A2!E24*T.A2!AN24/T.A2!Q24 -> 0.013166584 | G24: =T.A2!E24*T.A2!AP24/T.A2!Q24 -> 0.10482423 | H24: =T.A2!$F24*T.A2!AG24/T.A2!$R24 -> 0.21990924 | I24: =T.A2!$F24*T.A2!AO24/T.A2!$R24 -> 0.12803288 | J24: =T.A2!$F24*T.A2!AL24/T.A2!$R24 -> 0.012238361 | K24: =T.A2!$F24*T.A2!AM24/T.A2!$R24 -> 0.0086558749 | L24: =T.A2!$F24*T.A2!X24/T.A2!$R24 -> 0.02003899 | M24: =T.A2!$F24*T.A2!Z24/T.A2!$R24 -> 0.014184407 | N24: =T.A2!$F24*T.A2!Y24/T.A2!$R24 -> 0.0005256091 | O24: =T.A2!$G24*T.A2!AF24/T.A2!$S24 -> 0.0093958367 | P24: =T.A2!$G24*T.A2!AI24/T.A2!$S24 -> 0.023500233 | Q24: =T.A2!$G24*T.A2!AH24/T.A2!$S24 -> 0.0093050122 | R24: =T.A2!$G24*T.A2!AK24/T.A2!$S24 -> 0.059798876 | S24: =T.A2!$G24*T.A2!AD24/T.A2!$S24 -> 0.0063205403 | T24: =T.A2!$G24*T.A2!AE24/T.A2!$S24 -> 0.12143106 | U24: =T.A2!$F24*T.A2!AC24/T.A2!$R24 -> 0 | V24: =T.A2!$G24*T.A2!V24/T.A2!$S24 -> 0.0031620715 | W24: =T.A2!$G24*T.A2!W24/T.A2!$S24 -> 0.002170386
A25: 2021 | B25: =T.A1!C28/T.A1!$C28 -> 1 | C25: =T.A1!F28/T.A1!$C28 -> 0.21565889 | D25: =1-C25 -> 0.78434111 | E25: =T.A2!E25*T.A2!AJ25/T.A2!Q25 -> 0.022910174 | F25: =T.A2!E25*T.A2!AN25/T.A2!Q25 -> 0.01353636 | G25: =T.A2!E25*T.A2!AP25/T.A2!Q25 -> 0.11606161 | H25: =T.A2!$F25*T.A2!AG25/T.A2!$R25 -> 0.22007633 | I25: =T.A2!$F25*T.A2!AO25/T.A2!$R25 -> 0.12895054 | J25: =T.A2!$F25*T.A2!AL25/T.A2!$R25 -> 0.012933263 | K25: =T.A2!$F25*T.A2!AM25/T.A2!$R25 -> 0.0084853693 | L25: =T.A2!$F25*T.A2!X25/T.A2!$R25 -> 0.020695596 | M25: =T.A2!$F25*T.A2!Z25/T.A2!$R25 -> 0.014141942 | N25: =T.A2!$F25*T.A2!Y25/T.A2!$R25 -> 0.00047557686 | O25: =T.A2!$G25*T.A2!AF25/T.A2!$S25 -> 0.0090489095 | P25: =T.A2!$G25*T.A2!AI25/T.A2!$S25 -> 0.023782341 | Q25: =T.A2!$G25*T.A2!AH25/T.A2!$S25 -> 0.010593314 | R25: =T.A2!$G25*T.A2!AK25/T.A2!$S25 -> 0.051325628 | S25: =T.A2!$G25*T.A2!AD25/T.A2!$S25 -> 0.0061166668 | T25: =T.A2!$G25*T.A2!AE25/T.A2!$S25 -> 0.12048794 | U25: =T.A2!$F25*T.A2!AC25/T.A2!$R25 -> 0 | V25: =T.A2!$G25*T.A2!V25/T.A2!$S25 -> 0.0026959158 | W25: =T.A2!$G25*T.A2!W25/T.A2!$S25 -> 0.0020236304
A26: 2022 | B26: =T.A1!C29/T.A1!$C29 -> 1 | C26: =T.A1!F29/T.A1!$C29 -> 0.21433309 | D26: =1-C26 -> 0.78566691 | E26: =T.A2!E26*T.A2!AJ26/T.A2!Q26 -> 0.019293669 | F26: =T.A2!E26*T.A2!AN26/T.A2!Q26 -> 0.015122359 | G26: =T.A2!E26*T.A2!AP26/T.A2!Q26 -> 0.11981433 | H26: =T.A2!$F26*T.A2!AG26/T.A2!$R26 -> 0.2292591 | I26: =T.A2!$F26*T.A2!AO26/T.A2!$R26 -> 0.12993958 | J26: =T.A2!$F26*T.A2!AL26/T.A2!$R26 -> 0.011866715 | K26: =T.A2!$F26*T.A2!AM26/T.A2!$R26 -> 0.0094542344 | L26: =T.A2!$F26*T.A2!X26/T.A2!$R26 -> 0.02181856 | M26: =T.A2!$F26*T.A2!Z26/T.A2!$R26 -> 0.0087465212 | N26: =T.A2!$F26*T.A2!Y26/T.A2!$R26 -> 0.00069575286 | O26: =T.A2!$G26*T.A2!AF26/T.A2!$S26 -> 0.0082860755 | P26: =T.A2!$G26*T.A2!AI26/T.A2!$S26 -> 0.022710865 | Q26: =T.A2!$G26*T.A2!AH26/T.A2!$S26 -> 0.011423519 | R26: =T.A2!$G26*T.A2!AK26/T.A2!$S26 -> 0.050735738 | S26: =T.A2!$G26*T.A2!AD26/T.A2!$S26 -> 0.0052308918 | T26: =T.A2!$G26*T.A2!AE26/T.A2!$S26 -> 0.11610221 | U26: =T.A2!$F26*T.A2!AC26/T.A2!$R26 -> 0 | V26: =T.A2!$G26*T.A2!V26/T.A2!$S26 -> 0.0031347388 | W26: =T.A2!$G26*T.A2!W26/T.A2!$S26 -> 0.0020320578
B28: Billions of $US
B29: Total offshore wealth | C29: Switzerland | D29: Tax havens other than Switzerland | E29: Cayman Islands | F29: Panama | G29: US | H29: Hong Kong | I29: Singapore | J29: Macao | K29: Malaysia | L29: Bahrain | M29: Bahamas | N29: Bermuda | O29: Guernsey | P29: Jersey | Q29: Isle of Man | R29: Luxembourg | S29: Cyprus | T29: UK | U29: Netherlands Antilles (then Curaçao) | V29: Austria | W29: Belgium
A30: 2001 | B30: =B5*T.A2!$I5 -> 3311.5496 | C30: =C5*T.A2!$I5 -> 1271.2507 | D30: =D5*T.A2!$I5 -> 2040.2989 | E30: =E5*T.A2!$I5 -> 270.34003 | F30: =F5*T.A2!$I5 -> 0 | G30: =G5*T.A2!$I5 -> 54.545801 | H30: =H5*T.A2!$I5 -> 152.75448 | I30: =I5*T.A2!$I5 -> 235.56078 | ... W30: =W5*T.A2!$I5 -> 99.392012
A31: 2002 | B31: =B6*T.A2!$I6 -> 3326.7462 | C31: =C6*T.A2!$I6 -> 1282.4401 | D31: =D6*T.A2!$I6 -> 2044.3061 | E31: =E6*T.A2!$I6 -> 368.55395 | F31: =F6*T.A2!$I6 -> 0.035845409 | G31: =G6*T.A2!$I6 -> 57.984086 | H31: =H6*T.A2!$I6 -> 117.62837 | I31: =I6*T.A2!$I6 -> 226.23141 | ... W31: =W6*T.A2!$I6 -> 119.64646
A32: 2003 | B32: =B7*T.A2!$I7 -> 3569.3503 | C32: =C7*T.A2!$I7 -> 1556.1789 | D32: =D7*T.A2!$I7 -> 2013.1714 | E32: =E7*T.A2!$I7 -> 304.84679 | F32: =F7*T.A2!$I7 -> 11.045726 | G32: =G7*T.A2!$I7 -> 94.79008 | H32: =H7*T.A2!$I7 -> 112.34598 | I32: =I7*T.A2!$I7 -> 195.49057 | ... W32: =W7*T.A2!$I7 -> 118.31734
A33: 2004 | B33: =B8*T.A2!$I8 -> 4266.8114 | C33: =C8*T.A2!$I8 -> 1819.919 | D33: =D8*T.A2!$I8 -> 2446.8924 | E33: =E8*T.A2!$I8 -> 355.70119 | F33: =F8*T.A2!$I8 -> 14.379607 | G33: =G8*T.A2!$I8 -> 152.98796 | H33: =H8*T.A2!$I8 -> 145.20503 | I33: =I8*T.A2!$I8 -> 212.54868 | ... W33: =W8*T.A2!$I8 -> 158.4988
A34: 2005 | B34: =B9*T.A2!$I9 -> 4566.7319 | C34: =C9*T.A2!$I9 -> 2019.5016 | D34: =D9*T.A2!$I9 -> 2547.2304 | E34: =E9*T.A2!$I9 -> 340.79828 | F34: =F9*T.A2!$I9 -> 15.178175 | G34: =G9*T.A2!$I9 -> 141.95037 | H34: =H9*T.A2!$I9 -> 160.26665 | I34: =I9*T.A2!$I9 -> 231.4618 | ... W34: =W9*T.A2!$I9 -> 166.35723
A35: 2006 | B35: =B10*T.A2!$I10 -> 5052.61 | C35: =C10*T.A2!$I10 -> 2422.1622 | D35: =D10*T.A2!$I10 -> 2630.4479 | E35: =E10*T.A2!$I10 -> 344.53787 | F35: =F10*T.A2!$I10 -> 15.377436 | G35: =G10*T.A2!$I10 -> 178.21975 | H35: =H10*T.A2!$I10 -> 162.92167 | I35: =I10*T.A2!$I10 -> 236.76957 | ... W35: =W10*T.A2!$I10 -> 143.5201
A36: 2007 | B36: =B11*T.A2!$I11 -> 6795.0723 | C36: =C11*T.A2!$I11 -> 2911.7417 | D36: =D11*T.A2!$I11 -> 3883.3306 | E36: =E11*T.A2!$I11 -> 532.8188 | F36: =F11*T.A2!$I11 -> 23.327758 | G36: =G11*T.A2!$I11 -> 248.36444 | H36: =H11*T.A2!$I11 -> 260.78363 | I36: =I11*T.A2!$I11 -> 372.50333 | ... W36: =W11*T.A2!$I11 -> 224.33508
A37: 2008 | B37: =B12*T.A2!$I12 -> 5644.1316 | C37: =C12*T.A2!$I12 -> 2135.3864 | D37: =D12*T.A2!$I12 -> 3508.7452 | E37: =E12*T.A2!$I12 -> 648.22942 | F37: =F12*T.A2!$I12 -> 27.908776 | G37: =G12*T.A2!$I12 -> 232.40485 | H37: =H12*T.A2!$I12 -> 264.24266 | I37: =I12*T.A2!$I12 -> 347.95464 | ... W37: =W12*T.A2!$I12 -> 164.31526
A38: 2009 | B38: =B13*T.A2!$I13 -> 6305.3213 | C38: =C13*T.A2!$I13 -> 2358.6086 | D38: =D13*T.A2!$I13 -> 3946.7127 | E38: =E13*T.A2!$I13 -> 707.783 | F38: =F13*T.A2!$I13 -> 44.591625 | G38: =G13*T.A2!$I13 -> 243.08962 | H38: =H13*T.A2!$I13 -> 345.09381 | I38: =I13*T.A2!$I13 -> 451.75859 | ... W38: =W13*T.A2!$I13 -> 135.2267
A39: 2010 | B39: =B14*T.A2!$I14 -> 5844.8574 | C39: =C14*T.A2!$I14 -> 2301.2504 | D39: =D14*T.A2!$I14 -> 3543.607 | E39: =E14*T.A2!$I14 -> 691.91369 | F39: =F14*T.A2!$I14 -> 42.669877 | G39: =G14*T.A2!$I14 -> 226.13222 | H39: =H14*T.A2!$I14 -> 338.97777 | I39: =I14*T.A2!$I14 -> 413.65095 | ... W39: =W14*T.A2!$I14 -> 73.853477
A40: 2011 | B40: =B15*T.A2!$I15 -> 6563.066 | C40: =C15*T.A2!$I15 -> 2251.6964 | D40: =D15*T.A2!$I15 -> 4311.3696 | E40: =E15*T.A2!$I15 -> 650.92208 | F40: =F15*T.A2!$I15 -> 61.625972 | G40: =G15*T.A2!$I15 -> 332.6719 | H40: =H15*T.A2!$I15 -> 515.14959 | I40: =I15*T.A2!$I15 -> 568.50176 | ... W40: =W15*T.A2!$I15 -> 52.685272
A41: 2012 | B41: =B16*T.A2!$I16 -> 8219.9757 | C41: =C16*T.A2!$I16 -> 2369.8748 | D41: =D16*T.A2!$I16 -> 5850.1009 | E41: =E16*T.A2!$I16 -> 741.36574 | F41: =F16*T.A2!$I16 -> 92.659228 | G41: =G16*T.A2!$I16 -> 456.73272 | H41: =H16*T.A2!$I16 -> 843.18005 | I41: =I16*T.A2!$I16 -> 647.6274 | ... W41: =W16*T.A2!$I16 -> 66.558973
... A51: 2022 | B51: =B26*T.A2!$I26 -> 12387.728 | C51: =C26*T.A2!$I26 -> 2655.1 | D51: =D26*T.A2!$I26 -> 9732.6282 | E51: =E26*T.A2!$I26 -> 239.00473 | F51: =F26*T.A2!$I26 -> 187.33168 | G51: =G26*T.A2!$I26 -> 1484.2273 | H51: =H26*T.A2!$I26 -> 2839.9994 | I51: =I26*T.A2!$I26 -> 1609.6562 | ... W51: =W26*T.A2!$I26 -> 25.17258
A53: Source: load_bis.do outsheets the "bisdepbyhaven" Excel sheet from which the share of each tax haven in non-Swiss offshore wealth is constructed

Sheet T.A2c
A2: Table A2c: Evolution of offshore deposits and offshore wealth in teach tax haven
A3: Evolution of offshore wealth, 2007- 2022 | H3: BCG 2022: https://web-assets.bcg.com/fb/64/e10897864913a480415d0e1fe3c6/bcg-global-wealth-report-2023-june-2023.pdf
B4: Wealth 2007 | C4: Wealth 2022 | D4: Evolution | E4: Evolution, % 2007 wealth in all tax havens | H4: Our estimates (2022) | I4: BCG 2022
A5: Switzerland | B5: =T.A2b!$C$36 -> 2911.7417 | C5: =T.A2b!$C$51 -> 2655.1 | D5: =C5-B5 -> -256.64173 | E5: =D5/$B$23 -> -0.037768801 | G5: =A5 -> Switzerland | H5: =C5 -> 2655.1 | I5: 2400
A6: Jersey | B6: =T.A2b!$P$36 -> 508.03159 | C6: =T.A2b!$P$51 -> 281.33603 | D6: =C6-B6 -> -226.69556 | E6: =D6/$B$23 -> -0.033361759 | G6: =A6 -> Jersey | H6: =C6 -> 281.33603 | I6: 200
A7: Other tax havens (Netherlands Antilles, Belgium, Austria) | B7: =T.A2b!#REF!+T.A2b!$U$36+T.A2b!$V$36+ T.A2b!$W$36 -> #REF! | C7: =T.A2b!#REF!+T.A2b!$U$51+T.A2b!$V$51+T.A2b!$W$51 -> #REF! | D7: =C7-B7 -> #REF! | E7: =D7/$B$23 -> #REF! | G7: =A7 -> Other tax havens (Netherlands Antilles, Belgium, Austria) | H7: =H18-H16-H15-H14-H13-H12-H11-H10-H9-H8-H6-H5 -> 859.15473 | I7: 2000
A8: Bahamas | B8: =T.A2b!$M$36 -> 275.67389 | C8: =T.A2b!$M$51 -> 108.34953 | D8: =C8-B8 -> -167.32437 | E8: =D8/$B$23 -> -0.024624369 | G8: =A8 -> Bahamas | H8: =C8 -> 108.34953 | I8: 400
A9: Guernsey | B9: =T.A2b!$O$36 -> 159.38291 | C9: =T.A2b!$O$51 -> 102.64565 | D9: =C9-B9 -> -56.737262 | E9: =D9/$B$23 -> -0.0083497657 | G9: =A9 -> Guernsey | H9: =C9 -> 102.64565 | I9: 200
A10: Isle of Man | B10: =T.A2b!$Q$36 -> 133.49212 | C10: =T.A2b!$Q$51 -> 141.51145 | D10: =C10-B10 -> 8.0193292 | E10: =D10/$B$23 -> 0.0011801683 | G10: =A10 -> Isle of Man | H10: =C10 -> 141.51145 | I10: 200
A11: Bermuda | B11: =T.A2b!$N$36 -> 3.3543015 | C11: =T.A2b!$N$51 -> 8.6187973 | D11: =C11-B11 -> 5.2644958 | E11: =D11/$B$23 -> 0.00077475199 | G11: =A17 -> Cayman Islands | H11: =C17 -> 239.00473 | I11: 400
A12: Cyprus | B12: =T.A2b!S36 -> 70.196612 | C12: =T.A2b!$S$51 -> 64.798866 | D12: =C12-B12 -> -5.3977464 | E12: =D12/$B$23 -> -0.00079436188 | G12: =A18 -> Luxembourg | H12: =C18 -> 628.50053 | I12: 500
A13: Malaysia | B13: =T.A2b!$K$36 -> 18.862501 | C13: =T.A2b!$K$51 -> 117.11649 | D13: =C13-B13 -> 98.253985 | E13: =D13/$B$23 -> 0.014459594 | G13: =A19 -> UK | H13: =C19 -> 1438.2426 | I13: 900
A14: Macao | B14: =T.A2b!$J$36 -> 15.222624 | C14: =T.A2b!$J$51 -> 147.00164 | D14: =C14-B14 -> 131.77902 | E14: =D14/$B$23 -> 0.019393321 | G14: =A20 -> US | H14: =C20 -> 1484.2273 | I14: 1100
A15: Panama | B15: =T.A2b!$F$36 -> 23.327758 | C15: =T.A2b!$F$51 -> 187.33168 | D15: =C15-B15 -> 164.00392 | E15: =D15/$B$23 -> 0.024135714 | G15: =A21 -> Singapore | H15: =C21 -> 1609.6562 | I15: 1500
A16: Bahrain | B16: =T.A2b!$L$36 -> 105.08209 | C16: =T.A2b!$L$51 -> 270.28239 | D16: =C16-B16 -> 165.2003 | E16: =D16/$B$23 -> 0.02431178 | G16: =A22 -> Hong Kong | H16: =C22 -> 2839.9994 | I16: 2200
A17: Cayman Islands | B17: =T.A2b!$E$36 -> 532.8188 | C17: =T.A2b!$E$51 -> 239.00473 | D17: =C17-B17 -> -293.81408 | E17: =D17/$B$23 -> -0.043239286
A18: Luxembourg | B18: =T.A2b!$R$36 -> 478.5544 | C18: =T.A2b!$R$51 -> 628.50053 | D18: =C18-B18 -> 149.94613 | E18: =D18/$B$23 -> 0.022066893 | H18: =C23 -> 12387.728 | I18: 12000
A19: UK | B19: =T.A2b!$T$36 -> 388.66013 | C19: =T.A2b!$T$51 -> 1438.2426 | D19: =C19-B19 -> 1049.5824 | E19: =D19/$B$23 -> 0.15446229
A20: US | B20: =T.A2b!$G$36 -> 248.36444 | C20: =T.A2b!$G$51 -> 1484.2273 | D20: =C20-B20 -> 1235.8629 | E20: =D20/$B$23 -> 0.18187634
A21: Singapore | B21: =T.A2b!$I$36 -> 372.50333 | C21: =T.A2b!$I$51 -> 1609.6562 | D21: =C21-B21 -> 1237.1529 | E21: =D21/$B$23 -> 0.18206618
A22: Hong Kong | B22: =T.A2b!$H$36 -> 260.78363 | C22: =T.A2b!$H$51 -> 2839.9994 | D22: =C22-B22 -> 2579.2158 | E22: =D22/$B$23 -> 0.3795715
A23: All tax havens | B23: =T.A2b!$B$36 -> 6795.0723 | C23: =T.A2b!$B$51 -> 12387.728 | D23: =C23-B23 -> 5592.6559 | E23: =D23/$B$23 -> 0.82304582
A26: Evolution of offshore wealth, 2007-2015
B27: Wealth 2007 | C27: Wealth 2015 | D27: Evolution | E27: Evolution, % 2007 wealth in all tax havens
A28: Switzerland | B28: =T.A2b!$C$36 -> 2911.7417 | C28: =T.A2b!$C$44 -> 2216.8993 | D28: =C28-B28 -> -694.84242 | E28: =D28/$B$46 -> -0.10225681
A29: Jersey | B29: =T.A2b!$P$36 -> 508.03159 | C29: =T.A2b!$P$44 -> 232.85811 | D29: =C29-B29 -> -275.17349 | E29: =D29/$B$46 -> -0.040496035
A30: Other tax havens (incl. Netherlands Antilles, Belgium, Austria) | B30: =T.A2b!$U$36+T.A2b!$V$36+T.A2b!$W$36 -> 289.01942 | C30: =T.A2b!$U$44+T.A2b!$V$44+T.A2b!$W$44 -> 112.09764 | D30: =C30-B30 -> -176.92178 | E30: =D30/$B$46 -> -0.026036777
A31: Isle of Man | B31: =T.A2b!$Q$36 -> 133.49212 | C31: =T.A2b!$Q$44 -> 118.35424 | D31: =C31-B31 -> -15.137884 | E31: =D31/$B$46 -> -0.0022277738
A32: Luxembourg | B32: =T.A2b!$R$36 -> 478.5544 | C32: =T.A2b!$R$44 -> 801.61065 | D32: =C32-B32 -> 323.05625 | E32: =D32/$B$46 -> 0.047542725
A33: Bermuda | B33: =T.A2b!$N$36 -> 3.3543015 | C33: =T.A2b!$N$44 -> 10.701872 | D33: =C33-B33 -> 7.3475701 | E33: =D33/$B$46 -> 0.0010813086
A34: Guernsey | B34: =T.A2b!$O$36 -> 159.38291 | C34: =T.A2b!$O$44 -> 131.07011 | D34: =C34-B34 -> -28.312802 | E34: =D34/$B$46 -> -0.0041666667
A35: Macao | B35: =T.A2b!$J$36 -> 15.222624 | C35: =T.A2b!$J$44 -> 136.10675 | D35: =C35-B35 -> 120.88412 | E35: =D35/$B$46 -> 0.017789969
A36: Bahrain | B36: =T.A2b!$L$36 -> 105.08209 | C36: =T.A2b!$L$44 -> 245.84959 | D36: =C36-B36 -> 140.7675 | E36: =D36/$B$46 -> 0.020716115
A37: Malaysia | B37: =T.A2b!$K$36 -> 18.862501 | C37: =T.A2b!$K$44 -> 88.721121 | D37: =C37-B37 -> 69.85862 | E37: =D37/$B$46 -> 0.010280777
A38: Panama | B38: =T.A2b!$F$36 -> 23.327758 | C38: =T.A2b!$F$44 -> 153.70389 | D38: =C38-B38 -> 130.37614 | E38: =D38/$B$46 -> 0.019186865
A39: Cyprus | B39: =T.A2b!S36 -> 70.196612 | C39: =T.A2b!S44 -> 87.518362 | D39: =C39-B39 -> 17.321751 | E39: =D39/$B$46 -> 0.0025491635
A40: Bahamas | B40: =T.A2b!$M$36 -> 275.67389 | C40: =T.A2b!$M$44 -> 256.35376 | D40: =C40-B40 -> -19.320129 | E40: =D40/$B$46 -> -0.0028432559
A41: US | B41: =T.A2b!$G$36 -> 248.36444 | C41: =T.A2b!$G$44 -> 742.90295 | D41: =C41-B41 -> 494.53851 | E41: =D41/$B$46 -> 0.072778991
A42: Cayman Islands | B42: =T.A2b!$E$36 -> 532.8188 | C42: =T.A2b!$E$44 -> 767.30277 | D42: =C42-B42 -> 234.48397 | E42: =D42/$B$46 -> 0.034507943
A43: UK | B43: =T.A2b!$T$36 -> 388.66013 | C43: =T.A2b!$T$44 -> 857.05159 | D43: =C43-B43 -> 468.39147 | E43: =D43/$B$46 -> 0.06893105
A44: Singapore | B44: =T.A2b!$I$36 -> 372.50333 | C44: =T.A2b!$I$44 -> 967.35081 | D44: =C44-B44 -> 594.84748 | E44: =D44/$B$46 -> 0.087541008
A45: Hong Kong | B45: =T.A2b!$H$36 -> 260.78363 | C45: =T.A2b!$H$44 -> 1596.9355 | D45: =C45-B45 -> 1336.1519 | E45: =D45/$B$46 -> 0.19663542
A46: All tax havens | B46: =T.A2b!$B$36 -> 6795.0723 | C46: =T.A2b!$B$44 -> 9523.3891 | D46: =C46-B46 -> 2728.3168 | E46: =D46/$B$46 -> 0.40151402
A48: Evolution of offshore wealth, 2015-2022
B49: Wealth 2015 | C49: Wealth 2022 | D49: Evolution | E49: Evolution, % 2015 wealth in all tax havens
A50: Bahamas | B50: =T.A2b!$M$44 -> 256.35376 | C50: =T.A2b!$M$51 -> 108.34953 | D50: =C50-B50 -> -148.00424 | E50: =D50/$B$68 -> -0.015541131
A51: Switzerland | B51: =T.A2b!$C$44 -> 2216.8993 | C51: =T.A2b!$C$51 -> 2655.1 | D51: =C51-B51 -> 438.20069 | E51: =D51/$B$68 -> 0.046013104
A52: Guernsey | B52: =T.A2b!$O$44 -> 131.07011 | C52: =T.A2b!$O$51 -> 102.64565 | D52: =C52-B52 -> -28.42446 | E52: =D52/$B$68 -> -0.0029847001
A53: Cyprus | B53: =T.A2b!S44 -> 87.518362 | C53: =T.A2b!$S$51 -> 64.798866 | D53: =C53-B53 -> -22.719497 | E53: =D53/$B$68 -> -0.0023856525
A54: Other tax haven (Netherlands Antilles, Belgium, Austria) | B54: =T.A2b!$U$44+T.A2b!$V$44+T.A2b!$W$44 -> 112.09764 | C54: =T.A2b!$U$51+T.A2b!$V$51+T.A2b!$W$51 -> 64.004872 | D54: =C54-B54 -> -48.092763 | E54: =D54/$B$68 -> -0.0050499631
A55: Jersey | B55: =T.A2b!$P$44 -> 232.85811 | C55: =T.A2b!$P$51 -> 281.33603 | D55: =C55-B55 -> 48.477922 | E55: =D55/$B$68 -> 0.0050904065
A56: Bermuda | B56: =T.A2b!$N$44 -> 10.701872 | C56: =T.A2b!$N$51 -> 8.6187973 | D56: =C56-B56 -> -2.0830743 | E56: =D56/$B$68 -> -0.00021873246
A57: Isle of Man | B57: =T.A2b!$Q$44 -> 118.35424 | C57: =T.A2b!$Q$51 -> 141.51145 | D57: =C57-B57 -> 23.157213 | E57: =D57/$B$68 -> 0.0024316147
A58: Malaysia | B58: =T.A2b!$K$44 -> 88.721121 | C58: =T.A2b!$K$51 -> 117.11649 | D58: =C58-B58 -> 28.395365 | E58: =D58/$B$68 -> 0.0029816449
A59: Panama | B59: =T.A2b!$F$44 -> 153.70389 | C59: =T.A2b!$F$51 -> 187.33168 | D59: =C59-B59 -> 33.627784 | E59: =D59/$B$68 -> 0.0035310732
A60: Macao | B60: =T.A2b!$J$44 -> 136.10675 | C60: =T.A2b!$J$51 -> 147.00164 | D60: =C60-B60 -> 10.894896 | E60: =D60/$B$68 -> 0.0011440146
A61: Cayman Islands | B61: =T.A2b!$E$44 -> 767.30277 | C61: =T.A2b!$E$51 -> 239.00473 | D61: =C61-B61 -> -528.29804 | E61: =D61/$B$68 -> -0.055473744
A62: Bahrain | B62: =T.A2b!$L$44 -> 245.84959 | C62: =T.A2b!$L$51 -> 270.28239 | D62: =C62-B62 -> 24.432803 | E62: =D62/$B$68 -> 0.0025655575
A63: UK | B63: =T.A2b!$T$44 -> 857.05159 | C63: =T.A2b!$T$51 -> 1438.2426 | D63: =C63-B63 -> 581.19097 | E63: =D63/$B$68 -> 0.061027746
A64: Luxembourg | B64: =T.A2b!$R$44 -> 801.61065 | C64: =T.A2b!$R$51 -> 628.50053 | D64: =C64-B64 -> -173.11012 | E64: =D64/$B$68 -> -0.018177365
A65: US | B65: =T.A2b!$G$44 -> 742.90295 | C65: =T.A2b!$G$51 -> 1484.2273 | D65: =C65-B65 -> 741.32439 | E65: =D65/$B$68 -> 0.077842497
A66: Singapore | B66: =T.A2b!$I$44 -> 967.35081 | C66: =T.A2b!$I$51 -> 1609.6562 | D66: =C66-B66 -> 642.3054 | E66: =D66/$B$68 -> 0.067445045
A67: Hong Kong | B67: =T.A2b!$H$44 -> 1596.9355 | C67: =T.A2b!$H$51 -> 2839.9994 | D67: =C67-B67 -> 1243.0639 | E67: =D67/$B$68 -> 0.13052747
A68: All tax havens | B68: =T.A2b!$B$44 -> 9523.3891 | C68: =T.A2b!$B$51 -> 12387.728 | D68: =C68-B68 -> 2864.3391 | E68: =D68/$B$68 -> 0.30076888
A70: Memo: Evolution of offshore bank deposits, 2007-2011, from Johannesen-Zucman (2014)
B71: Deposits 2007 | C71: Deposits 2011 | D71: Evolution | E71: Evolution, % 2007 deposits in tax havens
A72: Switzerland | B72: 504.19375 | C72: 479.838 | D72: =C72-B72 -> -24.35575 | E72: =D72/$B$92 -> -0.009198337
A73: Jersey | B73: 185.4955 | C73: 74.055 | D73: =C73-B73 -> -111.4405 | E73: =D73/$B$92 -> -0.04208728
A74: Luxembourg | B74: 198.60375 | C74: 156.157 | D74: =C74-B74 -> -42.44675 | E74: =D74/$B$92 -> -0.016030691
A75: Isle of Man | B75: 56.1405 | C75: 40.6815 | D75: =C75-B75 -> -15.459 | E75: =D75/$B$92 -> -0.0058383376
A76: Netherlands Antilles | B76: 9.60075 | C76: 6.811 | D76: =C76-B76 -> -2.78975 | E76: =D76/$B$92 -> -0.0010535935
A77: Chile | B77: 2.48 | C77: 7.7475 | D77: =C77-B77 -> 5.2675 | E77: =D77/$B$92 -> 0.0019893553
A78: Cyprus | B78: 23.297 | C78: 37.2715 | D78: =C78-B78 -> 13.9745 | E78: =D78/$B$92 -> 0.0052776926
A79: Austria | B79: 57.9245 | C79: 72.5225 | D79: =C79-B79 -> 14.598 | E79: =D79/$B$92 -> 0.0055131673
A80: Belgium | B80: 226.75525 | C80: 243.6955 | D80: =C80-B80 -> 16.94025 | E80: =D80/$B$92 -> 0.0063977553
A81: Bermuda | B81: 1.8255 | C81: 1.8605 | D81: =C81-B81 -> 0.035 | E81: =D81/$B$92 -> 1.3218308e-05
A82: Guernsey | B82: 61.6645 | C82: 52.2185 | D82: =C82-B82 -> -9.446 | E82: =D82/$B$92 -> -0.0035674324
A83: Macao | B83: 8.55375 | C83: 11.121 | D83: =C83-B83 -> 2.56725 | E83: =D83/$B$92 -> 0.00096956286
... A90: Hong Kong | B90: 128.096 | C90: 191.0605 | D90: =C90-B90 -> 62.9645 | E90: =D90/$B$92 -> 0.023779547
A92: All tax havens | B92: =SUM(B72:B90) -> 2647.8427 | C92: =SUM(C72:C90) -> 2677.3075 | D92: =C92-B92 -> 29.46475 | E92: =D92/$B$92 -> 0.011127832

Sheet T.A3
A2: Table A3: The world's offshore wealth, 2007
B3: [1] | D3: [2] | E3: [3] | F3: [4] | G3: [5] | H3: [6] | I3: [7] | K3: [8] | L3: [9] | M3: [10] | N3: [11] | O3: [12] | P3: [13] | R3: [14] | S3: [15] | T3: [16] | U3: [17] | V3: [18] | W3: [19] | Y3: [20]
B4: 2007 GDP (billion US$) | D4: Share of offshore wealth (2007) | K4: billion of current US$ (2007) | R4: fraction of GDP (2007) | Y4: Memo: Share of HSBC wealth
D5: Total offshore wealth | E5: Offshore wealth in Switzerland | F5: Offshore wealth in the havens other than Switzerland | G5: Of which: Caribbean tax havens | H5: Of which: Asian tax havens | I5: Of which: European tax havens | K5: Total offshore wealth | L5: Offshore wealth in Switzerland | M5: Offshore wealth in the havens other than Switzerland | N5: Of which: Caribbean tax havens | O5: Of which: Asian tax havens | P5: Of which: European tax havens | R5: Total offshore wealth | S5: Offshore wealth in Switzerland | T5: Offshore wealth in the havens other than Switzerland | U5: Of which: Caribbean tax havens | V5: Of which: Asian tax havens | W5: Of which: European tax havens
A6: Africa and Middle East (excl. Gulf countries) | B6: 2043.2007 | D6: 0.064509252 | E6: 0.10838201 | F6: 0.024936062 | G6: 0.0071442462 | H6: 0.012563777 | I6: 0.039163793 | K6: 362.77839 | L6: 289.04962 | M6: 73.728766 | N6: 4.5224783 | O6: 10.295761 | P6: 58.910528 | R6: 0.17755397 | S6: 0.14146903 | T6: 0.036084936 | U6: 0.0022134283 | V6: 0.0050390355 | W6: 0.028832472 | Y6: 0.15411975
A7: Algeria | B7: 134.97709 | D7: 0.0010378402 | E7: 0.0019584883 | F7: 0.00020741645 | G7: 0 | H7: 4.9839146e-05 | I7: 0.0003805513 | K7: 5.8364649 | L7: 5.2231941 | M7: 0.61327082 | N7: 0 | O7: 0.040842171 | P7: 0.57242866 | R7: 0.043240412 | S7: 0.038696894 | T7: 0.0045435179 | U7: 0 | V7: 0.00030258596 | W7: 0.004240932 | Y7: 0.0038623603
A8: Angola | B8: 60.448921 | D8: 0.0017045484 | E8: 0.0024365245 | F8: 0.0010443066 | G8: 0.0002156752 | H8: 0.00032452511 | I8: 0.0017851542 | K8: 9.585808 | L8: 6.4980937 | M8: 3.0877143 | N8: 0.13652755 | O8: 0.26594176 | P8: 2.6852449 | R8: 0.15857699 | S8: 0.10749727 | T8: 0.051079725 | U8: 0.0022585605 | V8: 0.004399446 | W8: 0.044421718 | Y8: 0.00021179386
A9: Benin | B9: 5.9695351 | D9: 5.7093426e-05 | E9: 0.00010503744 | F9: 1.3847969e-05 | G9: 7.8474915e-07 | H9: 0 | I9: 2.6889682e-05 | K9: 0.32107427 | L9: 0.28012981 | M9: 0.040944464 | N9: 0.00049676493 | O9: 0 | P9: 0.0404477 | R9: 0.053785473 | S9: 0.04692657 | T9: 0.0068589032 | U9: 8.3216686e-05 | V9: 0 | W9: 0.0067756867 | Y9: 3.7984766e-05
A10: Botswana | B10: 10.939053 | D10: 9.7096383e-05 | E10: 1.4772751e-05 | F10: 0.00017135222 | G10: 1.5498796e-05 | H10: 4.5654178e-06 | I10: 0.0003278048 | K10: 0.54603748 | L10: 0.039398218 | M10: 0.50663926 | N10: 0.0098111074 | O10: 0.0037412675 | P10: 0.4930869 | R10: 0.049916337 | S10: 0.0036016113 | T10: 0.046314726 | U10: 0.00089688815 | V10: 0.00034201017 | W10: 0.045075829 | Y10: 9.783955e-09
A11: Burkina Faso | B11: 6.7712779 | D11: 4.2200898e-05 | E11: 3.9149112e-05 | F11: 4.4953606e-05 | G11: 0 | H11: 0 | I11: 8.8361987e-05 | K11: 0.23732369 | L11: 0.1044088 | M11: 0.13291489 | N11: 0 | O11: 0 | P11: 0.13291489 | R11: 0.035048582 | S11: 0.015419364 | T11: 0.019629218 | U11: 0 | V11: 0 | W11: 0.019629218 | Y11: 0
A12: Burundi | B12: 1.3560783 | D12: 3.9333459e-05 | E12: 3.9149112e-05 | F12: 3.9499741e-05 | G12: 0 | H12: 0 | I12: 7.7641729e-05 | K12: 0.22119818 | L12: 0.1044088 | M12: 0.11678938 | N12: 0 | O12: 0 | P12: 0.11678938 | R12: 0.16311608 | S12: 0.076993196 | T12: 0.086122888 | U12: 0 | V12: 0 | W12: 0.086122891 | Y12: 0.00017380908
A13: Cabo Verde | B13: 1.513934 | D13: 1.8024312e-05 | E13: 2.2159129e-05 | F13: 1.4294711e-05 | G13: 9.6131762e-06 | H13: 1.3949888e-06 | I13: 2.3292519e-05 | K13: 0.10136268 | L13: 0.059097332 | M13: 0.042265351 | N13: 0.0060853699 | O13: 0.0011431651 | P13: 0.035036816 | R13: 0.06695317 | S13: 0.039035606 | T13: 0.027917564 | U13: 0.004019574 | V13: 0.00075509569 | W13: 0.023142894 | Y13: 1.1510535e-05
A14: Cameroon | B14: 20.43178 | D14: 0.00034526205 | E14: 0.00066952588 | F14: 5.2776384e-05 | G14: 1.5694983e-06 | H14: 3.804515e-06 | I14: 0.00010100548 | K14: 1.9416379 | L14: 1.7855933 | M14: 0.1560446 | N14: 0.00099352986 | O14: 0.0031177231 | P14: 0.15193334 | R14: 0.095030287 | S14: 0.08739294 | T14: 0.007637347 | U14: 4.8626691e-05 | V14: 0.00015259184 | W14: 0.0074361282 | Y14: 0.00013179563
A15: Central African Republic | B15: 1.6981256 | D15: 4.7157755e-06 | E15: 7.3863757e-06 | F15: 2.3068965e-06 | G15: 1.9618729e-07 | H15: 0 | I15: 4.4519338e-06 | K15: 0.026519939 | L15: 0.019699109 | M15: 0.0068208297 | N15: 0.00012419123 | O15: 0 | P15: 0.0066966386 | R15: 0.015617183 | S15: 0.011600502 | T15: 0.0040166815 | U15: 7.3134303e-05 | V15: 0 | W15: 0.0039435472 | Y15: 7.9422694e-05
A16: Chad | B16: 8.6387114 | D16: 1.4060923e-05 | E16: 0 | F16: 2.6743863e-05 | G16: 0 | H16: 0 | I16: 5.2568437e-05 | K16: 0.079073914 | L16: 0 | M16: 0.079073914 | N16: 0 | O16: 0 | P16: 0.079073912 | R16: 0.0091534385 | S16: 0 | T16: 0.0091534385 | U16: 0 | V16: 0 | W16: 0.0091534383 | Y16: 0.00069466082
A17: Comoros | B17: 0.46245358 | D17: 3.3607382e-07 | E17: 0 | F17: 6.3921209e-07 | G17: 0 | H17: 1.5218059e-06 | I17: 4.2738569e-07 | K17: 0.0018899664 | L17: 0 | M17: 0.0018899664 | N17: 0 | O17: 0.0012470891 | P17: 0.00064287736 | R17: 0.004086824 | S17: 0 | T17: 0.004086824 | U17: 0 | V17: 0.0026966795 | W17: 0.0013901446 | Y17: 0
... A156: Canada | B156: 1464.9772 | D156: 0.012097652 | E156: 0.012631709 | F156: 0.011615933 | G156: 0.010895195 | H156: 0.0090886066 | I156: 0.01329611 | K156: 68.033135 | L156: 33.68816 | M156: 34.344974 | N156: 6.8969186 | O156: 7.4479292 | P156: 20.000127 | R156: 0.046439723 | S156: 0.022995689 | T156: 0.023444033 | U156: 0.0047078676 | V156: 0.0050839898 | W156: 0.013652176 | Y156: 0.022445545
A157: Other | B157: 1287.4227 | K157: 6.2721669 | L157: 4.1369738 | M157: 2.135193 | N157: 0 | O157: 1.0675965 | P157: 1.0675965 | R157: 0.0048718786 | Y157: 0.0027572351
A159: Total | B159: 57452.22 | D159: 0.99888468 | E159: 0.9984488 | F159: 0.99927785 | G159: 0.99997691 | H159: 0.99934256 | I159: 0.9989484 | K159: 5623.6645 | L159: 2666.952 | M159: 2956.7125 | N159: 633.00924 | O159: 820.0086 | P159: 1503.6947 | R159: 0.097884198 | S159: 0.046420346 | T159: 0.051463852 | U159: 0.011018012 | V159: 0.014272879 | W159: 0.026172961 | Y159: 1
A163: Source: Alstadsaeter, Johannesen, and Zucman (2018)

Sheet T.A3b
B2: Table A3b: The world's offshore wealth, 2022
C3: [1] | E3: [2] | F3: [3] | G3: [4] | H3: [5] | I3: [6] | J3: [7] | L3: [8] | M3: [9] | N3: [10] | O3: [11] | P3: [12] | Q3: [13] | S3: [14] | T3: [15] | U3: [16] | V3: [17] | W3: [18] | X3: [19]
C4: 2022 GDP (billion US$) | E4: Share of offshore wealth (2022) | L4: billion of current US$ (2022) | S4: fraction of GDP (2022)
A5: ISO3 | E5: Total offshore wealth | F5: Offshore wealth in Switzerland | G5: Offshore wealth in the havens other than Switzerland | H5: Of which: Caribbean tax havens | I5: Of which: Asian tax havens | J5: Of which: European tax havens | L5: Total offshore wealth | M5: Offshore wealth in Switzerland | N5: Offshore wealth in the havens other than Switzerland | O5: Of which: Caribbean tax havens | P5: Of which: Asian tax havens | Q5: Of which: European tax havens | S5: Total offshore wealth | T5: Offshore wealth in Switzerland | U5: Offshore wealth in the havens other than Switzerland | V5: Of which: Caribbean tax havens | W5: Of which: Asian tax havens | X5: Of which: European tax havens

Sheet T.A4
B2: Table A.4: Fiduciary Deposits in Swiss Banks, 1987-2022, mn of USD
B4: year | C4: Tax Havens | D4: Europe | E4: Middle East | F4: Latin and South America | G4: Asia | H4: Africa | I4: North America | J4: Caribbean | K4: Total ex-tax havens | L4: Total | M4: Rich countries | N4: Of which: Euro area 16 | O4: Developing countries | P4: Excl. Middle East
B5: 1987 | C5: 42816.012 | D5: 36151.832 | E5: 19146.258 | F5: 7241.8425 | G5: 5389.062 | H5: 3219.7065 | I5: 4199.6745 | J5: 21.619719 | K5: 75369.996 | L5: 118186.01 | M5: 40838.628 | N5: 27155.012 | O5: 34531.364 | P5: 15385.106
B6: 1988 | C6: 43383.24 | D6: 37456.056 | E6: 19338.31 | F6: 7935.7275 | G6: 5387.9915 | H6: 3072.3803 | I6: 4320.372 | J6: 26.069148 | K6: 77536.904 | L6: 120920.14 | M6: 42334.256 | N6: 28005.904 | O6: 35202.652 | P6: 15864.342
B7: 1989 | C7: 58089.656 | D7: 47804.592 | E7: 21472.052 | F7: 10336.782 | G7: 5949.351 | H7: 3860.2095 | I7: 5439.4135 | J7: 14.863886 | K7: 94877.272 | L7: 152966.93 | M7: 53899.928 | N7: 37927.692 | O7: 40977.34 | P7: 19505.288
B8: 1990 | C8: 73910.208 | D8: 61880.3 | E8: 25286.254 | F8: 13686.719 | G8: 6458.143 | H8: 4324.803 | I8: 6533.72 | J8: 19.550752 | K8: 118189.49 | L8: 192099.7 | M8: 69223.736 | N8: 49619.692 | O8: 48965.756 | P8: 23679.502
B9: 1991 | C9: 69056.968 | D9: 59619.812 | E9: 25233.926 | F9: 12471.981 | G9: 6564.67 | H9: 4232.088 | I9: 6111.8575 | J9: 20.649207 | K9: 114254.98 | L9: 183311.95 | M9: 66428.476 | N9: 48421.852 | O9: 47826.504 | P9: 22592.578
B10: 1992 | C10: 64622.996 | D10: 58242.356 | E10: 23578.362 | F10: 10123.552 | G10: 6209.5375 | H10: 3792.215 | I10: 6870.328 | J10: 28.513049 | K10: 108844.86 | L10: 173467.86 | M10: 65909.588 | N10: 48480.284 | O10: 42935.276 | P10: 19356.914
B11: 1993 | C11: 57224.772 | D11: 50127.004 | E11: 21804.838 | F11: 7943.161 | G11: 5613.477 | H11: 3618.638 | I11: 4975.6085 | J11: 20.429875 | K11: 94103.164 | L11: 151327.94 | M11: 55666.424 | N11: 41331.88 | O11: 38436.732 | P11: 16631.894
B12: 1994 | C12: 66504.616 | D12: 51614.136 | E12: 22614.648 | F12: 9043.083 | G12: 6600.1655 | H12: 3904.3057 | I12: 4258.0635 | J12: 40.789172 | K12: 98075.192 | L12: 164579.81 | M12: 56430.732 | N12: 43321.716 | O12: 41644.46 | P12: 19029.812
B13: 1995 | C13: 70541.064 | D13: 52688.584 | E13: 22872.526 | F13: 8981.276 | G13: 7105.216 | H13: 3570.2703 | I13: 4512.877 | J13: 74.163406 | K13: 99804.92 | L13: 170345.98 | M13: 57729.44 | N13: 44284.1 | O13: 42075.472 | P13: 19202.946
B14: 1996 | C14: 74525.896 | D14: 51197.376 | E14: 22967.424 | F14: 9220.446 | G14: 8113.942 | H14: 3443.8695 | I14: 5013.7945 | J14: 62.214793 | K14: 100019.06 | L14: 174544.96 | M14: 56523.064 | N14: 42094.192 | O14: 43496.008 | P14: 20528.584
B15: 1997 | C15: 77261.832 | D15: 50345.9 | E15: 23138.206 | F15: 10021.484 | G15: 9278.733 | H15: 3692.6168 | I15: 4894.54 | J15: 37.988043 | K15: 101409.46 | L15: 178671.3 | M15: 55760.768 | N15: 41278.628 | O15: 45648.7 | P15: 22510.494
B16: 1998 | C16: 79888.592 | D16: 52017.196 | E16: 22636.672 | F16: 10523.08 | G16: 9873.194 | H16: 3938.4125 | I16: 5082.2615 | J16: 42.22666 | K16: 104113.04 | L16: 184001.63 | M16: 57923.336 | N16: 42101 | O16: 46189.708 | P16: 23553.036
... B40: 2022 | C40: 114868.67 | D40: 34616.428 | E40: 26049.174 | F40: 2407.4538 | G40: 7147.203 | H40: 1382.8666 | I40: 2381.002 | J40: 8.5658369 | K40: 73992.688 | L40: 188861.36 | M40: 32646.788 | N40: 18666.418 | O40: 41345.904 | P40: 15296.73
B41: Notes:

Sheet T.A5
B2: Table A.5 Distribution of Fiduciary Deposits in Swiss Banks by Country of Owner, 1987-2022, Uncorrected Shares (% of Total)
B4: year | C4: Tax Havens | D4: Europe | E4: Middle East | F4: Latin and South America | G4: Asia | H4: Africa | I4: North America | J4: Caribbean | K4: Total | L4: Rich countries | M4: Of which: Euro area 16 | N4: Developing countries | O4: Excl. Middle East | P4: Total ex-tax havens
B5: 1987 | C5: 36 | D5: 31 | E5: 16 | F5: 6 | G5: 5 | H5: 3 | I5: 4 | J5: 0 | K5: 100 | L5: 35 | M5: 25 | N5: 29 | O5: 13 | P5: 64
B6: 1988 | C6: 36 | D6: 31 | E6: 16 | F6: 7 | G6: 4 | H6: 3 | I6: 4 | J6: 0 | K6: 100 | L6: 35 | M6: 24 | N6: 29 | O6: 13 | P6: 64
B7: 1989 | C7: 38 | D7: 31 | E7: 14 | F7: 7 | G7: 4 | H7: 3 | I7: 4 | J7: 0 | K7: 100 | L7: 35 | M7: 19 | N7: 27 | O7: 13 | P7: 62
B8: 1990 | C8: 38 | D8: 32 | E8: 13 | F8: 7 | G8: 3 | H8: 2 | I8: 3 | J8: 0 | K8: 100 | L8: 36 | M8: 15 | N8: 25 | O8: 12 | P8: 62
B9: 1991 | C9: 38 | D9: 33 | E9: 14 | F9: 7 | G9: 4 | H9: 2 | I9: 3 | J9: 0 | K9: 100 | L9: 36 | M9: 15 | N9: 26 | O9: 12 | P9: 62
B10: 1992 | C10: 37 | D10: 34 | E10: 14 | F10: 6 | G10: 4 | H10: 2 | I10: 4 | J10: 0 | K10: 100 | L10: 38 | M10: 15 | N10: 25 | O10: 11 | P10: 63
B11: 1993 | C11: 38 | D11: 33 | E11: 14 | F11: 5 | G11: 4 | H11: 2 | I11: 3 | J11: 0 | K11: 100 | L11: 37 | M11: 18 | N11: 25 | O11: 11 | P11: 62
B12: 1994 | C12: 40 | D12: 31 | E12: 14 | F12: 5 | G12: 4 | H12: 2 | I12: 3 | J12: 0 | K12: 100 | L12: 34 | M12: 18 | N12: 25 | O12: 12 | P12: 60
B13: 1995 | C13: 41 | D13: 31 | E13: 13 | F13: 5 | G13: 4 | H13: 2 | I13: 3 | J13: 0 | K13: 100 | L13: 34 | M13: 18 | N13: 25 | O13: 11 | P13: 59
B14: 1996 | C14: 43 | D14: 29 | E14: 13 | F14: 5 | G14: 5 | H14: 2 | I14: 3 | J14: 0 | K14: 100 | L14: 32 | M14: 18 | N14: 25 | O14: 12 | P14: 57
B15: 1997 | C15: 43 | D15: 28 | E15: 13 | F15: 6 | G15: 5 | H15: 2 | I15: 3 | J15: 0 | K15: 100 | L15: 31 | M15: 18 | N15: 26 | O15: 13 | P15: 57
B16: 1998 | C16: 43 | D16: 28 | E16: 12 | F16: 6 | G16: 5 | H16: 2 | I16: 3 | J16: 0 | K16: 100 | L16: 31 | M16: 17 | N16: 25 | O16: 13 | P16: 57
... B40: 2022 | C40: 61 | D40: 18 | E40: 14 | F40: 1 | G40: 4 | H40: 1 | I40: 1 | J40: 0 | K40: 100 | L40: 17 | M40: 31 | N40: 22 | O40: 8 | P40: 39
B41: Notes:

Sheet T.A6
A2: Table A.6: Distribution of Fiduciary Deposits in Swiss Banks by Country of Owner, 1987-2022, Corrected Shares (% of Total)
A4: year | B4: Tax Havens | C4: Europe | D4: Middle East | E4: Latin and South America | F4: Asia | G4: Africa | H4: North America | I4: Caribbean | J4: Total | K4: Rich countries | L4: Of which: Euro area 16 | M4: Developing countries | N4: Excl. Middle East | O4: Total ex-tax havens
A5: 1987
A6: 1988
A7: 1989
A8: 1990
A9: 1991
A10: 1992
A11: 1993
A12: 1994
A13: 1995
A14: 1996
A15: 1997
A16: 1998
... A40: 2022
A41: Notes:

Sheet T.A7
A2: Table S.1: Offshore wealth in Switzerland
B3: [1] | C3: [2] | D3: [3] | E3: [4] | F3: [5] | G3: [6] | H3: [7] | I3: [8] | J3: [9] | K3: [10]
B4: bn current US$ | G4: bn current euros
B5: Total offshore wealth | C5: Foreign securities belonging to foreigners | D5: Swiss securities belonging to foreigners | E5: Foreign securities wrongly attributed to Switzerland | F5: Fiduciary deposits | G5: Total offshore wealth | H5: Foreign securities belonging to foreigners | I5: Swiss securities belonging to foreigners | J5: Foreign securities wrongly attributed to Switzerland | K5: Fiduciary deposits
A6: 36161 | B6: =C6+D6+E6+F6 -> 1227.0842 | C6: =(SNB_D5_1a_M33!B32/0.968/SNB_FX!L25)/(1-0.06) -> 837.52837 | D6: =D7*C6/C7 -> 35.739416 | E6: =E7*C6/C7 -> 41.450233 | F6: =(SNB_D4_1a!I157/1000+SNB_2E!H158/1000)/SNB_FX!L25 -> 312.36617 | G6: =H6+I6+J6+K6 -> 1056.7663 | H6: =C6*SNB_FX!$L25/SNB_FX!$B25 -> 721.28035 | I6: =D6*SNB_FX!$L25/SNB_FX!$B25 -> 30.778824 | J6: =E6*SNB_FX!$L25/SNB_FX!$B25 -> 35.696986 | K6: =F6*SNB_FX!$L25/SNB_FX!$B25 -> 269.01009
A7: 36192 | B7: =C7+D7+E7+F7 -> 1193.6354 | C7: =(SNB_D5_1a_M33!B33/0.968/SNB_FX!L26)/(1-0.06) -> 812.82019 | D7: =D8*C7/C8 -> 34.685056 | E7: =E8*C7/C8 -> 40.227397 | F7: =(SNB_D4_1a!I158/1000+SNB_2E!H159/1000)/SNB_FX!L26 -> 305.90278 | G7: =H7+I7+J7+K7 -> 1064.6604 | H7: =C7*SNB_FX!$L26/SNB_FX!$B26 -> 724.99309 | I7: =D7*SNB_FX!$L26/SNB_FX!$B26 -> 30.937256 | J7: =E7*SNB_FX!$L26/SNB_FX!$B26 -> 35.880734 | K7: =F7*SNB_FX!$L26/SNB_FX!$B26 -> 272.84928 | M7: Growth rates
A8: 36220 | B8: =C8+D8+E8+F8 -> 1198.5647 | C8: =(SNB_D5_1a_M33!B34/0.968/SNB_FX!L27)/(1-0.06) -> 816.8364 | D8: =D9*C8/C9 -> 34.856438 | E8: =E9*C8/C9 -> 40.426164 | F8: =(SNB_D4_1a!I159/1000+SNB_2E!H160/1000)/SNB_FX!L27 -> 306.44569 | G8: =H8+I8+J8+K8 -> 1100.7886 | H8: =C8*SNB_FX!$L27/SNB_FX!$B27 -> 750.20082 | I8: =D8*SNB_FX!$L27/SNB_FX!$B27 -> 32.012932 | J8: =E8*SNB_FX!$L27/SNB_FX!$B27 -> 37.128293 | K8: =F8*SNB_FX!$L27/SNB_FX!$B27 -> 281.44658 | N8: US$ | O8: Euros
A9: 36251 | B9: =C9+D9+E9+F9 -> 1211.5935 | C9: =(SNB_D5_1a_M33!B35/0.968/SNB_FX!L28)/(1-0.06) -> 832.52872 | D9: =D10*C9/C10 -> 35.526068 | E9: =E10*C9/C10 -> 41.202795 | F9: =(SNB_D4_1a!I160/1000+SNB_2E!H161/1000)/SNB_FX!L28 -> 302.33592 | G9: =H9+I9+J9+K9 -> 1131.6475 | H9: =C9*SNB_FX!$L28/SNB_FX!$B28 -> 777.59503 | I9: =D9*SNB_FX!$L28/SNB_FX!$B28 -> 33.181911 | J9: =E9*SNB_FX!$L28/SNB_FX!$B28 -> 38.484064 | K9: =F9*SNB_FX!$L28/SNB_FX!$B28 -> 282.38654 | M9: April 2009 (G20 meeting) - June 2021 | N9: =B281/B129-1 -> 0.4394007 | O9: =G191/G129-1 -> 0.13652748
A10: 36281 | B10: =C10+D10+E10+F10 -> 1192.3196 | C10: =(SNB_D5_1a_M33!B36/0.968/SNB_FX!L29)/(1-0.06) -> 817.97692 | D10: =D11*C10/C11 -> 34.905107 | E10: =E11*C10/C11 -> 40.482609 | F10: =(SNB_D4_1a!I161/1000+SNB_2E!H162/1000)/SNB_FX!L29 -> 298.95495 | G10: =H10+I10+J10+K10 -> 1121.1286 | H10: =C10*SNB_FX!$L29/SNB_FX!$B29 -> 769.13714 | I10: =D10*SNB_FX!$L29/SNB_FX!$B29 -> 32.820992 | J10: =E10*SNB_FX!$L29/SNB_FX!$B29 -> 38.065473 | K10: =F10*SNB_FX!$L29/SNB_FX!$B29 -> 281.10494 | M10: May 2013 (book) - June 2021 | N10: =B281/B178-1 -> 0.25485106 | O10: =G281/G178-1 -> 0.4423615
A11: 36312 | B11: =C11+D11+E11+F11 -> 1181.4655 | C11: =(SNB_D5_1a_M33!B37/0.968/SNB_FX!L30)/(1-0.06) -> 810.06841 | D11: =D12*C11/C12 -> 34.567631 | E11: =E12*C11/C12 -> 40.091208 | F11: =(SNB_D4_1a!I162/1000+SNB_2E!H163/1000)/SNB_FX!L30 -> 296.7383 | G11: =H11+I11+J11+K11 -> 1137.6829 | H11: =C11*SNB_FX!$L30/SNB_FX!$B30 -> 780.04894 | I11: =D11*SNB_FX!$L30/SNB_FX!$B30 -> 33.286626 | J11: =E11*SNB_FX!$L30/SNB_FX!$B30 -> 38.605511 | K11: =F11*SNB_FX!$L30/SNB_FX!$B30 -> 285.74179 | M11: Yearly growth rate, 1999-2021 | N11: =(B281/B6)^(1/15)-1 -> 0.062031714 | O11: =(G281/G6)^(1/15)-1 -> 0.06394885
A12: 36342 | B12: =C12+D12+E12+F12 -> 1140.0018 | C12: =(SNB_D5_1a_M33!B38/0.968/SNB_FX!L31)/(1-0.06) -> 779.32608 | D12: =D13*C12/C13 -> 33.255779 | E12: =E13*C12/C13 -> 38.569735 | F12: =(SNB_D4_1a!I163/1000+SNB_2E!H164/1000)/SNB_FX!L31 -> 288.85025 | G12: =H12+I12+J12+K12 -> 1101.483 | H12: =C12*SNB_FX!$L31/SNB_FX!$B31 -> 752.99389 | I12: =D12*SNB_FX!$L31/SNB_FX!$B31 -> 32.132119 | J12: =E12*SNB_FX!$L31/SNB_FX!$B31 -> 37.266525 | K12: =F12*SNB_FX!$L31/SNB_FX!$B31 -> 279.09046
A13: 36373 | B13: =C13+D13+E13+F13 -> 1189.9195 | C13: =(SNB_D5_1a_M33!B39/0.968/SNB_FX!L32)/(1-0.06) -> 813.97544 | D13: =D14*C13/C14 -> 34.734353 | E13: =E14*C13/C14 -> 40.284571 | F13: =(SNB_D4_1a!I164/1000+SNB_2E!H165/1000)/SNB_FX!L32 -> 300.92518 | G13: =H13+I13+J13+K13 -> 1121.9581 | H13: =C13*SNB_FX!$L32/SNB_FX!$B32 -> 767.48581 | I13: =D13*SNB_FX!$L32/SNB_FX!$B32 -> 32.750526 | J13: =E13*SNB_FX!$L32/SNB_FX!$B32 -> 37.983747 | K13: =F13*SNB_FX!$L32/SNB_FX!$B32 -> 283.73805
A14: 36404 | B14: =C14+D14+E14+F14 -> 1169.7438 | C14: =(SNB_D5_1a_M33!B40/0.968/SNB_FX!L33)/(1-0.06) -> 798.75577 | D14: =D15*C14/C15 -> 34.084892 | E14: =E15*C14/C15 -> 39.531333 | F14: =(SNB_D4_1a!I165/1000+SNB_2E!H166/1000)/SNB_FX!L33 -> 297.37177 | G14: =H14+I14+J14+K14 -> 1113.5061 | H14: =C14*SNB_FX!$L33/SNB_FX!$B33 -> 760.35405 | I14: =D14*SNB_FX!$L33/SNB_FX!$B33 -> 32.446196 | J14: =E14*SNB_FX!$L33/SNB_FX!$B33 -> 37.630788 | K14: =F14*SNB_FX!$L33/SNB_FX!$B33 -> 283.07505
A15: 36434 | B15: =C15+D15+E15+F15 -> 1219.1928 | C15: =(SNB_D5_1a_M33!B41/0.968/SNB_FX!L34)/(1-0.06) -> 831.28029 | D15: =D16*C15/C16 -> 35.472795 | E15: =E16*C15/C16 -> 41.141008 | F15: =(SNB_D4_1a!I166/1000+SNB_2E!H167/1000)/SNB_FX!L34 -> 311.29874 | G15: =H15+I15+J15+K15 -> 1137.8113 | H15: =C15*SNB_FX!$L34/SNB_FX!$B34 -> 775.79207 | I15: =D15*SNB_FX!$L34/SNB_FX!$B34 -> 33.104974 | J15: =E15*SNB_FX!$L34/SNB_FX!$B34 -> 38.394833 | K15: =F15*SNB_FX!$L34/SNB_FX!$B34 -> 290.51945
A16: 36465 | B16: =C16+D16+E16+F16 -> 1220.8872 | C16: =(SNB_D5_1a_M33!B42/0.968/SNB_FX!L35)/(1-0.06) -> 837.72128 | D16: =D17*C16/C17 -> 35.747647 | E16: =E17*C16/C17 -> 41.45978 | F16: =(SNB_D4_1a!I167/1000+SNB_2E!H168/1000)/SNB_FX!L35 -> 305.95846 | G16: =H16+I16+J16+K16 -> 1179.4277 | H16: =C16*SNB_FX!$L35/SNB_FX!$B35 -> 809.27352 | I16: =D16*SNB_FX!$L35/SNB_FX!$B35 -> 34.533711 | J16: =E16*SNB_FX!$L35/SNB_FX!$B35 -> 40.051868 | K16: =F16*SNB_FX!$L35/SNB_FX!$B35 -> 295.56857
A17: 36495 | B17: =C17+D17+E17+F17 -> 1231.6908 | C17: =(SNB_D5_1a_M33!B43/0.968/SNB_FX!L36)/(1-0.06) -> 849.82471 | D17: =D18*C17/C18 -> 36.264131 | E17: =E18*C17/C18 -> 42.058793 | F17: =(SNB_D4_1a!I168/1000+SNB_2E!H169/1000)/SNB_FX!L36 -> 303.54321 | G17: =H17+I17+J17+K17 -> 1216.8447 | H17: =C17*SNB_FX!$L36/SNB_FX!$B36 -> 839.58138 | I17: =D17*SNB_FX!$L36/SNB_FX!$B36 -> 35.827023 | J17: =E17*SNB_FX!$L36/SNB_FX!$B36 -> 41.551839 | K17: =F17*SNB_FX!$L36/SNB_FX!$B36 -> 299.88446
A18: 36526 | B18: =C18+D18+E18+F18 -> 1248.7241 | C18: =(SNB_D5_1a_M33!B44/0.968/SNB_FX!L37)/(1-0.06) -> 860.69724 | D18: =D19*C18/C19 -> 36.728089 | E18: =E19*C18/C19 -> 42.596887 | F18: =(SNB_D4_1a!I169/1000+SNB_2E!H170/1000)/SNB_FX!L37 -> 308.7019 | G18: =H18+I18+J18+K18 -> 1229.8734 | H18: =C18*SNB_FX!$L37/SNB_FX!$B37 -> 847.70417 | I18: =D18*SNB_FX!$L37/SNB_FX!$B37 -> 36.173642 | J18: =E18*SNB_FX!$L37/SNB_FX!$B37 -> 41.953845 | K18: =F18*SNB_FX!$L37/SNB_FX!$B37 -> 304.04175
A19: 36557 | B19: =C19+D19+E19+F19 -> 1245.9704 | C19: =(SNB_D5_1a_M33!B45/0.968/SNB_FX!L38)/(1-0.06) -> 863.14736 | D19: =D20*C19/C20 -> 36.832642 | E19: =E20*C19/C20 -> 42.718146 | F19: =(SNB_D4_1a!I170/1000+SNB_2E!H171/1000)/SNB_FX!L38 -> 303.27225 | G19: =H19+I19+J19+K19 -> 1265.1225 | H19: =C19*SNB_FX!$L38/SNB_FX!$B38 -> 876.41498 | I19: =D19*SNB_FX!$L38/SNB_FX!$B38 -> 37.398804 | J19: =E19*SNB_FX!$L38/SNB_FX!$B38 -> 43.374776 | K19: =F19*SNB_FX!$L38/SNB_FX!$B38 -> 307.93391
A20: 36586 | B20: =C20+D20+E20+F20 -> 1241.1206 | C20: =(SNB_D5_1a_M33!B46/0.968/SNB_FX!L39)/(1-0.06) -> 859.94178 | D20: =D21*C20/C21 -> 36.695851 | E20: =E21*C20/C21 -> 42.559498 | F20: =(SNB_D4_1a!I171/1000+SNB_2E!H172/1000)/SNB_FX!L39 -> 301.92345 | G20: =H20+I20+J20+K20 -> 1285.2087 | H20: =C20*SNB_FX!$L39/SNB_FX!$B39 -> 890.48938 | I20: =D20*SNB_FX!$L39/SNB_FX!$B39 -> 37.999393 | J20: =E20*SNB_FX!$L39/SNB_FX!$B39 -> 44.071334 | K20: =F20*SNB_FX!$L39/SNB_FX!$B39 -> 312.64864
A21: 36617 | B21: =C21+D21+E21+F21 -> 1250.1165 | C21: =(SNB_D5_1a_M33!B47/0.968/SNB_FX!L40)/(1-0.06) -> 861.614 | D21: =D22*C21/C22 -> 36.767209 | E21: =E22*C21/C22 -> 42.642258 | F21: =(SNB_D4_1a!I172/1000+SNB_2E!H173/1000)/SNB_FX!L40 -> 309.09304 | G21: =H21+I21+J21+K21 -> 1318.9849 | H21: =C21*SNB_FX!$L40/SNB_FX!$B40 -> 909.07996 | I21: =D21*SNB_FX!$L40/SNB_FX!$B40 -> 38.7927 | J21: =E21*SNB_FX!$L40/SNB_FX!$B40 -> 44.991403 | K21: =F21*SNB_FX!$L40/SNB_FX!$B40 -> 326.12085
A22: 36647 | B22: =C22+D22+E22+F22 -> 1188.4146 | C22: =(SNB_D5_1a_M33!B48/0.968/SNB_FX!L41)/(1-0.06) -> 814.66303 | D22: =D23*C22/C23 -> 34.763695 | E22: =E23*C22/C23 -> 40.318601 | F22: =(SNB_D4_1a!I173/1000+SNB_2E!H174/1000)/SNB_FX!L41 -> 298.66931 | G22: =H22+I22+J22+K22 -> 1310.501 | H22: =C22*SNB_FX!$L41/SNB_FX!$B41 -> 898.35376 | I22: =D22*SNB_FX!$L41/SNB_FX!$B41 -> 38.334986 | J22: =E22*SNB_FX!$L41/SNB_FX!$B41 -> 44.460551 | K22: =F22*SNB_FX!$L41/SNB_FX!$B41 -> 329.35175
A23: 36678 | B23: =C23+D23+E23+F23 -> 1219.246 | C23: =(SNB_D5_1a_M33!B49/0.968/SNB_FX!L42)/(1-0.06) -> 838.08295 | D23: =D24*C23/C24 -> 35.763081 | E23: =E24*C23/C24 -> 41.47768 | F23: =(SNB_D4_1a!I174/1000+SNB_2E!H175/1000)/SNB_FX!L42 -> 303.92229 | G23: =H23+I23+J23+K23 -> 1283.421 | H23: =C23*SNB_FX!$L42/SNB_FX!$B42 -> 882.19541 | I23: =D23*SNB_FX!$L42/SNB_FX!$B42 -> 37.645469 | J23: =E23*SNB_FX!$L42/SNB_FX!$B42 -> 43.660856 | K23: =F23*SNB_FX!$L42/SNB_FX!$B42 -> 319.91922
... A74: 38231 | B74: =C74+D74+E74+F74 -> 1648.5486 | C74: =(SNB_D5_1a_M33!B100/0.968/SNB_FX!L93)/(1-0.06) -> 1207.0753 | D74: =D75*C74/C75 -> 51.508901 | E74: =E75*C74/C75 -> 59.739531 | F74: =(SNB_D4_1a!I225/1000+SNB_2E!H226/1000)/SNB_FX!L93 -> 330.22484 | G74: =H74+I74+J74+K74 -> 1349.4146 | H74: =C74*SNB_FX!$L93/SNB_FX!$B93 -> 988.04795 | I74: =D74*SNB_FX!$L93/SNB_FX!$B93 -> 42.16246 | J74: =E74*SNB_FX!$L93/SNB_FX!$B93 -> 48.899619 | K74: =F74*SNB_FX!$L93/SNB_FX!$B93 -> 270.30458
A75: 38261 | B75: =C75+D75+E75+F75 -> 1666.8384 | C75: =(SNB_D5_1a_M33!B101/0.968/SNB_FX!L94)/(1-0.06) -> 1220.9056 | D75: =D76*C75/C76 -> 52.099074 | E75: =E76*C75/C76 -> 60.424008 | F75: =(SNB_D4_1a!I226/1000+SNB_2E!H227/1000)/SNB_FX!L94 -> 333.40972 | G75: =H75+I75+J75+K75 -> 1334.3783 | H75: =C75*SNB_FX!$L94/SNB_FX!$B94 -> 977.38926 | I75: =D75*SNB_FX!$L94/SNB_FX!$B94 -> 41.707627 | J75: =E75*SNB_FX!$L94/SNB_FX!$B94 -> 48.372108 | K75: =F75*SNB_FX!$L94/SNB_FX!$B94 -> 266.90931 | L75: =B75/G75 -> 1.2491498
A76: 38292 | B76: =C76+D76+E76+F76 -> 1739.1477 | C76: =(SNB_D5_1a_M33!B102/0.968/SNB_FX!L95)/(1-0.06) -> 1276.3291 | D76: =D77*C76/C77 -> 54.464131 | E76: =E77*C76/C77 -> 63.166979 | F76: =(SNB_D4_1a!I227/1000+SNB_2E!H228/1000)/SNB_FX!L95 -> 345.18752 | G76: =H76+I76+J76+K76 -> 1340.4954 | H76: =C76*SNB_FX!$L95/SNB_FX!$B95 -> 983.76536 | I76: =D76*SNB_FX!$L95/SNB_FX!$B95 -> 41.979711 | J76: =E76*SNB_FX!$L95/SNB_FX!$B95 -> 48.687668 | K76: =F76*SNB_FX!$L95/SNB_FX!$B95 -> 266.06268 | L76: =B76/G76 -> 1.2973917
A77: 38322 | B77: =C77+D77+E77+F77 -> 1819.919 | C77: =(SNB_D5_1a_M33!B103/0.968/SNB_FX!L96)/(1-0.06) -> 1335.896 | D77: =D78*C77/C78 -> 57.006001 | E77: =E78*C77/C78 -> 66.115015 | F77: =(SNB_D4_1a!I228/1000+SNB_2E!H229/1000)/SNB_FX!L96 -> 360.90195 | G77: =H77+I77+J77+K77 -> 1357.0891 | H77: =C77*SNB_FX!$L96/SNB_FX!$B96 -> 996.15971 | I77: =D77*SNB_FX!$L96/SNB_FX!$B96 -> 42.508609 | J77: =E77*SNB_FX!$L96/SNB_FX!$B96 -> 49.301079 | K77: =F77*SNB_FX!$L96/SNB_FX!$B96 -> 269.11973 | L77: =B77/G77 -> 1.341046
A78: 38353 | B78: =C78+D78+E78+F78 -> 1826.1102 | C78: =(SNB_D5_1a_M33!B104/0.968/SNB_FX!L97)/(1-0.06) -> 1340.2006 | D78: =D79*C78/C79 -> 57.189686 | E78: =E79*C78/C79 -> 66.328052 | F78: =(SNB_D4_1a!I229/1000+SNB_2E!H230/1000)/SNB_FX!L97 -> 362.39195 | G78: =H78+I78+J78+K78 -> 1390.4507 | H78: =C78*SNB_FX!$L97/SNB_FX!$B97 -> 1020.4656 | I78: =D78*SNB_FX!$L97/SNB_FX!$B97 -> 43.545803 | J78: =E78*SNB_FX!$L97/SNB_FX!$B97 -> 50.504006 | K78: =F78*SNB_FX!$L97/SNB_FX!$B97 -> 275.93522 | L78: =B78/G78 -> 1.3133226
A79: 38384 | B79: =C79+D79+E79+F79 -> 1803.8375 | C79: =(SNB_D5_1a_M33!B105/0.968/SNB_FX!L98)/(1-0.06) -> 1327.4133 | D79: =D80*C79/C80 -> 56.644021 | E79: =E80*C79/C80 -> 65.695194 | F79: =(SNB_D4_1a!I230/1000+SNB_2E!H231/1000)/SNB_FX!L98 -> 354.08499 | G79: =H79+I79+J79+K79 -> 1385.7857 | H79: =C79*SNB_FX!$L98/SNB_FX!$B98 -> 1019.7761 | I79: =D79*SNB_FX!$L98/SNB_FX!$B98 -> 43.516379 | J79: =E79*SNB_FX!$L98/SNB_FX!$B98 -> 50.469881 | K79: =F79*SNB_FX!$L98/SNB_FX!$B98 -> 272.02336 | L79: =B79/G79 -> 1.3016713
A80: 38412 | B80: =C80+D80+E80+F80 -> 1925.8069 | C80: =(SNB_D5_1a_M33!B106/0.968/SNB_FX!L99)/(1-0.06) -> 1426.3108 | D80: =D81*C80/C81 -> 60.864223 | E80: =E81*C80/C81 -> 70.589745 | F80: =(SNB_D4_1a!I231/1000+SNB_2E!H232/1000)/SNB_FX!L99 -> 368.04213 | G80: =H80+I80+J80+K80 -> 1458.063 | H80: =C80*SNB_FX!$L99/SNB_FX!$B99 -> 1079.8855 | I80: =D80*SNB_FX!$L99/SNB_FX!$B99 -> 46.081396 | J80: =E80*SNB_FX!$L99/SNB_FX!$B99 -> 53.444763 | K80: =F80*SNB_FX!$L99/SNB_FX!$B99 -> 278.6513 | L80: =B80/G80 -> 1.3207982
A81: 38443 | B81: =C81+D81+E81+F81 -> 1894.5794 | C81: =(SNB_D5_1a_M33!B107/0.968/SNB_FX!L100)/(1-0.06) -> 1399.7709 | D81: =D82*C81/C82 -> 59.731702 | E81: =E82*C81/C82 -> 69.276258 | F81: =(SNB_D4_1a!I232/1000+SNB_2E!H233/1000)/SNB_FX!L100 -> 365.80049 | G81: =H81+I81+J81+K81 -> 1463.2751 | H81: =C81*SNB_FX!$L100/SNB_FX!$B100 -> 1081.1106 | I81: =D81*SNB_FX!$L100/SNB_FX!$B100 -> 46.133676 | J81: =E81*SNB_FX!$L100/SNB_FX!$B100 -> 53.505397 | K81: =F81*SNB_FX!$L100/SNB_FX!$B100 -> 282.52537 | L81: =B81/G81 -> 1.2947527
A82: 38473 | B82: =C82+D82+E82+F82 -> 1928.7249 | C82: =(SNB_D5_1a_M33!B108/0.968/SNB_FX!L101)/(1-0.06) -> 1423.3765 | D82: =D83*C82/C83 -> 60.739009 | E82: =E83*C82/C83 -> 70.444522 | F82: =(SNB_D4_1a!I233/1000+SNB_2E!H234/1000)/SNB_FX!L101 -> 374.16496 | G82: =H82+I82+J82+K82 -> 1519.8323 | H82: =C82*SNB_FX!$L101/SNB_FX!$B101 -> 1121.6184 | I82: =D82*SNB_FX!$L101/SNB_FX!$B101 -> 47.862244 | J82: =E82*SNB_FX!$L101/SNB_FX!$B101 -> 55.510174 | K82: =F82*SNB_FX!$L101/SNB_FX!$B101 -> 294.8414 | L82: =B82/G82 -> 1.269038
A83: 38504 | B83: =C83+D83+E83+F83 -> 1900.2406 | C83: =(SNB_D5_1a_M33!B109/0.968/SNB_FX!L102)/(1-0.06) -> 1410.6696 | D83: =D84*C83/C84 -> 60.196774 | E83: =E84*C83/C84 -> 69.815644 | F83: =(SNB_D4_1a!I234/1000+SNB_2E!H235/1000)/SNB_FX!L102 -> 359.55865 | G83: =H83+I83+J83+K83 -> 1561.8738 | H83: =C83*SNB_FX!$L102/SNB_FX!$B102 -> 1159.4783 | I83: =D83*SNB_FX!$L102/SNB_FX!$B102 -> 49.477819 | J83: =E83*SNB_FX!$L102/SNB_FX!$B102 -> 57.383902 | K83: =F83*SNB_FX!$L102/SNB_FX!$B102 -> 295.53374 | L83: =B83/G83 -> 1.2166416
A84: 38534 | B84: =C84+D84+E84+F84 -> 1886.0717 | C84: =(SNB_D5_1a_M33!B110/0.968/SNB_FX!L103)/(1-0.06) -> 1398.6234 | D84: =D85*C84/C85 -> 59.682735 | E84: =E85*C84/C85 -> 69.219467 | F84: =(SNB_D4_1a!I235/1000+SNB_2E!H236/1000)/SNB_FX!L103 -> 358.54603 | G84: =H84+I84+J84+K84 -> 1566.0169 | H84: =C84*SNB_FX!$L103/SNB_FX!$B103 -> 1161.2856 | I84: =D84*SNB_FX!$L103/SNB_FX!$B103 -> 49.554942 | J84: =E84*SNB_FX!$L103/SNB_FX!$B103 -> 57.473348 | K84: =F84*SNB_FX!$L103/SNB_FX!$B103 -> 297.70297 | L84: =B84/G84 -> 1.204375
A85: 38565 | B85: =C85+D85+E85+F85 -> 1936.1286 | C85: =(SNB_D5_1a_M33!B111/0.968/SNB_FX!L104)/(1-0.06) -> 1437.8705 | D85: =D86*C85/C86 -> 61.357505 | E85: =E86*C85/C86 -> 71.161848 | F85: =(SNB_D4_1a!I236/1000+SNB_2E!H237/1000)/SNB_FX!L104 -> 365.73873 | G85: =H85+I85+J85+K85 -> 1574.1177 | H85: =C85*SNB_FX!$L104/SNB_FX!$B104 -> 1169.0222 | I85: =D85*SNB_FX!$L104/SNB_FX!$B104 -> 49.885082 | J85: =E85*SNB_FX!$L104/SNB_FX!$B104 -> 57.856242 | K85: =F85*SNB_FX!$L104/SNB_FX!$B104 -> 297.35412 | L85: =B85/G85 -> 1.229977
A86: 38596 | B86: =C86+D86+E86+F86 -> 2008.2858 | C86: =(SNB_D5_1a_M33!B112/0.968/SNB_FX!L105)/(1-0.06) -> 1500.7766 | D86: =D87*C86/C87 -> 64.041866 | E86: =E87*C86/C87 -> 74.275145 | F86: =(SNB_D4_1a!I237/1000+SNB_2E!H238/1000)/SNB_FX!L105 -> 369.19212 | G86: =H86+I86+J86+K86 -> 1638.4169 | H86: =C86*SNB_FX!$L105/SNB_FX!$B105 -> 1224.3764 | I86: =D86*SNB_FX!$L105/SNB_FX!$B105 -> 52.247183 | J86: =E86*SNB_FX!$L105/SNB_FX!$B105 -> 60.595783 | K86: =F86*SNB_FX!$L105/SNB_FX!$B105 -> 301.19747 | L86: =B86/G86 -> 1.2257477
... A160: 40848 | B160: =C160+D160+E160+F160 -> 2301.2443 | C160: =(SNB_D5_1a_M33!B186/0.968/SNB_FX!L179)/(1-0.06) -> 1838.1809 | D160: =D161*C160/C161 -> 78.439743 | E160: =E161*C160/C161 -> 90.973664 | F160: =(SNB_D4_1a!I311/1000+SNB_2E!H312/1000)/SNB_FX!L179 -> 293.65008 | G160: =H160+I160+J160+K160 -> 1697.1093 | H160: =C160*SNB_FX!$L179/SNB_FX!$B179 -> 1355.6117 | I160: =D160*SNB_FX!$L179/SNB_FX!$B179 -> 57.84732 | J160: =E160*SNB_FX!$L179/SNB_FX!$B179 -> 67.090769 | K160: =F160*SNB_FX!$L179/SNB_FX!$B179 -> 216.55948 | L160: =B160/G160 -> 1.3559789
A161: 40878 | B161: =C161+D161+E161+F161 -> 2251.6964 | C161: =(SNB_D5_1a_M33!B187/0.968/SNB_FX!L180)/(1-0.06) -> 1804.4415 | D161: 77 | E161: =E162*C161/C162 -> 89.303865 | F161: =(SNB_D4_1a!I312/1000+SNB_2E!H313/1000)/SNB_FX!L180 -> 280.95105 | G161: =H161+I161+J161+K161 -> 1708.7654 | H161: =C161*SNB_FX!$L180/SNB_FX!$B180 -> 1369.353 | I161: =D161*SNB_FX!$L180/SNB_FX!$B180 -> 58.433692 | J161: =E161*SNB_FX!$L180/SNB_FX!$B180 -> 67.770838 | K161: =F161*SNB_FX!$L180/SNB_FX!$B180 -> 213.20789 | L161: =B161/G161 -> 1.3177329
A162: 40909 | B162: =C162+D162+E162+F162 -> 2265.8645 | C162: =(SNB_D5_1a_M33!B188/0.968/SNB_FX!L181)/(1-0.06) -> 1824.0628 | D162: =D161*C162/C161 -> 77.837289 | E162: =E163*C162/C163 -> 90.274945 | F162: =(SNB_D4_1a!I313/1000+SNB_2E!H314/1000)/SNB_FX!L181 -> 273.68949 | G162: =H162+I162+J162+K162 -> 1754.5436 | H162: =C162*SNB_FX!$L181/SNB_FX!$B181 -> 1412.44 | I162: =D162*SNB_FX!$L181/SNB_FX!$B181 -> 60.272323 | J162: =E162*SNB_FX!$L181/SNB_FX!$B181 -> 69.903264 | K162: =F162*SNB_FX!$L181/SNB_FX!$B181 -> 211.928 | L162: =B162/G162 -> 1.2914267
A163: 40940 | B163: =C163+D163+E163+F163 -> 2353.5477 | C163: =(SNB_D5_1a_M33!B189/0.968/SNB_FX!L182)/(1-0.06) -> 1904.1052 | D163: =D162*C163/C162 -> 81.252898 | E163: =E164*C163/C164 -> 94.236335 | F163: =(SNB_D4_1a!I314/1000+SNB_2E!H315/1000)/SNB_FX!L182 -> 273.95328 | G163: =H163+I163+J163+K163 -> 1777.8331 | H163: =C163*SNB_FX!$L182/SNB_FX!$B182 -> 1438.3313 | I163: =D163*SNB_FX!$L182/SNB_FX!$B182 -> 61.377168 | J163: =E163*SNB_FX!$L182/SNB_FX!$B182 -> 71.184653 | K163: =F163*SNB_FX!$L182/SNB_FX!$B182 -> 206.94003 | L163: =B163/G163 -> 1.3238294
A164: 40969 | B164: =C164+D164+E164+F164 -> 2346.5837 | C164: =(SNB_D5_1a_M33!B190/0.968/SNB_FX!L183)/(1-0.06) -> 1901.8478 | D164: =D163*C164/C163 -> 81.15657 | E164: =E165*C164/C165 -> 94.124615 | F164: =(SNB_D4_1a!I315/1000+SNB_2E!H316/1000)/SNB_FX!L183 -> 269.45472 | G164: =H164+I164+J164+K164 -> 1776.6185 | H164: =C164*SNB_FX!$L183/SNB_FX!$B183 -> 1439.9052 | I164: =D164*SNB_FX!$L183/SNB_FX!$B183 -> 61.44433 | J164: =E164*SNB_FX!$L183/SNB_FX!$B183 -> 71.262548 | K164: =F164*SNB_FX!$L183/SNB_FX!$B183 -> 204.00647 | L164: =B164/G164 -> 1.3208146
A165: 41000 | B165: =C165+D165+E165+F165 -> 2371.3505 | C165: =(SNB_D5_1a_M33!B191/0.968/SNB_FX!L184)/(1-0.06) -> 1927.3216 | D165: =D164*C165/C164 -> 82.2436 | E165: =E166*C165/C166 -> 95.385342 | F165: =(SNB_D4_1a!I316/1000+SNB_2E!H317/1000)/SNB_FX!L184 -> 266.39996 | G165: =H165+I165+J165+K165 -> 1802.0844 | H165: =C165*SNB_FX!$L184/SNB_FX!$B184 -> 1464.649 | I165: =D165*SNB_FX!$L184/SNB_FX!$B184 -> 62.50021 | J165: =E165*SNB_FX!$L184/SNB_FX!$B184 -> 72.487147 | K165: =F165*SNB_FX!$L184/SNB_FX!$B184 -> 202.44801 | L165: =B165/G165 -> 1.3158932
A166: 41030 | B166: =C166+D166+E166+F166 -> 2304.2285 | C166: =(SNB_D5_1a_M33!B192/0.968/SNB_FX!L185)/(1-0.06) -> 1866.7028 | D166: =D165*C166/C165 -> 79.656844 | E166: =E167*C166/C167 -> 92.385247 | F166: =(SNB_D4_1a!I317/1000+SNB_2E!H318/1000)/SNB_FX!L185 -> 265.48363 | G166: =H166+I166+J166+K166 -> 1798.7638 | H166: =C166*SNB_FX!$L185/SNB_FX!$B185 -> 1457.2154 | I166: =D166*SNB_FX!$L185/SNB_FX!$B185 -> 62.183002 | J166: =E166*SNB_FX!$L185/SNB_FX!$B185 -> 72.119252 | K166: =F166*SNB_FX!$L185/SNB_FX!$B185 -> 207.24609 | L166: =B166/G166 -> 1.2810067
A167: 41061 | B167: =C167+D167+E167+F167 -> 2219.2035 | C167: =(SNB_D5_1a_M33!B193/0.968/SNB_FX!L186)/(1-0.06) -> 1804.5898 | D167: =D166*C167/C166 -> 77.00633 | E167: =E168*C167/C168 -> 89.311206 | F167: =(SNB_D4_1a!I318/1000+SNB_2E!H319/1000)/SNB_FX!L186 -> 248.29612 | G167: =H167+I167+J167+K167 -> 1770.9281 | H167: =C167*SNB_FX!$L186/SNB_FX!$B186 -> 1440.0657 | I167: =D167*SNB_FX!$L186/SNB_FX!$B186 -> 61.451179 | J167: =E167*SNB_FX!$L186/SNB_FX!$B186 -> 71.270491 | K167: =F167*SNB_FX!$L186/SNB_FX!$B186 -> 198.14072 | L167: =B167/G167 -> 1.2531302
A168: 41091 | B168: =C168+D168+E168+F168 -> 2222.1357 | C168: =(SNB_D5_1a_M33!B194/0.968/SNB_FX!L187)/(1-0.06) -> 1818.228 | D168: =D167*C168/C167 -> 77.588304 | E168: =E169*C168/C169 -> 89.986174 | F168: =(SNB_D4_1a!I319/1000+SNB_2E!H320/1000)/SNB_FX!L187 -> 236.3332 | G168: =H168+I168+J168+K168 -> 1806.9423 | H168: =C168*SNB_FX!$L187/SNB_FX!$B187 -> 1478.5025 | I168: =D168*SNB_FX!$L187/SNB_FX!$B187 -> 63.091372 | J168: =E168*SNB_FX!$L187/SNB_FX!$B187 -> 73.172771 | K168: =F168*SNB_FX!$L187/SNB_FX!$B187 -> 192.17569 | L168: =B168/G168 -> 1.2297768
A169: 41122 | B169: =C169+D169+E169+F169 -> 2234.829 | C169: =(SNB_D5_1a_M33!B195/0.968/SNB_FX!L188)/(1-0.06) -> 1830.8766 | D169: =D168*C169/C168 -> 78.128053 | E169: =E170*C169/C170 -> 90.61217 | F169: =(SNB_D4_1a!I320/1000+SNB_2E!H321/1000)/SNB_FX!L188 -> 235.21218 | G169: =H169+I169+J169+K169 -> 1802.0414 | H169: =C169*SNB_FX!$L188/SNB_FX!$B188 -> 1476.3167 | I169: =D169*SNB_FX!$L188/SNB_FX!$B188 -> 62.998101 | J169: =E169*SNB_FX!$L188/SNB_FX!$B188 -> 73.064596 | K169: =F169*SNB_FX!$L188/SNB_FX!$B188 -> 189.66198 | L169: =B169/G169 -> 1.2401652
A170: 41153 | B170: =C170+D170+E170+F170 -> 2312.8434 | C170: =(SNB_D5_1a_M33!B196/0.968/SNB_FX!L189)/(1-0.06) -> 1903.8605 | D170: =D169*C170/C169 -> 81.242457 | E170: =E171*C170/C171 -> 94.224225 | F170: =(SNB_D4_1a!I321/1000+SNB_2E!H322/1000)/SNB_FX!L189 -> 233.51621 | G170: =H170+I170+J170+K170 -> 1799.3459 | H170: =C170*SNB_FX!$L189/SNB_FX!$B189 -> 1481.1654 | I170: =D170*SNB_FX!$L189/SNB_FX!$B189 -> 63.205005 | J170: =E170*SNB_FX!$L189/SNB_FX!$B189 -> 73.304561 | K170: =F170*SNB_FX!$L189/SNB_FX!$B189 -> 181.67094 | L170: =B170/G170 -> 1.2853801
A171: 41183 | B171: =C171+D171+E171+F171 -> 2322.0632 | C171: =(SNB_D5_1a_M33!B197/0.968/SNB_FX!L190)/(1-0.06) -> 1917.4349 | D171: =D170*C171/C170 -> 81.821709 | E171: =E172*C171/C172 -> 94.896037 | F171: =(SNB_D4_1a!I322/1000+SNB_2E!H323/1000)/SNB_FX!L190 -> 227.91059 | G171: =H171+I171+J171+K171 -> 1790.3956 | H171: =C171*SNB_FX!$L190/SNB_FX!$B190 -> 1478.4124 | I171: =D171*SNB_FX!$L190/SNB_FX!$B190 -> 63.087527 | J171: =E171*SNB_FX!$L190/SNB_FX!$B190 -> 73.168312 | K171: =F171*SNB_FX!$L190/SNB_FX!$B190 -> 175.72739 | L171: =B171/G171 -> 1.2969554
A172: 41214 | B172: =C172+D172+E172+F172 -> 2311.8517 | C172: =(SNB_D5_1a_M33!B198/0.968/SNB_FX!L191)/(1-0.06) -> 1911.7913 | D172: =D171*C172/C171 -> 81.580882 | E172: =E173*C172/C173 -> 94.616728 | F172: =(SNB_D4_1a!I323/1000+SNB_2E!H324/1000)/SNB_FX!L191 -> 223.86286 | G172: =H172+I172+J172+K172 -> 1801.6024 | H172: =C172*SNB_FX!$L191/SNB_FX!$B191 -> 1489.8393 | I172: =D172*SNB_FX!$L191/SNB_FX!$B191 -> 63.575145 | J172: =E172*SNB_FX!$L191/SNB_FX!$B191 -> 73.733846 | K172: =F172*SNB_FX!$L191/SNB_FX!$B191 -> 174.45403 | L172: =B172/G172 -> 1.2832198
A173: 41244 | B173: =C173+D173+E173+F173 -> 2369.8748 | C173: =(SNB_D5_1a_M33!B199/0.968/SNB_FX!L192) -> 1967.9492 | D173: =D172*C173/C172 -> 83.97728 | E173: =E174*C173/C174 -> 97.396047 | F173: =(SNB_D4_1a!I324/1000+SNB_2E!H325/1000)/SNB_FX!L192 -> 220.5523 | G173: =H173+I173+J173+K173 -> 1806.3656 | H173: =C173*SNB_FX!$L192/SNB_FX!$B192 -> 1500.0099 | I173: =D173*SNB_FX!$L192/SNB_FX!$B192 -> 64.009148 | J173: =E173*SNB_FX!$L192/SNB_FX!$B192 -> 74.237199 | K173: =F173*SNB_FX!$L192/SNB_FX!$B192 -> 168.10934 | L173: =B173/G173 -> 1.3119575
A174: 41275 | B174: =C174+D174+E174+F174 -> 2399.8648 | C174: =(SNB_D5_1a_M33!B200/0.968/SNB_FX!L193) -> 2002.1385 | D174: =D173*C174/C173 -> 85.43622 | E174: =E175*C174/C175 -> 99.088112 | F174: =(SNB_D4_1a!I325/1000+SNB_2E!H326/1000)/SNB_FX!L193 -> 213.20203 | G174: =H174+I174+J174+K174 -> 1805.9569 | H174: =C174*SNB_FX!$L193/SNB_FX!$B193 -> 1506.6581 | I174: =D174*SNB_FX!$L193/SNB_FX!$B193 -> 64.292843 | J174: =E174*SNB_FX!$L193/SNB_FX!$B193 -> 74.566225 | K174: =F174*SNB_FX!$L193/SNB_FX!$B193 -> 160.43974 | L174: =B174/G174 -> 1.3288605
A175: 41306 | B175: =C175+D175+E175+F175 -> 2437.4738 | C175: =(SNB_D5_1a_M33!B201/0.968/SNB_FX!L194) -> 2036.1752 | D175: =D174*C175/C174 -> 86.888654 | E175: =E176*C175/C176 -> 100.77263 | F175: =(SNB_D4_1a!I326/1000+SNB_2E!H327/1000)/SNB_FX!L194 -> 213.63725 | G175: =H175+I175+J175+K175 -> 1823.844 | H175: =C175*SNB_FX!$L194/SNB_FX!$B194 -> 1523.5717 | I175: =D175*SNB_FX!$L194/SNB_FX!$B194 -> 65.014587 | J175: =E175*SNB_FX!$L194/SNB_FX!$B194 -> 75.403297 | K175: =F175*SNB_FX!$L194/SNB_FX!$B194 -> 159.85445 | L175: =B175/G175 -> 1.3364486
A176: 41334 | B176: =C176+D176+E176+F176 -> 2404.8151 | C176: =(SNB_D5_1a_M33!B202/0.968/SNB_FX!L195) -> 2007.9458 | D176: =D175*C176/C175 -> 85.684035 | E176: =E177*C176/C177 -> 99.375526 | F176: =(SNB_D4_1a!I327/1000+SNB_2E!H328/1000)/SNB_FX!L195 -> 211.80973 | G176: =H176+I176+J176+K176 -> 1854.9862 | H176: =C176*SNB_FX!$L195/SNB_FX!$B195 -> 1548.8558 | I176: =D176*SNB_FX!$L195/SNB_FX!$B195 -> 66.093524 | J176: =E176*SNB_FX!$L195/SNB_FX!$B195 -> 76.654638 | K176: =F176*SNB_FX!$L195/SNB_FX!$B195 -> 163.38226 | L176: =B176/G176 -> 1.2964059
A177: 41365 | B177: =C177+D177+E177+F177 -> 2399.132 | C177: =(SNB_D5_1a_M33!B203/0.968/SNB_FX!L196) -> 2003.209 | D177: =D176*C177/C176 -> 85.481904 | E177: =E178*C177/C178 -> 99.141096 | F177: =(SNB_D4_1a!I328/1000+SNB_2E!H329/1000)/SNB_FX!L196 -> 211.29999 | G177: =H177+I177+J177+K177 -> 1844.2909 | H177: =C177*SNB_FX!$L196/SNB_FX!$B196 -> 1539.932 | I177: =D177*SNB_FX!$L196/SNB_FX!$B196 -> 65.712724 | J177: =E177*SNB_FX!$L196/SNB_FX!$B196 -> 76.21299 | K177: =F177*SNB_FX!$L196/SNB_FX!$B196 -> 162.43319 | L177: =B177/G177 -> 1.3008425
A178: 41395 | B178: =C178+D178+E178+F178 -> 2411.8176 | C178: =(SNB_D5_1a_M33!B204/0.968/SNB_FX!L197) -> 2020.5637 | D178: =D177*C178/C177 -> 86.222472 | E178: 100 | F178: =(SNB_D4_1a!I329/1000+SNB_2E!H330/1000)/SNB_FX!L197 -> 205.03141 | G178: =H178+I178+J178+K178 -> 1856.5902 | H178: =C178*SNB_FX!$L197/SNB_FX!$B197 -> 1555.4073 | I178: =D178*SNB_FX!$L197/SNB_FX!$B197 -> 66.373094 | J178: =E178*SNB_FX!$L197/SNB_FX!$B197 -> 76.978881 | K178: =F178*SNB_FX!$L197/SNB_FX!$B197 -> 157.83089 | L178: =B178/G178 -> 1.2990576
A179: 41426 | B179: =C179+D179+E179+F179 -> 2355.4968 | C179: =(SNB_D5_1a_M33!B205/0.968/SNB_FX!L198) -> 1968.1498 | D179: =D178*C179/C178 -> 83.985838 | E179: =E178*C179/C178 -> 97.405973 | F179: =(SNB_D4_1a!I330/1000+SNB_2E!H331/1000)/SNB_FX!L198 -> 205.95526 | G179: =H179+I179+J179+K179 -> 1785.446 | H179: =C179*SNB_FX!$L198/SNB_FX!$B198 -> 1491.8403 | I179: =D179*SNB_FX!$L198/SNB_FX!$B198 -> 63.66053 | J179: =E179*SNB_FX!$L198/SNB_FX!$B198 -> 73.832874 | K179: =F179*SNB_FX!$L198/SNB_FX!$B198 -> 156.11228 | L179: =B179/G179 -> 1.3192765
A180: 41456 | B180: =C180+D180+E180+F180 -> 2334.8746 | C180: =(SNB_D5_1a_M33!B206/0.968/SNB_FX!L199) -> 1954.2197 | D180: =D179*C180/C179 -> 83.391407 | E180: =E179*C180/C179 -> 96.716558 | F180: =(SNB_D4_1a!I331/1000+SNB_2E!H332/1000)/SNB_FX!L199 -> 200.54697 | G180: =H180+I180+J180+K180 -> 1784.9591 | H180: =C180*SNB_FX!$L199/SNB_FX!$B199 -> 1493.957 | I180: =D180*SNB_FX!$L199/SNB_FX!$B199 -> 63.750856 | J180: =E180*SNB_FX!$L199/SNB_FX!$B199 -> 73.937634 | K180: =F180*SNB_FX!$L199/SNB_FX!$B199 -> 153.31365 | L180: =B180/G180 -> 1.3080829
A181: 41487 | B181: =C181+D181+E181+F181 -> 2350.643 | C181: =(SNB_D5_1a_M33!B207/0.968/SNB_FX!L200) -> 1962.9504 | D181: =D180*C181/C180 -> 83.763968 | E181: =E180*C181/C180 -> 97.14865 | F181: =(SNB_D4_1a!I332/1000+SNB_2E!H333/1000)/SNB_FX!L200 -> 206.78001 | G181: =H181+I181+J181+K181 -> 1765.5551 | H181: =C181*SNB_FX!$L200/SNB_FX!$B200 -> 1474.3613 | I181: =D181*SNB_FX!$L200/SNB_FX!$B200 -> 62.914658 | J181: =E181*SNB_FX!$L200/SNB_FX!$B200 -> 72.96782 | K181: =F181*SNB_FX!$L200/SNB_FX!$B200 -> 155.31133 | L181: =B181/G181 -> 1.3313903
A182: 41518 | B182: =C182+D182+E182+F182 -> 2340.3782 | C182: =(SNB_D5_1a_M33!B208/0.968/SNB_FX!L201) -> 1960.3153 | D182: =D181*C182/C181 -> 83.651523 | E182: =E181*C182/C181 -> 97.018238 | F182: =(SNB_D4_1a!I333/1000+SNB_2E!H334/1000)/SNB_FX!L201 -> 199.39312 | G182: =H182+I182+J182+K182 -> 1753.4816 | H182: =C182*SNB_FX!$L201/SNB_FX!$B201 -> 1468.7271 | I182: =D182*SNB_FX!$L201/SNB_FX!$B201 -> 62.674232 | J182: =E182*SNB_FX!$L201/SNB_FX!$B201 -> 72.688976 | K182: =F182*SNB_FX!$L201/SNB_FX!$B201 -> 149.39131 | L182: =B182/G182 -> 1.3347036
A183: 41548 | B183: =C183+D183+E183+F183 -> 2431.1848 | C183: =(SNB_D5_1a_M33!B209/0.968/SNB_FX!L202) -> 2041.9246 | D183: =D182*C183/C182 -> 87.133993 | E183: =E182*C183/C182 -> 101.05717 | F183: =(SNB_D4_1a!I334/1000+SNB_2E!H335/1000)/SNB_FX!L202 -> 201.06902 | G183: =H183+I183+J183+K183 -> 1782.2239 | H183: =C183*SNB_FX!$L202/SNB_FX!$B202 -> 1496.8697 | I183: =D183*SNB_FX!$L202/SNB_FX!$B202 -> 63.875147 | J183: =E183*SNB_FX!$L202/SNB_FX!$B202 -> 74.081785 | K183: =F183*SNB_FX!$L202/SNB_FX!$B202 -> 147.39727 | L183: =B183/G183 -> 1.3641298
A184: 41579 | B184: =C184+D184+E184+F184 -> 2415.3204 | C184: =(SNB_D5_1a_M33!B210/0.968/SNB_FX!L203) -> 2034.1515 | D184: =D183*C184/C183 -> 86.802295 | E184: =E183*C184/C183 -> 100.67247 | F184: =(SNB_D4_1a!I335/1000+SNB_2E!H336/1000)/SNB_FX!L203 -> 193.69413 | G184: =H184+I184+J184+K184 -> 1789.6781 | H184: =C184*SNB_FX!$L203/SNB_FX!$B203 -> 1507.2437 | I184: =D184*SNB_FX!$L203/SNB_FX!$B203 -> 64.31783 | J184: =E184*SNB_FX!$L203/SNB_FX!$B203 -> 74.595205 | K184: =F184*SNB_FX!$L203/SNB_FX!$B203 -> 143.52139 | L184: =B184/G184 -> 1.3495837
A185: 41609 | B185: =C185+D185+E185+F185 -> 2423.484 | C185: =(SNB_D5_1a_M33!B211/0.968/SNB_FX!L204) -> 2038.3345 | D185: =D184*C185/C184 -> 86.980797 | E185: =E184*C185/C184 -> 100.8795 | F185: =(SNB_D4_1a!I336/1000+SNB_2E!H337/1000)/SNB_FX!L204 -> 197.2892 | G185: =H185+I185+J185+K185 -> 1769.1888 | H185: =C185*SNB_FX!$L204/SNB_FX!$B204 -> 1488.0225 | I185: =D185*SNB_FX!$L204/SNB_FX!$B204 -> 63.497615 | J185: =E185*SNB_FX!$L204/SNB_FX!$B204 -> 73.643928 | K185: =F185*SNB_FX!$L204/SNB_FX!$B204 -> 144.02482 | L185: =B185/G185 -> 1.3698278
A186: 41640 | B186: =C186+D186+E186+F186 -> 2394.7917 | C186: =(SNB_D5_1a_M33!B212/0.968/SNB_FX!L205) -> 2013.2388 | D186: =D185*C186/C185 -> 85.909898 | E186: =E185*C186/C185 -> 99.637479 | F186: =(SNB_D4_1a!I337/1000+SNB_2E!H338/1000)/SNB_FX!L205 -> 196.00553 | G186: =H186+I186+J186+K186 -> 1757.3865 | H186: =C186*SNB_FX!$L205/SNB_FX!$B205 -> 1477.3889 | I186: =D186*SNB_FX!$L205/SNB_FX!$B205 -> 63.043854 | J186: =E186*SNB_FX!$L205/SNB_FX!$B205 -> 73.11766 | K186: =F186*SNB_FX!$L205/SNB_FX!$B205 -> 143.83609 | L186: =B186/G186 -> 1.3627006
A187: 41671 | B187: =C187+D187+E187+F187 -> 2413.5969 | C187: =(SNB_D5_1a_M33!B213/0.968/SNB_FX!L206) -> 2033.4973 | D187: =D186*C187/C186 -> 86.774381 | E187: =E186*C187/C186 -> 100.6401 | F187: =(SNB_D4_1a!I338/1000+SNB_2E!H339/1000)/SNB_FX!L206 -> 192.68508 | G187: =H187+I187+J187+K187 -> 1767.1648 | H187: =C187*SNB_FX!$L206/SNB_FX!$B206 -> 1488.867 | I187: =D187*SNB_FX!$L206/SNB_FX!$B206 -> 63.533654 | J187: =E187*SNB_FX!$L206/SNB_FX!$B206 -> 73.685725 | K187: =F187*SNB_FX!$L206/SNB_FX!$B206 -> 141.07836 | L187: =B187/G187 -> 1.3658018
A188: 41699 | B188: =C188+D188+E188+F188 -> 2416.5569 | C188: =(SNB_D5_1a_M33!B214/0.968/SNB_FX!L207) -> 2034.0927 | D188: =D187*C188/C187 -> 86.799787 | E188: =E187*C188/C187 -> 100.66956 | F188: =(SNB_D4_1a!I339/1000+SNB_2E!H340/1000)/SNB_FX!L207 -> 194.99489 | G188: =H188+I188+J188+K188 -> 1748.422 | H188: =C188*SNB_FX!$L207/SNB_FX!$B207 -> 1471.7023 | I188: =D188*SNB_FX!$L207/SNB_FX!$B207 -> 62.801193 | J188: =E188*SNB_FX!$L207/SNB_FX!$B207 -> 72.836223 | K188: =F188*SNB_FX!$L207/SNB_FX!$B207 -> 141.08228 | L188: =B188/G188 -> 1.382136
A189: 41730 | B189: =C189+D189+E189+F189 -> 2434.6013 | C189: =(SNB_D5_1a_M33!B215/0.968/SNB_FX!L208) -> 2051.2269 | D189: =D188*C189/C188 -> 87.530948 | E189: =E188*C189/C188 -> 101.51756 | F189: =(SNB_D4_1a!I340/1000+SNB_2E!H341/1000)/SNB_FX!L208 -> 194.32586 | G189: =H189+I189+J189+K189 -> 1762.5946 | H189: =C189*SNB_FX!$L208/SNB_FX!$B208 -> 1485.0405 | I189: =D189*SNB_FX!$L208/SNB_FX!$B208 -> 63.370367 | J189: =E189*SNB_FX!$L208/SNB_FX!$B208 -> 73.496347 | K189: =F189*SNB_FX!$L208/SNB_FX!$B208 -> 140.68739 | L189: =B189/G189 -> 1.3812599
A190: 41760 | B190: =C190+D190+E190+F190 -> 2475.6075 | C190: =(SNB_D5_1a_M33!B216/0.968/SNB_FX!L209) -> 2088.8361 | D190: =D189*C190/C189 -> 89.135824 | E190: =E189*C190/C189 -> 103.37888 | F190: =(SNB_D4_1a!I341/1000+SNB_2E!H342/1000)/SNB_FX!L209 -> 194.25676 | G190: =H190+I190+J190+K190 -> 1801.327 | H190: =C190*SNB_FX!$L209/SNB_FX!$B209 -> 1519.9004 | I190: =D190*SNB_FX!$L209/SNB_FX!$B209 -> 64.857925 | J190: =E190*SNB_FX!$L209/SNB_FX!$B209 -> 75.221602 | K190: =F190*SNB_FX!$L209/SNB_FX!$B209 -> 141.3471 | L190: =B190/G190 -> 1.3743243
A191: 41791 | B191: =C191+D191+E191+F191 -> 2461.9887 | C191: =(SNB_D5_1a_M33!B217/0.968/SNB_FX!L210) -> 2079.5599 | D191: =D190*C191/C190 -> 88.739987 | E191: =E190*C191/C190 -> 102.91979 | F191: =(SNB_D4_1a!I342/1000+SNB_2E!H343/1000)/SNB_FX!L210 -> 190.76897 | G191: =H191+I191+J191+K191 -> 1810.9694 | H191: =C191*SNB_FX!$L210/SNB_FX!$B210 -> 1529.6656 | I191: =D191*SNB_FX!$L210/SNB_FX!$B210 -> 65.274631 | J191: =E191*SNB_FX!$L210/SNB_FX!$B210 -> 75.704894 | K191: =F191*SNB_FX!$L210/SNB_FX!$B210 -> 140.32428 | L191: =B191/G191 -> 1.3594866
A192: 41821 | B192: =C192+D192+E192+F192 -> 2471.0706 | C192: =(SNB_D5_1a_M33!B218/0.968/SNB_FX!L211) -> 2090.4569 | D192: =D191*C192/C191 -> 89.204988 | E192: =E191*C192/C191 -> 103.45909 | F192: =(SNB.MONA!B26/1000)/SNB_FX!L211 -> 187.9496 | G192: =H192+I192+J192+K192 -> 1824.1179 | H192: =C192*SNB_FX!$L211/SNB_FX!$B211 -> 1543.1529 | I192: =D192*SNB_FX!$L211/SNB_FX!$B211 -> 65.850168 | J192: =E192*SNB_FX!$L211/SNB_FX!$B211 -> 76.372396 | K192: =F192*SNB_FX!$L211/SNB_FX!$B211 -> 138.74239 | L192: =B192/G192 -> 1.3546661
A193: 41852 | B193: =C193+D193+E193+F193 -> 2489.1188 | C193: =(SNB_D5_1a_M33!B219/0.968/SNB_FX!L212) -> 2108.605 | D193: =D192*C193/C192 -> 89.979411 | E193: =E192*C193/C192 -> 104.35726 | F193: =(SNB.MONA!B27/1000)/SNB_FX!L212 -> 186.17718 | G193: =H193+I193+J193+K193 -> 1868.6363 | H193: =C193*SNB_FX!$L212/SNB_FX!$B212 -> 1582.9762 | I193: =D193*SNB_FX!$L212/SNB_FX!$B212 -> 67.549524 | J193: =E193*SNB_FX!$L212/SNB_FX!$B212 -> 78.343293 | K193: =F193*SNB_FX!$L212/SNB_FX!$B212 -> 139.76731 | L193: =B193/G193 -> 1.332051
A194: 41883 | B194: =C194+D194+E194+F194 -> 2438.464 | C194: =(SNB_D5_1a_M33!B220/0.968/SNB_FX!L213) -> 2069.6034 | D194: =D193*C194/C193 -> 88.315117 | E194: =E193*C194/C193 -> 102.42703 | F194: =(SNB.MONA!B28/1000)/SNB_FX!L213 -> 178.11845 | G194: =H194+I194+J194+K194 -> 1888.6637 | H194: =C194*SNB_FX!$L213/SNB_FX!$B213 -> 1602.9701 | I194: =D194*SNB_FX!$L213/SNB_FX!$B213 -> 68.402716 | J194: =E194*SNB_FX!$L213/SNB_FX!$B213 -> 79.332817 | K194: =F194*SNB_FX!$L213/SNB_FX!$B213 -> 137.9581 | L194: =B194/G194 -> 1.2911054
A195: 41913 | B195: =C195+D195+E195+F195 -> 2399.6734 | C195: =(SNB_D5_1a_M33!B221/0.968/SNB_FX!L214) -> 2041.9098 | D195: =D194*C195/C194 -> 87.133363 | E195: =E194*C195/C194 -> 101.05644 | F195: =(SNB.MONA!B29/1000)/SNB_FX!L214 -> 169.5738 | G195: =H195+I195+J195+K195 -> 1892.6386 | H195: =C195*SNB_FX!$L214/SNB_FX!$B214 -> 1610.468 | I195: =D195*SNB_FX!$L214/SNB_FX!$B214 -> 68.722671 | J195: =E195*SNB_FX!$L214/SNB_FX!$B214 -> 79.703897 | K195: =F195*SNB_FX!$L214/SNB_FX!$B214 -> 133.744 | L195: =B195/G195 -> 1.2678984
A196: 41944 | B196: =C196+D196+E196+F196 -> 2350.7766 | C196: =(SNB_D5_1a_M33!B222/0.968/SNB_FX!L215) -> 2004.6531 | D196: =D195*C196/C195 -> 85.543528 | E196: =E195*C196/C195 -> 99.212567 | F196: =(SNB.MONA!B30/1000)/SNB_FX!L215 -> 161.36741 | G196: =H196+I196+J196+K196 -> 1885.5473 | H196: =C196*SNB_FX!$L215/SNB_FX!$B215 -> 1607.9232 | I196: =D196*SNB_FX!$L215/SNB_FX!$B215 -> 68.614075 | J196: =E196*SNB_FX!$L215/SNB_FX!$B215 -> 79.577949 | K196: =F196*SNB_FX!$L215/SNB_FX!$B215 -> 129.43206 | L196: =B196/G196 -> 1.2467344
A197: 41974 | B197: =C197+D197+E197+F197 -> 2340.5341 | C197: =(SNB_D5_1a_M33!B223/0.968/SNB_FX!L216) -> 1990.9567 | D197: =D196*C197/C196 -> 84.959068 | E197: =E196*C197/C196 -> 98.534716 | F197: =(SNB.MONA!B31/1000)/SNB_FX!L216 -> 166.08362 | G197: =H197+I197+J197+K197 -> 1899.6401 | H197: =C197*SNB_FX!$L216/SNB_FX!$B216 -> 1615.9137 | I197: =D197*SNB_FX!$L216/SNB_FX!$B216 -> 68.955052 | J197: =E197*SNB_FX!$L216/SNB_FX!$B216 -> 79.973411 | K197: =F197*SNB_FX!$L216/SNB_FX!$B216 -> 134.7979 | L197: =B197/G197 -> 1.2320935
A198: 42005 | B198: =C198+D198+E198+F198 -> 2220.3269 | C198: =(SNB_D5_1a_M33!B224/0.968/SNB_FX!L217) -> 1893.6771 | D198: =D197*C198/C197 -> 80.807905 | E198: =E197*C198/C197 -> 93.720236 | F198: =(SNB.MONA!B32/1000)/SNB_FX!L217 -> 152.12163 | G198: =H198+I198+J198+K198 -> 1904.7546 | H198: =C198*SNB_FX!$L217/SNB_FX!$B217 -> 1624.5311 | I198: =D198*SNB_FX!$L217/SNB_FX!$B217 -> 69.322779 | J198: =E198*SNB_FX!$L217/SNB_FX!$B217 -> 80.399897 | K198: =F198*SNB_FX!$L217/SNB_FX!$B217 -> 130.50077 | L198: =B198/G198 -> 1.1656761
A199: 42036 | B199: =C199+D199+E199+F199 -> 2367.8302 | C199: =(SNB_D5_1a_M33!B225/0.968/SNB_FX!L218) -> 2027.1046 | D199: =D198*C199/C198 -> 86.501587 | E199: =E198*C199/C198 -> 100.32371 | F199: =(SNB.MONA!B33/1000)/SNB_FX!L218 -> 153.90035 | G199: =H199+I199+J199+K199 -> 2084.7516 | H199: =C199*SNB_FX!$L218/SNB_FX!$B218 -> 1784.7603 | I199: =D199*SNB_FX!$L218/SNB_FX!$B218 -> 76.160157 | J199: =E199*SNB_FX!$L218/SNB_FX!$B218 -> 88.329822 | K199: =F199*SNB_FX!$L218/SNB_FX!$B218 -> 135.50127 | L199: =B199/G199 -> 1.1357853
A200: 42064 | B200: =C200+D200+E200+F200 -> 2262.7899 | C200: =(SNB_D5_1a_M33!B226/0.968/SNB_FX!L219) -> 1937.7973 | D200: =D199*C200/C199 -> 82.690622 | E200: =E199*C200/C199 -> 95.903794 | F200: =(SNB.MONA!B34/1000)/SNB_FX!L219 -> 146.39824 | G200: =H200+I200+J200+K200 -> 2089.812 | H200: =C200*SNB_FX!$L219/SNB_FX!$B219 -> 1789.6633 | I200: =D200*SNB_FX!$L219/SNB_FX!$B219 -> 76.369376 | J200: =E200*SNB_FX!$L219/SNB_FX!$B219 -> 88.572473 | K200: =F200*SNB_FX!$L219/SNB_FX!$B219 -> 135.2069 | L200: =B200/G200 -> 1.082772
A201: 42095 | B201: =C201+D201+E201+F201 -> 2336.6769 | C201: =(SNB_D5_1a_M33!B227/0.968/SNB_FX!L220) -> 2004.4783 | D201: =D200*C201/C200 -> 85.536065 | E201: =E200*C201/C200 -> 99.203912 | F201: =(SNB.MONA!B35/1000)/SNB_FX!L220 -> 147.45868 | G201: =H201+I201+J201+K201 -> 2165.3986 | H201: =C201*SNB_FX!$L220/SNB_FX!$B220 -> 1857.5501 | I201: =D201*SNB_FX!$L220/SNB_FX!$B220 -> 79.266277 | J201: =E201*SNB_FX!$L220/SNB_FX!$B220 -> 91.932271 | K201: =F201*SNB_FX!$L220/SNB_FX!$B220 -> 136.64997 | L201: =B201/G201 -> 1.0790978
A202: 42125 | B202: =C202+D202+E202+F202 -> 2419.4517 | C202: =(SNB_D5_1a_M33!B228/0.968/SNB_FX!L221) -> 2078.2183 | D202: =D201*C202/C201 -> 88.682735 | E202: =E201*C202/C201 -> 102.85339 | F202: =(SNB.MONA!B36/1000)/SNB_FX!L221 -> 149.69729 | G202: =H202+I202+J202+K202 -> 2167.6872 | H202: =C202*SNB_FX!$L221/SNB_FX!$B221 -> 1861.962 | I202: =D202*SNB_FX!$L221/SNB_FX!$B221 -> 79.454545 | J202: =E202*SNB_FX!$L221/SNB_FX!$B221 -> 92.150622 | K202: =F202*SNB_FX!$L221/SNB_FX!$B221 -> 134.12002 | L202: =B202/G202 -> 1.1161443
A203: 42156 | B203: =C203+D203+E203+F203 -> 2384.4931 | C203: =(SNB_D5_1a_M33!B229/0.968/SNB_FX!L222) -> 2050.8206 | D203: =D202*C203/C202 -> 87.51361 | E203: =E202*C203/C202 -> 101.49745 | F203: =(SNB.MONA!B37/1000)/SNB_FX!L222 -> 144.66144 | G203: =H203+I203+J203+K203 -> 2126.8273 | H203: =C203*SNB_FX!$L222/SNB_FX!$B222 -> 1829.2111 | I203: =D203*SNB_FX!$L222/SNB_FX!$B222 -> 78.05698 | J203: =E203*SNB_FX!$L222/SNB_FX!$B222 -> 90.52974 | K203: =F203*SNB_FX!$L222/SNB_FX!$B222 -> 129.02948 | L203: =B203/G203 -> 1.1211503
... A219: 42644 | B219: =C219+D219+E219+F219 -> 2131.4416 | C219: =(SNB_D5_1a_M33!B245/0.968/SNB_FX!L238) -> 1822.5154 | D219: =D218*C219/C218 -> 77.771257 | E219: =E218*C219/C218 -> 90.198361 | F219: =(SNB.MONA!B53/1000)/SNB_FX!L238 -> 140.95663 | G219: =H219+I219+J219+K219 -> 1932.4574 | H219: =C219*SNB_FX!$L238/SNB_FX!$B238 -> 1652.3715 | I219: =D219*SNB_FX!$L238/SNB_FX!$B238 -> 70.510796 | J219: =E219*SNB_FX!$L238/SNB_FX!$B238 -> 81.777748 | K219: =F219*SNB_FX!$L238/SNB_FX!$B238 -> 127.79739 | L219: =B219/G219 -> 1.1029695
A220: 42675 | B220: =C220+D220+E220+F220 -> 2160.8516 | C220: =(SNB_D5_1a_M33!B246/0.968/SNB_FX!L239) -> 1848.1077 | D220: =D219*C220/C219 -> 78.863346 | E220: =E219*C220/C219 -> 91.464955 | F220: =(SNB.MONA!B54/1000)/SNB_FX!L239 -> 142.41555 | G220: =H220+I220+J220+K220 -> 1999.9777 | H220: =C220*SNB_FX!$L239/SNB_FX!$B239 -> 1710.5174 | I220: =D220*SNB_FX!$L239/SNB_FX!$B239 -> 72.992025 | J220: =E220*SNB_FX!$L239/SNB_FX!$B239 -> 84.655454 | K220: =F220*SNB_FX!$L239/SNB_FX!$B239 -> 131.81281
A221: 42705 | B221: =C221+D221+E221+F221 -> 2128.9411 | C221: =(SNB_D5_1a_M33!B247/0.968/SNB_FX!L240) -> 1816.8996 | D221: =D220*C221/C220 -> 77.531617 | E221: =E220*C221/C220 -> 89.920429 | F221: =(SNB.MONA!B55/1000)/SNB_FX!L240 -> 144.58946 | G221: =H221+I221+J221+K221 -> 2017.8814 | H221: =C221*SNB_FX!$L240/SNB_FX!$B240 -> 1722.118 | I221: =D221*SNB_FX!$L240/SNB_FX!$B240 -> 73.487054 | J221: =E221*SNB_FX!$L240/SNB_FX!$B240 -> 85.229583 | K221: =F221*SNB_FX!$L240/SNB_FX!$B240 -> 137.04672
A222: 42736 | B222: =C222+D222+E222+F222 -> 2128.4035 | C222: =(SNB_D5_1a_M33!B248/0.968/SNB_FX!L241) -> 1820.8316 | D222: =D221*C222/C221 -> 77.699406 | E222: =E221*C222/C221 -> 90.115029 | F222: =(SNB.MONA!B56/1000)/SNB_FX!L241 -> 139.75748 | G222: =H222+I222+J222+K222 -> 2003.8344 | H222: =C222*SNB_FX!$L241/SNB_FX!$B241 -> 1714.2637 | I222: =D222*SNB_FX!$L241/SNB_FX!$B241 -> 73.151891 | J222: =E222*SNB_FX!$L241/SNB_FX!$B241 -> 84.840865 | K222: =F222*SNB_FX!$L241/SNB_FX!$B241 -> 131.57789
A223: 42767 | B223: =C223+D223+E223+F223 -> 2195.9926 | C223: =(SNB_D5_1a_M33!B249/0.968/SNB_FX!L242) -> 1878.0916 | D223: =D222*C223/C222 -> 80.142835 | E223: =E222*C223/C222 -> 92.948894 | F223: =(SNB.MONA!B57/1000)/SNB_FX!L242 -> 144.80928 | G223: =H223+I223+J223+K223 -> 2063.7263 | H223: =C223*SNB_FX!$L242/SNB_FX!$B242 -> 1764.9727 | I223: =D223*SNB_FX!$L242/SNB_FX!$B242 -> 75.315768 | J223: =E223*SNB_FX!$L242/SNB_FX!$B242 -> 87.350509 | K223: =F223*SNB_FX!$L242/SNB_FX!$B242 -> 136.08731
A224: 42795 | B224: =C224+D224+E224+F224 -> 2214.009 | C224: =(SNB_D5_1a_M33!B250/0.968/SNB_FX!L243) -> 1892.1005 | D224: =D223*C224/C223 -> 80.740627 | E224: =E223*C224/C223 -> 93.642209 | F224: =(SNB.MONA!B58/1000)/SNB_FX!L243 -> 147.52568 | G224: =H224+I224+J224+K224 -> 2072.3505 | H224: =C224*SNB_FX!$L243/SNB_FX!$B243 -> 1771.0386 | I224: =D224*SNB_FX!$L243/SNB_FX!$B243 -> 75.574615 | J224: =E224*SNB_FX!$L243/SNB_FX!$B243 -> 87.650717 | K224: =F224*SNB_FX!$L243/SNB_FX!$B243 -> 138.08657
A225: 42826 | B225: =C225+D225+E225+F225 -> 2243.5285 | C225: =(SNB_D5_1a_M33!B251/0.968/SNB_FX!L244) -> 1915.1869 | D225: =D224*C225/C224 -> 81.72578 | E225: =E224*C225/C224 -> 94.784779 | F225: =(SNB.MONA!B59/1000)/SNB_FX!L244 -> 151.8311 | G225: =H225+I225+J225+K225 -> 2093.9321 | H225: =C225*SNB_FX!$L244/SNB_FX!$B244 -> 1787.4839 | I225: =D225*SNB_FX!$L244/SNB_FX!$B244 -> 76.276378 | J225: =E225*SNB_FX!$L244/SNB_FX!$B244 -> 88.464615 | K225: =F225*SNB_FX!$L244/SNB_FX!$B244 -> 141.70714
A226: 42856 | B226: =C226+D226+E226+F226 -> 2256.0504 | C226: =(SNB_D5_1a_M33!B252/0.968/SNB_FX!L245) -> 1926.8078 | D226: =D225*C226/C225 -> 82.221673 | E226: =E225*C226/C225 -> 95.359912 | F226: =(SNB.MONA!B60/1000)/SNB_FX!L245 -> 151.66099 | G226: =H226+I226+J226+K226 -> 2042.8053 | H226: =C226*SNB_FX!$L245/SNB_FX!$B245 -> 1744.6832 | I226: =D226*SNB_FX!$L245/SNB_FX!$B245 -> 74.449963 | J226: =E226*SNB_FX!$L245/SNB_FX!$B245 -> 86.346357 | K226: =F226*SNB_FX!$L245/SNB_FX!$B245 -> 137.32578
A227: 42887 | B227: =C227+D227+E227+F227 -> 2283.27 | C227: =(SNB_D5_1a_M33!B253/0.968/SNB_FX!L246) -> 1947.4927 | D227: =D226*C227/C226 -> 83.104349 | E227: =E226*C227/C226 -> 96.383631 | F227: =(SNB.MONA!B61/1000)/SNB_FX!L246 -> 156.28937 | G227: =H227+I227+J227+K227 -> 2032.7927 | H227: =C227*SNB_FX!$L246/SNB_FX!$B246 -> 1733.8505 | I227: =D227*SNB_FX!$L246/SNB_FX!$B246 -> 73.987707 | J227: =E227*SNB_FX!$L246/SNB_FX!$B246 -> 85.810236 | K227: =F227*SNB_FX!$L246/SNB_FX!$B246 -> 139.14425
A228: 42917 | B228: =C228+D228+E228+F228 -> 2374.8094 | C228: =(SNB_D5_1a_M33!B254/0.968/SNB_FX!L247) -> 2022.6996 | D228: =D227*C228/C227 -> 86.313614 | E228: =E227*C228/C227 -> 100.10571 | F228: =(SNB.MONA!B62/1000)/SNB_FX!L247 -> 165.69048 | G228: =H228+I228+J228+K228 -> 2063.9401 | H228: =C228*SNB_FX!$L247/SNB_FX!$B247 -> 1757.9224 | I228: =D228*SNB_FX!$L247/SNB_FX!$B247 -> 75.014917 | J228: =E228*SNB_FX!$L247/SNB_FX!$B247 -> 87.001584 | K228: =F228*SNB_FX!$L247/SNB_FX!$B247 -> 144.00113
A229: 42948 | B229: =C229+D229+E229+F229 -> 2372.1792 | C229: =(SNB_D5_1a_M33!B255/0.968/SNB_FX!L248) -> 2017.9568 | D229: =D228*C229/C228 -> 86.111228 | E229: =E228*C229/C228 -> 99.87098 | F229: =(SNB.MONA!B63/1000)/SNB_FX!L248 -> 168.2402 | G229: =H229+I229+J229+K229 -> 2008.3174 | H229: =C229*SNB_FX!$L248/SNB_FX!$B248 -> 1708.4281 | I229: =D229*SNB_FX!$L248/SNB_FX!$B248 -> 72.902872 | J229: =E229*SNB_FX!$L248/SNB_FX!$B248 -> 84.552055 | K229: =F229*SNB_FX!$L248/SNB_FX!$B248 -> 142.43431
A230: 42979 | B230: =C230+D230+E230+F230 -> 2419.6756 | C230: =(SNB_D5_1a_M33!B256/0.968/SNB_FX!L249) -> 2060.2504 | D230: =D229*C230/C229 -> 87.916004 | E230: =E229*C230/C229 -> 101.96414 | F230: =(SNB.MONA!B64/1000)/SNB_FX!L249 -> 169.54502 | G230: =H230+I230+J230+K230 -> 2030.1813 | H230: =C230*SNB_FX!$L249/SNB_FX!$B249 -> 1728.6126 | I230: =D230*SNB_FX!$L249/SNB_FX!$B249 -> 73.764195 | J230: =E230*SNB_FX!$L249/SNB_FX!$B249 -> 85.551009 | K230: =F230*SNB_FX!$L249/SNB_FX!$B249 -> 142.25341
A231: 43009 | B231: =C231+D231+E231+F231 -> 2467.0805 | C231: =(SNB_D5_1a_M33!B257/0.968/SNB_FX!L250) -> 2099.9023 | D231: =D230*C231/C230 -> 89.608045 | E231: =E230*C231/C230 -> 103.92655 | F231: =(SNB.MONA!B65/1000)/SNB_FX!L250 -> 173.64366 | G231: =H231+I231+J231+K231 -> 2098.365 | H231: =C231*SNB_FX!$L250/SNB_FX!$B250 -> 1786.0631 | I231: =D231*SNB_FX!$L250/SNB_FX!$B250 -> 76.215749 | J231: =E231*SNB_FX!$L250/SNB_FX!$B250 -> 88.394298 | K231: =F231*SNB_FX!$L250/SNB_FX!$B250 -> 147.69189
... A297: 45017 | B297: =C297+D297+E297+F297 -> 2855.0793 | C297: =(SNB_D5_1a_M33!B323/0.968/SNB_FX!L316) -> 2348.834 | D297: =D296*C297/C296 -> 100.23058 | E297: =E296*C297/C296 -> 116.24647 | F297: =(SNB.MONA!B131/1000)/SNB_FX!L316 -> 289.76821 | G297: =H297+I297+J297+K297 -> 2602.5321 | H297: =C297*SNB_FX!$L316/SNB_FX!$B316 -> 2141.067 | I297: =D297*SNB_FX!$L316/SNB_FX!$B316 -> 91.364645 | J297: =E297*SNB_FX!$L316/SNB_FX!$B316 -> 105.96384 | K297: =F297*SNB_FX!$L316/SNB_FX!$B316 -> 264.13665
A303: Notes: Foreign securities are multiplied by 1/0.968 to account of the less than exhaustive coverage of the SNB's monthly survey (see Zucman2013LivreSuisse.xls file for computation of this correction factor). With effect from the end of December 2012 the SNB has expanded the reporting population to include institutions "with a special field of business", which adds about 6% in foreign securities belonging to foreigners; therefore I upgrade pre-December 2012 figures by 6%. Col. 3 and 8 are set equal to $77bn in end-2011, the discrepancy between Swiss-reported portfolio liabilities and CPIS creditor-derived liabilities (that's the figure used in the book for 2010-2013), and follow evolution of col. 1 otherwise. Col. 4 and 9 are estimated at $100bn in May 2013 (figure used in the book) and follow evolution of col. 1 otherwise. Fiduciary deposits (col. 5 and 10) are the sum of foreign-owned and Swiss-owned (in reality Liechtenstein-foundations-owned) monthly fiduciary deposits data.

Sheet AppendixFigures

Sheet DataFA3
C1: GDP | D1: Offshore bn | E1: Offshore wealth /GDP
A2: Somalia | B2: Somalia | C2: 367.26201 | D2: 0.047814354 | E2: 0.0001301914
A3: Cuba | B3: Cuba | C3: 146.03521 | D3: 0.093126096 | E3: 0.00063769616
A4: Iran | B4: Iran (Islamic Republic of) | C4: 352.21301 | D4: 2.4288454 | E4: 0.0068959558
A5: India | B5: India | C5: 3386.4029 | D5: 26.021391 | E5: 0.00768408
A6: Bangladesh | B6: Bangladesh | C6: 460.201 | D6: 5.5185099 | E6: 0.011991521
A7: Algeria | B7: Algeria | C7: 191.91289 | D7: 2.8491778 | E7: 0.014846203
A8: Ethiopia | B8: Ethiopia | C8: 126.78347 | D8: 1.9062188 | E8: 0.015035231
A9: Pakistan | B9: Pakistan | C9: 376.53276 | D9: 6.9851918 | E9: 0.018551352
A10: Indonesia | B10: Indonesia | C10: 1318.807 | D10: 28.966833 | E10: 0.021964421
A11: Viet Nam | B11: Viet Nam | C11: 406.45201 | D11: 13.591372 | E11: 0.033439059
A12: Romania | B12: Romania | C12: 301.84499 | D12: 10.632418 | E12: 0.035224762
A13: Brazil | B13: Brazil | C13: 1924.1339 | D13: 77.173401 | E13: 0.040108123
... A66: UAE | B66: United Arab Emirates (the) | C66: 507.53493 | D66: 545.35034 | E66: 1.074508

Sheet DataFA4
C1: GDP | D1: Offshore bn | E1: Offshore wealth /GDP
A2: Somalia | B2: Somalia | C2: 367.26201 | D2: 0.047814354 | E2: 0.0001301914
A3: South Sudan | B3: South Sudan | C3: 6.1801149 | D3: 0.020714728 | E3: 0.0033518353
A4: Sudan | B4: Sudan (the) | C4: 51.662242 | D4: 0.41804299 | E4: 0.0080918479
A5: Rwanda | B5: Rwanda | C5: 13.312797 | D5: 0.13200355 | E5: 0.0099155384
A6: Niger | B6: Niger (the) | C6: 13.969606 | D6: 0.1555738 | E6: 0.011136593
A7: Benin | B7: Benin | C7: 17.401745 | D7: 0.20047179 | E7: 0.011520212
A8: Chad | B8: Chad | C8: 12.70415 | D8: 0.14771312 | E8: 0.011627156
A9: Burkina Faso | B9: Burkina Faso | C9: 18.88462 | D9: 0.2263075 | E9: 0.011983693
A10: Algeria | B10: Algeria | C10: 191.91289 | D10: 2.8491778 | E10: 0.014846203
A11: Ethiopia | B11: Ethiopia | C11: 126.78347 | D11: 1.9062188 | E11: 0.015035231
A12: Mauritania | B12: Mauritania | C12: 10.375461 | D12: 0.1750962 | E12: 0.016875993
A13: Cameroon | B13: Cameroon | C13: 44.341645 | D13: 0.89800775 | E13: 0.020252018
... A40: Angola | B40: Angola | C40: 106.71362 | D40: 51.790737 | E40: 0.48532452

Sheet DataFA5
C1: GDP | D1: Offshore bn | E1: Offshore wealth /GDP
A2: Turkmenistan | B2: Turkmenistan | C2: 78.003003 | D2: 0.17416985 | E2: 0.0022328609
A3: India | B3: India | C3: 3386.4029 | D3: 26.021391 | E3: 0.00768408
A4: Bangladesh | B4: Bangladesh | C4: 460.201 | D4: 5.5185099 | E4: 0.011991521
A5: New Caledonia | B5: New Caledonia | C5: 9.1742751 | D5: 0.16139674 | E5: 0.017592316
A6: Pakistan | B6: Pakistan | C6: 376.53276 | D6: 6.9851918 | E6: 0.018551352
A7: Indonesia | B7: Indonesia | C7: 1318.807 | D7: 28.966833 | E7: 0.021964421
A8: Sri Lanka | B8: Sri Lanka | C8: 74.403578 | D8: 1.9631125 | E8: 0.026384652
A9: Lao | B9: Lao People's Democratic Republic (the) | C9: 15.724384 | D9: 0.43068105 | E9: 0.027389374
A10: Viet Nam | B10: Viet Nam | C10: 406.45201 | D10: 13.591372 | E10: 0.033439059
A11: Myanmar | B11: Myanmar | C11: 59.364364 | D11: 2.3712497 | E11: 0.039943991
A12: Uzbekistan | B12: Uzbekistan | C12: 80.391856 | D12: 3.6034029 | E12: 0.044822984
A13: Nepal | B13: Nepal | C13: 40.828248 | D13: 1.8927461 | E13: 0.046358738
... A32: Taiwan | B32: Taiwan (Province of China) | C32: 761.69098 | D32: 649.69464 | E32: 0.85296356

Sheet DataFA6
B1: country_name | C1: GDP | D1: Offshore bn | E1: Offshore wealth /GDP
A2: Albania | B2: Albania | C2: 18.88 | D2: 0.1572895 | E2: =D2/C2 -> 0.0083310117
A3: Belarus | B3: Belarus | C3: 73.12 | D3: 1.010643 | E3: =D3/C3 -> 0.013821704
A4: Bosnia | B4: Bosnia and Herzegovina | C4: 24.53 | D4: 0.7143279 | E4: =D4/C4 -> 0.029120583
A5: Moldova | B5: Moldova (the Republic of) | C5: 14.41 | D5: 0.4945536 | E5: =D5/C5 -> 0.034320167
A6: Romania | B6: Romania | C6: 301.8 | D6: 10.63242 | E6: =D6/C6 -> 0.03523002
A7: Macedonia | B7: North Macedonia | C7: 13.56 | D7: 0.4897907 | E7: =D7/C7 -> 0.036120258
A8: Slovakia | B8: Slovakia | C8: 113.5 | D8: 5.559678 | E8: =D8/C8 -> 0.048983947
A9: Iceland | B9: Iceland | C9: 27.84 | D9: 1.678002 | E9: =D9/C9 -> 0.06027306
A10: Croatia | B10: Croatia | C10: 70.96 | D10: 4.859325 | E10: =D10/C10 -> 0.068479777
A11: Norway | B11: Norway | C11: 579.3 | D11: 45.81178 | E11: =D11/C11 -> 0.07908127
A12: Slovenia | B12: Slovenia | C12: 62.17 | D12: 4.982425 | E12: =D12/C12 -> 0.080141949
A13: Ukraine | B13: Ukraine | C13: 160.5 | D13: 13.52508 | E13: =D13/C13 -> 0.084268411
... A36: Greece | B36: Greece | C36: 219.2 | D36: 133.9185 | E36: =D36/C36 -> 0.61094206

Sheet DataFA7
C1: GDP | D1: Offshore bn | E1: Offshore wealth /GDP
A2: Cuba | B2: Cuba | C2: 146.03521 | D2: 0.093126096 | E2: 0.00063769616
A3: Haiti | B3: Haiti | C3: 20.253553 | D3: 0.58966917 | E3: 0.029114358
A4: Brazil | B4: Brazil | C4: 1924.1339 | D4: 77.173401 | E4: 0.040108123
A5: Argentina | B5: Argentina | C5: 632.77027 | D5: 47.721878 | E5: 0.075417385
A6: Guatemala | B6: Guatemala | C6: 95.003337 | D6: 7.2555065 | E6: 0.076371069
A7: Ecuador | B7: Ecuador | C7: 115.04947 | D7: 10.275703 | E7: 0.089315519
A8: Colombia | B8: Colombia | C8: 343.93899 | D8: 31.195257 | E8: 0.090699978
A9: Jamaica | B9: Jamaica | C9: 17.097761 | D9: 1.942238 | E9: 0.11359604
A10: Peru | B10: Peru | C10: 242.63156 | D10: 28.222538 | E10: 0.11631849
A11: Dominican R. | B11: Dominican Republic (the) | C11: 113.64186 | D11: 13.277531 | E11: 0.11683662
A12: Bolivia | B12: Bolivia (Plurinational State of) | C12: 43.068887 | D12: 5.5668983 | E12: 0.12925569
A13: Honduras | B13: Honduras | C13: 31.7177 | D13: 4.1094322 | E13: 0.12956274
... A20: Venezuela | B20: Venezuela (Bolivarian Republic of) | C20: 75.763892 | D20: 33.656013 | E20: 0.44422234

Sheet DataFA8
A1: year | B1: Total offshore wealth | C1: Switzerland | D1: Of which: American tax havens | E1: Of which: Asian tax havens | F1: Of which: European tax havens
A2: 2001 | B2: =T.A1!C8/T.A1!B8 -> 0.095132134 | C2: =T.A2!J5/T.A1!$B8 -> 0.036519698 | D2: =T.A2!L5/T.A1!$B8 -> 0.0093331177 | E2: =T.A2!M5/T.A1!$B8 -> 0.018425337 | F2: =T.A2!N5/T.A1!$B8 -> 0.030853981
A3: 2002 | B3: =T.A1!C9/T.A1!B9 -> 0.093447928 | C3: =T.A2!J6/T.A1!$B9 -> 0.0360236 | D3: =T.A2!L6/T.A1!$B9 -> 0.011982412 | E3: =T.A2!M6/T.A1!$B9 -> 0.01504065 | F3: =T.A2!N6/T.A1!$B9 -> 0.030401265
A4: 2003 | B4: =T.A1!C10/T.A1!B10 -> 0.089479827 | C4: =T.A2!J7/T.A1!$B10 -> 0.039011754 | D4: =T.A2!L7/T.A1!$B10 -> 0.010295377 | E4: =T.A2!M7/T.A1!$B10 -> 0.012403157 | F4: =T.A2!N7/T.A1!$B10 -> 0.027769538
A5: 2004 | B5: =T.A1!C11/T.A1!B11 -> 0.095220071 | C5: =T.A2!J8/T.A1!$B11 -> 0.040614126 | D5: =T.A2!L8/T.A1!$B11 -> 0.011673036 | E5: =T.A2!M8/T.A1!$B11 -> 0.012975584 | F5: =T.A2!N8/T.A1!$B11 -> 0.029957325
A6: 2005 | B6: =T.A1!C12/T.A1!B12 -> 0.094120609 | C6: =T.A2!J9/T.A1!$B12 -> 0.041622044 | D6: =T.A2!L9/T.A1!$B12 -> 0.010262301 | E6: =T.A2!M9/T.A1!$B12 -> 0.013798557 | F6: =T.A2!N9/T.A1!$B12 -> 0.028437708
A7: 2006 | B7: =T.A1!C13/T.A1!B13 -> 0.097748308 | C7: =T.A2!J10/T.A1!$B13 -> 0.046859396 | D7: =T.A2!L10/T.A1!$B13 -> 0.010410816 | E7: =T.A2!M10/T.A1!$B13 -> 0.013476085 | F7: =T.A2!N10/T.A1!$B13 -> 0.027002011
A8: 2007 | B8: =T.A1!C14/T.A1!B14 -> 0.11647364 | C8: =T.A2!J11/T.A1!$B14 -> 0.049909869 | D8: =T.A2!L11/T.A1!$B14 -> 0.013790041 | E8: =T.A2!M11/T.A1!$B14 -> 0.018362574 | F8: =T.A2!N11/T.A1!$B14 -> 0.034411158
A9: 2008 | B9: =T.A1!C15/T.A1!B15 -> 0.088189556 | C9: =T.A2!J12/T.A1!$B15 -> 0.033365412 | D9: =T.A2!L12/T.A1!$B15 -> 0.014195985 | E9: =T.A2!M12/T.A1!$B15 -> 0.01650071 | F9: =T.A2!N12/T.A1!$B15 -> 0.024127448
A10: 2009 | B10: =T.A1!C16/T.A1!B16 -> 0.10389391 | C10: =T.A2!J13/T.A1!$B16 -> 0.038863216 | D10: =T.A2!L13/T.A1!$B16 -> 0.016402443 | E10: =T.A2!M13/T.A1!$B16 -> 0.020896699 | F10: =T.A2!N13/T.A1!$B16 -> 0.02773155
A11: 2010 | B11: =T.A1!C17/T.A1!B17 -> 0.088024961 | C11: =T.A2!J14/T.A1!$B17 -> 0.034657385 | D11: =T.A2!L14/T.A1!$B17 -> 0.014468611 | E11: =T.A2!M14/T.A1!$B17 -> 0.018096018 | F11: =T.A2!N14/T.A1!$B17 -> 0.020802947
A12: 2011 | B12: =T.A1!C18/T.A1!B18 -> 0.088810095 | C12: =T.A2!J15/T.A1!$B18 -> 0.030469505 | D12: =T.A2!L15/T.A1!$B18 -> 0.014143707 | E12: =T.A2!M15/T.A1!$B18 -> 0.021713881 | F12: =T.A2!N15/T.A1!$B18 -> 0.022483002
A13: 2012 | B13: =T.A1!C19/T.A1!B19 -> 0.1092646 | C13: =T.A2!J16/T.A1!$B19 -> 0.031501726 | D13: =T.A2!L16/T.A1!$B19 -> 0.017157486 | E13: =T.A2!M16/T.A1!$B19 -> 0.029170165 | F13: =T.A2!N16/T.A1!$B19 -> 0.031435221
... A23: 2022 | B23: =T.A1!C29/T.A1!B29 -> 0.12252946 | C23: =T.A2!J26/T.A1!$B29 -> 0.026262117 | D23: =T.A2!L26/T.A1!$B29 -> 0.018897762 | E23: =T.A2!M26/T.A1!$B29 -> 0.050455237 | F23: =T.A2!N26/T.A1!$B29 -> 0.026914342

Sheet DataFA9
C1: offshore GDP 2007 | D1: offshore GDP 2022
A2: Korea | B2: Korea (Republic of) | C2: 0.0099207 | D2: 0.0614186
A3: China | B3: China | C3: 0.0160425 | D3: 0.1076974
A4: Poland | B4: Poland | C4: 0.0256956 | D4: 0.1143301
A5: Japan | B5: Japan | C5: 0.0283229 | D5: 0.0750068
A6: Denmark | B6: Denmark | C6: 0.0295126 | D6: 0.2410948
A7: Indonesia | B7: Indonesia | C7: 0.0311421 | D7: 0.0219644
A8: India | B8: India | C8: 0.0321279 | D8: 0.0076841
A9: Finland | B9: Finland | C9: 0.0411651 | D9: 0.0918229
A10: Iran | B10: Iran (Islamic Republic of) | C10: 0.0423505 | D10: 0.006896
A11: Norway | B11: Norway | C11: 0.0591804 | D11: 0.0790858
A12: Australia | B12: Australia | C12: 0.065719202 | D12: 0.1121529
A13: Brazil | B13: Brazil | C13: 0.072026685 | D13: 0.0401081
... A38: UAE | B38: United Arab Emirates | C38: 0.90611988 | D38: 1.074508

Sheet DataFA10
A1: % of world GDP
A2: year | B2: High income | C2: Middle and low income
A3: 2001 | B3: 7.285758 | C3: 2.124259
A4: 2002 | B4: 7.164482 | C4: 2.143686
A5: 2003 | B5: 6.808281 | C5: 2.010056
A6: 2004 | B6: 7.349789 | C6: 2.132471
A7: 2005 | B7: 7.164348 | C7: 2.222794
A8: 2006 | B8: 7.271956 | C8: 2.438498
A9: 2007 | B9: 8.745173 | C9: 2.799008
A10: 2008 | B10: 6.695837 | C10: 2.068999
A11: 2009 | B11: 7.842956 | C11: 2.487825
A12: 2010 | B12: 6.505993 | C12: 2.196171
A13: 2011 | B13: 6.669974 | C13: 2.125346
A14: 2012 | B14: 8.365094 | C14: 2.530113
... A24: 2022 | B24: 8.381131 | C24: 3.560555

Sheet DataFA11
A2: year | B2: High income | C2: Middle and low income
A3: 2001 | B3: 78.70493 | C3: 21.29507
A4: 2002 | B4: 80.31441 | C4: 19.6856
A5: 2003 | B5: 80.46981 | C5: 19.53019
A6: 2004 | B6: 79.67316 | C6: 20.32684
A7: 2005 | B7: 77.82666 | C7: 22.17334
A8: 2006 | B8: 77.15979 | C8: 22.84021
A9: 2007 | B9: 74.9642 | C9: 25.0358
A10: 2008 | B10: 72.71261 | C10: 27.2874
A11: 2009 | B11: 71.88229 | C11: 28.11771
A12: 2010 | B12: 68.91095 | C12: 31.08905
A13: 2011 | B13: 66.86182 | C13: 33.13819
A14: 2012 | B14: 65.60708 | C14: 34.39293
... A24: 2022 | B24: 60.76504 | C24: 39.23496

Sheet RawSources

Sheet source-bis
A1: Source of bilateral deposits and method: AJZ - FGZ comparison
B3: AJZ source | C3: AJZ method | D3: FGZ source | E3: FGZ method
A4: Switzerland | B4: Public BIS bilateral deposits | C4: 2003-04 average value | D4: Public BIS bilateral deposits | E4: weighted moving average
A5: EUROPEAN HAVENS (excl. Switzerland)
A6: Cyprus | B6: Public BIS all counterparty deposits | C6: saver distribution: 90% in RU, 10% in GR 2006-07 average value | D6: Public BIS all counterparty deposits | E6: saver distribution: 90% in RU, 10% in GR weighted moving average
A7: Guernsey | B7: Public BIS bilateral deposits | C7: 2006-07 average value | D7: Public BIS bilateral deposits | E7: weighted moving average
A8: Jersey | B8: Public BIS bilateral deposits | C8: 2006-07 average value | D8: Public BIS bilateral deposits | E8: weighted moving average
A9: Isle of Man | B9: Public BIS bilateral deposits | C9: 2006-07 average value | D9: Public BIS bilateral deposits | E9: weighted moving average
A10: Luxembourg | B10: Public BIS bilateral deposits | C10: 2006-07 average value | D10: Public BIS bilateral deposits | E10: weighted moving average
A11: Austria | B11: Public BIS bilateral deposits | C11: 2006-07 average value | D11: Public BIS bilateral deposits | E11: weighted moving average
A12: Belgium | B12: Public BIS bilateral deposits | C12: 2006-07 average value | D12: Public BIS bilateral deposits | E12: weighted moving average
A13: United Kingdom | B13: Public BIS bilateral deposits | C13: 2006-07 average value | D13: Public BIS bilateral deposits | E13: weighted moving average
A14: ASIAN HAVENS
A15: Macao | B15: Public BIS bilateral deposits | C15: 2006-07 average value | D15: Public BIS bilateral deposits | E15: weighted moving average
A16: Malaysia | B16: Public BIS bilateral deposits | C16: 2006-07 average value | D16: Public BIS all counterparty deposits | E16: saver share in residual countries weighted moving average
A17: Hong Kong | B17: Public BIS bilateral deposits | C17: 2006-07 average value | D17: Public BIS bilateral deposits | E17: weighted moving average
A18: Singapore | B18: BIS bilateral deposits (from 1N, haven aggregate) | C18: Substract non-Asian havens from aggregate Havens and add Malaysia. 2006-07 average value of this aggregate | D18: Public BIS all counterparty deposits | E18: saver share in residual countries weighted moving average
A19: Bahrain | D19: Public BIS all counterparty deposits | E19: saver share in residual countries weighted moving average
A20: Bahamas | D20: Public BIS all counterparty deposits | E20: saver share in residual countries weighted moving average
A21: Bermuda | D21: Public BIS all counterparty deposits | E21: saver share in residual countries weighted moving average
A22: Netherlands Antilles | D22: Public BIS all counterparty deposits | E22: saver share in residual countries weighted moving average
A23: Curaçao and other former parts of Netherlands Antilles | D23: Public BIS all counterparty deposits | E23: saver share in residual countries weighted moving average
A24: AMERICAN HAVENS
A25: Cayman Islands | B25: BIS bilateral deposits | C25: 2006-07 average value | D25: Public BIS all counterparty deposits | E25: 100% in the US weighted moving average
A26: Panama | B26: BIS bilateral deposits | C26: 2006-07 average value | D26: Public BIS all counterparty deposits | E26: saver share in residual countries weighted moving average
A27: United States | B27: BIS bilateral deposits | C27: 2006-07 average value | D27: Public BIS bilateral deposits | E27: weighted moving average
A28: Notes:

Sheet sharehouseholddep
A1: Share household deposit
A3: year | B3: AN | C3: AT | D3: BE | E3: BH | F3: BM | G3: BS | H3: CH | I3: CL | J3: CW | K3: CY | L3: GB | M3: GG | N3: HK | O3: IM | P3: JE | Q3: KY | R3: LU | S3: MO | T3: MY | U3: PA | V3: SG | W3: US
A4: 2001 | B4: 0.7 | C4: 0.3 | D4: 0.3 | E4: 0.7 | F4: 0.7 | G4: 0.7 | H4: 1 | I4: 0 | J4: 0.7 | K4: 1 | L4: 0.1 | M4: 1 | N4: 0.7 | O4: 1 | P4: 1 | Q4: 0.3 | R4: 1 | S4: 0.7 | T4: 0.7 | U4: 1 | V4: 0.7 | W4: 0.1
A5: 2002 | B5: 0.7 | C5: 0.3 | D5: 0.3 | E5: 0.7 | F5: 0.7 | G5: 0.7 | H5: 1 | I5: 0 | J5: 0.7 | K5: 1 | L5: 0.1 | M5: 1 | N5: 0.7 | O5: 1 | P5: 1 | Q5: 0.3 | R5: 1 | S5: 0.7 | T5: 0.7 | U5: 1 | V5: 0.7 | W5: 0.1
A6: 2003 | B6: 0.7 | C6: 0.3 | D6: 0.3 | E6: 0.7 | F6: 0.7 | G6: 0.7 | H6: 1 | I6: 0 | J6: 0.7 | K6: 1 | L6: 0.1 | M6: 1 | N6: 0.7 | O6: 1 | P6: 1 | Q6: 0.3 | R6: 1 | S6: 0.7 | T6: 0.7 | U6: 1 | V6: 0.7 | W6: 0.1
A7: 2004 | B7: 0.7 | C7: 0.3 | D7: 0.3 | E7: 0.7 | F7: 0.7 | G7: 0.7 | H7: 1 | I7: 0 | J7: 0.7 | K7: 1 | L7: 0.1 | M7: 1 | N7: 0.7 | O7: 1 | P7: 1 | Q7: 0.3 | R7: 1 | S7: 0.7 | T7: 0.7 | U7: 1 | V7: 0.7 | W7: 0.1
A8: 2005 | B8: 0.7 | C8: 0.3 | D8: 0.3 | E8: 0.7 | F8: 0.7 | G8: 0.7 | H8: 1 | I8: 0 | J8: 0.7 | K8: 1 | L8: 0.1 | M8: 1 | N8: 0.7 | O8: 1 | P8: 1 | Q8: 0.3 | R8: 1 | S8: 0.7 | T8: 0.7 | U8: 1 | V8: 0.7 | W8: 0.1
A9: 2006 | B9: 0.7 | C9: 0.3 | D9: 0.3 | E9: 0.7 | F9: 0.7 | G9: 0.7 | H9: 1 | I9: 0 | J9: 0.7 | K9: 1 | L9: 0.1 | M9: 1 | N9: 0.7 | O9: 1 | P9: 1 | Q9: 0.3 | R9: 1 | S9: 0.7 | T9: 0.7 | U9: 1 | V9: 0.7 | W9: 0.1
A10: 2007 | B10: 0.7 | C10: 0.3 | D10: 0.3 | E10: 0.7 | F10: 0.7 | G10: 0.7 | H10: 1 | I10: 0 | J10: 0.7 | K10: 1 | L10: 0.1 | M10: 1 | N10: 0.7 | O10: 1 | P10: 1 | Q10: 0.3 | R10: 1 | S10: 0.7 | T10: 0.7 | U10: 1 | V10: 0.7 | W10: 0.1
A11: 2008 | B11: 0.7 | C11: 0.2 | D11: 0.2 | E11: 0.7 | F11: 0.7 | G11: 0.7 | H11: 1 | I11: 0 | J11: 0.7 | K11: 1 | L11: 0.1 | M11: 1 | N11: 0.7 | O11: 1 | P11: 1 | Q11: 0.3 | R11: 1 | S11: 0.7 | T11: 0.7 | U11: 1 | V11: 0.7 | W11: 0.1
A12: 2009 | B12: 0.7 | C12: 0.15 | D12: 0.15 | E12: 0.7 | F12: 0.7 | G12: 0.7 | H12: 1 | I12: 0 | J12: 0.7 | K12: 1 | L12: 0.1 | M12: 0.95 | N12: 0.7 | O12: =O11-0.05 -> 0.95 | P12: =P11-0.05 -> 0.95 | Q12: 0.3 | R12: 1 | S12: 0.7 | T12: 0.7 | U12: 1 | V12: 0.7 | W12: 0.1
A13: 2010 | B13: 0.7 | C13: 0.1 | D13: 0.1 | E13: 0.7 | F13: 0.7 | G13: 0.7 | H13: 1 | I13: 0 | J13: 0.7 | K13: 1 | L13: 0.1 | M13: 0.9 | N13: 0.7 | O13: =O12-0.05 -> 0.9 | P13: =P12-0.05 -> 0.9 | Q13: 0.3 | R13: 1 | S13: 0.7 | T13: 0.7 | U13: 1 | V13: 0.7 | W13: 0.1
A14: 2011 | B14: 0.7 | C14: 0.05 | D14: 0.05 | E14: 0.7 | F14: 0.7 | G14: 0.7 | H14: 1 | I14: 0 | J14: 0.7 | K14: 1 | L14: 0.1 | M14: 0.85 | N14: 0.7 | O14: =O13-0.05 -> 0.85 | P14: =P13-0.05 -> 0.85 | Q14: 0.3 | R14: 1 | S14: 0.7 | T14: 0.7 | U14: 1 | V14: 0.7 | W14: 0.1
A15: 2012 | B15: 0.7 | C15: 0.05 | D15: 0.05 | E15: 0.7 | F15: 0.7 | G15: 0.7 | H15: 1 | I15: 0 | J15: 0.7 | K15: 1 | L15: 0.1 | M15: 0.8 | N15: 0.7 | O15: =O14-0.05 -> 0.8 | P15: =P14-0.05 -> 0.8 | Q15: 0.3 | R15: 1 | S15: 0.7 | T15: 0.7 | U15: 1 | V15: 0.7 | W15: 0.1
A16: 2013 | B16: 0.7 | C16: 0.05 | D16: 0.05 | E16: 0.7 | F16: 0.7 | G16: 0.7 | H16: 1 | I16: 0 | J16: 0.7 | K16: 1 | L16: 0.1 | M16: 0.75 | N16: 0.7 | O16: =O15-0.05 -> 0.75 | P16: =P15-0.05 -> 0.75 | Q16: 0.3 | R16: 1 | S16: 0.7 | T16: 0.7 | U16: 1 | V16: 0.7 | W16: 0.1
A17: 2014 | B17: 0.7 | C17: 0.05 | D17: 0.05 | E17: 0.7 | F17: 0.7 | G17: 0.7 | H17: 1 | I17: 0 | J17: 0.7 | K17: 1 | L17: 0.1 | M17: 0.7 | N17: 0.7 | O17: =O16-0.05 -> 0.7 | P17: =P16-0.05 -> 0.7 | Q17: 0.3 | R17: 1 | S17: 0.7 | T17: 0.7 | U17: 1 | V17: 0.7 | W17: 0.1
A18: 2015 | B18: 0.7 | C18: 0.05 | D18: 0.05 | E18: 0.7 | F18: 0.7 | G18: 0.7 | H18: 1 | I18: 0 | J18: 0.7 | K18: 1 | L18: 0.1 | M18: 0.65 | N18: 0.7 | O18: =O17-0.05 -> 0.65 | P18: =P17-0.05 -> 0.65 | Q18: 0.3 | R18: 1 | S18: 0.7 | T18: 0.7 | U18: 1 | V18: 0.7 | W18: 0.1
A19: 2016 | B19: 0.7 | C19: 0.05 | D19: 0.05 | E19: 0.7 | F19: 0.7 | G19: 0.7 | H19: 1 | I19: 0 | J19: 0.7 | K19: 1 | L19: 0.1 | M19: 0.65 | N19: 0.7 | O19: 0.65 | P19: 0.65 | Q19: 0.3 | R19: 0.9 | S19: 0.5 | T19: 0.5 | U19: 1 | V19: 0.7 | W19: 0.1
A20: 2017 | B20: 0.7 | C20: 0.05 | D20: 0.05 | E20: 0.7 | F20: 0.7 | G20: 0.7 | H20: 1 | I20: 0 | J20: 0.7 | K20: 1 | L20: 0.1 | M20: 0.65 | N20: 0.7 | O20: 0.65 | P20: 0.65 | Q20: 0.3 | R20: 0.8 | S20: 0.5 | T20: 0.5 | U20: 1 | V20: 0.7 | W20: 0.1
A21: 2018 | B21: 0.7 | C21: 0.05 | D21: 0.05 | E21: 0.7 | F21: 0.7 | G21: 0.7 | H21: 1 | I21: 0 | J21: 0.7 | K21: 1 | L21: 0.1 | M21: 0.65 | N21: 0.7 | O21: 0.65 | P21: 0.65 | Q21: 0.3 | R21: 0.7 | S21: 0.5 | T21: 0.5 | U21: 1 | V21: 0.7 | W21: 0.1
A22: 2019 | B22: 0.7 | C22: 0.05 | D22: 0.05 | E22: 0.7 | F22: 0.7 | G22: 0.7 | H22: 1 | I22: 0 | J22: 0.7 | K22: 1 | L22: 0.1 | M22: 0.65 | N22: 0.7 | O22: 0.65 | P22: 0.65 | Q22: 0.3 | R22: 0.6 | S22: 0.5 | T22: 0.5 | U22: 1 | V22: 0.7 | W22: 0.1
A23: 2020 | B23: 0.7 | C23: 0.05 | D23: 0.05 | E23: 0.7 | F23: 0.7 | G23: 0.7 | H23: 1 | I23: 0 | J23: 0.7 | K23: 1 | L23: 0.1 | M23: 0.65 | N23: 0.7 | O23: 0.65 | P23: 0.65 | Q23: 0.3 | R23: 0.5 | S23: 0.5 | T23: 0.5 | U23: 1 | V23: 0.7 | W23: 0.1
A24: 2021 | B24: 0.7 | C24: 0.05 | D24: 0.05 | E24: 0.7 | F24: 0.7 | G24: 0.7 | H24: 1 | I24: 0 | J24: 0.7 | K24: 1 | L24: 0.1 | M24: 0.65 | N24: 0.7 | O24: 0.65 | P24: 0.65 | Q24: 0.3 | R24: 0.4 | S24: 0.5 | T24: 0.5 | U24: 1 | V24: 0.7 | W24: 0.1
A25: 2022 | B25: 0.7 | C25: 0.05 | D25: 0.05 | E25: 0.7 | F25: 0.7 | G25: 0.7 | H25: 1 | I25: 0 | J25: 0.7 | K25: 1 | L25: 0.1 | M25: 0.65 | N25: 0.7 | O25: 0.65 | P25: 0.65 | Q25: 0.3 | R25: 0.4 | S25: 0.5 | T25: 0.5 | U25: 1 | V25: 0.7 | W25: 0.1

Sheet offshoreGDP2007
A1: Evolution of Offshore wealth / GDP between 2007 and mid-2023 (All countries with GDP > $200 billion in 2022) Assumption: 2023 country shares are a moving average which the highest weight on 2020.
A6: iso3 | C6: country | D6: 2007 GDP | E6: Offshore wealth bn | F6: Offshore wealth /GDP 2007
A7: KOR | B7: Korea | C7: Korea (Republic of) | D7: 1122.6792 | E7: 13.04814 | F7: 0.011622323
A8: POL | B8: Poland | C8: Poland | D8: 429.24965 | E8: 6.4260057 | F8: 0.014970323
A9: CHN | B9: China | C9: China | D9: 3552.1827 | E9: 81.36457 | F9: 0.022905514
A10: DNK | B10: Denmark | C10: Denmark | D10: 319.42337 | E10: 8.4203639 | F10: 0.026361139
A11: FIN | B11: Finland | C11: Finland | D11: 255.38462 | E11: 6.8864636 | F11: 0.026965068
A12: JPN | B12: Japan | C12: Japan | D12: 4515.2645 | E12: 123.85752 | F12: 0.027430844
A13: IND | B13: India | C13: India | D13: 1201.1118 | E13: 33.307825 | F13: 0.027730829
A14: NOR | B14: Norway | C14: Norway | D14: 400.88387 | E14: 14.092 | F14: 0.035152324
A15: IDN | B15: Indonesia | C15: Indonesia | D15: 432.21674 | E15: 15.332827 | F15: 0.035474857
A16: CAN | B16: Canada | C16: Canada | D16: 1464.9772 | E16: 68.033135 | F16: 0.046439723
A17: IRN | B17: Iran | C17: Iran (Islamic Republic of) | D17: 337.47449 | E17: 18.667731 | F17: 0.055315977
A18: SWE | B18: Sweden | C18: Sweden | D18: 487.81633 | E18: 28.449068 | F18: 0.05831922
... A43: ARE | B43: UAE | C43: United Arab Emirates | D43: 257.91613 | E43: 188.66282 | F43: 0.73148903

Sheet SNB_D4_1a
A1: Banque nationale suisse
A2: Bulletin mensuel de statistiques économiques août 2014
A3: Banques et autres intermédiaires financiers
A4: D4_1a Opérations fiduciaires - Avoirs à l'étranger et engagements envers l'étranger - Périmètre de consolidation: comptoir
A5: Passifs à titre fiduciaire en comptes étrangers (mensuel)
A7: Remarque: Pour bien comprendre les données du présent fichier, il est
A8: nécessaire de consulter le document correspondant de la publication.
A9: Ce fichier ne contient aucune information sur des indices,
A10: des notes de bas de page, etc. Pour accéder au document
A11: correspondant disponible en format PDF, activez le lien qui figure à la page
A12: web précédant celle-ci.
A13: Droits d'auteur: des restrictions sont apportées au téléchargement
... A15: un "x" symbolise les chiffres inaccessibles.
A17: Légende: | B17: M (missing) est représenté par "." dans la publication;
B18: Z (zero) est représenté par "-" dans la publication.
A20: Ruptures dans la série: | B20: Depuis septembre 2006, les données afférentes aux banques Raiffeisen portent sur l'ensemble du groupe Raiffeisen. Avant cette date, seuls les chiffres des principales banques Raiffeisen étaient pris en compte. De plus amples informations figurent dans le Bulletin mensuel de statistiques économiques de mars 2007 (Informations afférentes aux statistiques de la BNS) ainsi que dans les tableaux complémentaires D11a et D31a contenant des données extrapolées.
B22: CHF | C22: USD | D22: EUR | E22: DEM | F22: Autres monnaies | G22: Métaux précieux | H22: Prêts et pensions de titres | I22: Total
A24: 32142 | B24: 24330 | C24: 91282 | D24: M | E24: 23191 | F24: 37853 | G24: 313 | H24: M | I24: 176969
A25: 32173 | B25: 22254 | C25: 95659 | D25: M | E25: 23163 | F25: 38427 | G25: 316 | H25: M | I25: 179819
A26: 32202 | B26: 18593 | C26: 99129 | D26: M | E26: 22935 | F26: 40477 | G26: 301 | H26: M | I26: 181435
A27: 32233 | B27: 16584 | C27: 99377 | D27: M | E27: 22608 | F27: 42414 | G27: 314 | H27: M | I27: 181297
A28: 32263 | B28: 15899 | C28: 101166 | D28: M | E28: 22365 | F28: 43405 | G28: 312 | H28: M | I28: 183147
A29: 32294 | B29: 16196 | C29: 105463 | D29: M | E29: 22768 | F29: 45055 | G29: 336 | H29: M | I29: 189818
A30: 32324 | B30: 16175 | C30: 109983 | D30: M | E30: 21948 | F30: 44957 | G30: 337 | H30: M | I30: 193400
A31: 32355 | B31: 17119 | C31: 115643 | D31: M | E31: 21512 | F31: 45955 | G31: 345 | H31: M | I31: 200574
A32: 32386 | B32: 17543 | C32: 120385 | D32: M | E32: 22246 | F32: 47041 | G32: 346 | H32: M | I32: 207561
A33: 32416 | B33: 17636 | C33: 122922 | D33: M | E33: 21810 | F33: 48205 | G33: 384 | H33: M | I33: 210957
A34: 32447 | B34: 17428 | C34: 116155 | D34: M | E34: 21518 | F34: 48534 | G34: 377 | H34: M | I34: 204012
A35: 32477 | B35: 17916 | C35: 110822 | D35: M | E35: 21971 | F35: 49445 | G35: 373 | H35: M | I35: 200527
... A158: 36219 | B158: 15858 | C158: 232517 | D158: M | E158: 15867 | F158: 89934 | G158: 72 | H158: M | I158: 354248
A159: 36250 | B159: 17522 | C159: 239359 | D159: 73610 | E159: 12874 | F159: 34895 | G159: 69 | H159: M | I159: 365454
A160: 36280 | B160: 16932 | C160: 246460 | D160: 76631 | E160: 12366 | F160: 35344 | G160: 72 | H160: M | I160: 375439
A161: 36311 | B161: 17069 | C161: 243620 | D161: 76414 | E161: 11501 | F161: 34640 | G161: 68 | H161: M | I161: 371810
A162: 36341 | B162: 14787 | C162: 246715 | D162: 75762 | E162: 10194 | F162: 36037 | G162: 68 | H162: M | I162: 373370
A163: 36372 | B163: 14495 | C163: 238216 | D163: 76781 | E163: 9380 | F163: 34834 | G163: 64 | H163: M | I163: 364391
A164: 36403 | B164: 14723 | C164: 244015 | D164: 77849 | E164: 9390 | F164: 35459 | G164: 64 | H164: M | I164: 372111
A165: 36433 | B165: 14688 | C165: 242552 | D165: 78401 | E165: 8834 | F165: 35865 | G165: 75 | H165: M | I165: 371580
A166: 36464 | B166: 14502 | C166: 249829 | D166: 78549 | E166: 7921 | F166: 36014 | G166: 76 | H166: M | I166: 378971
A167: 36494 | B167: 14678 | C167: 257394 | D167: 78320 | E167: 7423 | F167: 37663 | G167: 76 | H167: M | I167: 388132
A168: 36525 | B168: 14829 | C168: 259613 | D168: 81428 | E168: 7204 | F168: 37495 | G168: 77 | H168: M | I168: 393442
A169: 36556 | B169: 14531 | C169: 265004 | D169: 82565 | E169: 6781 | F169: 38019 | G169: 77 | H169: M | I169: 400196
A170: 36585 | B170: 14732 | C170: 266633 | D170: 83685 | E170: 6548 | F170: 38474 | G170: 80 | H170: M | I170: 403604
... A194: 37315 | B194: 22662 | C194: 275530 | D194: 109020 | E194: 8 | F194: 36867 | G194: 61 | H194: M | I194: 444141
A195: 37346 | B195: 20646 | C195: 270117 | D195: 107271 | E195: M | F195: 36765 | G195: 61 | H195: M | I195: 434860
A196: 37376 | B196: 20731 | C196: 259066 | D196: 105209 | E196: M | F196: 35965 | G196: 60 | H196: M | I196: 421031
A197: 37407 | B197: 20213 | C197: 250638 | D197: 104263 | E197: M | F197: 35337 | G197: 62 | H197: M | I197: 410512
A198: 37437 | B198: 19761 | C198: 237379 | D198: 106479 | E198: M | F198: 35344 | G198: 57 | H198: M | I198: 399020
A199: 37468 | B199: 19158 | C199: 237653 | D199: 106766 | E199: M | F199: 36104 | G199: 114 | H199: M | I199: 399794
A200: 37499 | B200: 18128 | C200: 239221 | D200: 108987 | E200: M | F200: 36004 | G200: 57 | H200: M | I200: 402397
A201: 37529 | B201: 16599 | C201: 235683 | D201: 108999 | E201: M | F201: 36061 | G201: 58 | H201: M | I201: 397399
A202: 37560 | B202: 16218 | C202: 235398 | D202: 109202 | E202: M | F202: 36481 | G202: 57 | H202: M | I202: 397356
A203: 37590 | B203: 15006 | C203: 238179 | D203: 108645 | E203: M | F203: 36350 | G203: 57 | H203: M | I203: 398237
A204: 37621 | B204: 14928 | C204: 222522 | D204: 106241 | E204: M | F204: 35681 | G204: 59 | H204: M | I204: 379431
A205: 37652 | B205: 14856 | C205: 217844 | D205: 110649 | E205: M | F205: 36509 | G205: 61 | H205: M | I205: 379919
A206: 37680 | B206: 14339 | C206: 215277 | D206: 110409 | E206: M | F206: 35551 | G206: 57 | H206: M | I206: 375634
... A439: 44743 | B439: 74777.014 | C439: 4873347.4 | D439: 75008.348 | E439: M | F439: 504292.02 | G439: 0 | H439: M | I439: 172952.29
A440: 44774 | B440: 76120.45 | C440: 5460607.4 | D440: 72067.182 | E440: M | F440: 506322.04 | G440: 0 | H440: M
A441: 44805 | B441: 87700.825 | C441: 5523769.8 | D441: 592797.15 | E441: M | F441: 529356.11 | G441: 0 | H441: M
A442: 44835 | B442: 125128.99 | C442: 5813347.2 | D442: 976641.03 | E442: M | F442: 567020.75 | G442: 0 | H442: M
A443: 44866 | B443: 252007.56 | C443: 5571190.3 | D443: 1449252.5 | E443: M | F443: 538426.63 | G443: 0 | H443: M
A444: 44896 | B444: 293460.34 | C444: 5312585.2 | D444: 1623863.5 | E444: M | F444: 1421767 | G444: 0 | H444: M
A445: 44927 | B445: 285375.03 | C445: 5367415 | D445: 1688533.9 | E445: M | F445: 565016.86 | G445: 0 | H445: M
A446: 44958 | B446: 292875.79 | C446: 5455900.9 | D446: 1734956.5 | E446: M | F446: 526913.69 | G446: 0 | H446: M
A447: 44986 | B447: 184337.6 | C447: 5200129.8 | D447: 1773401.3 | E447: M | F447: 549802.14 | G447: 0 | H447: M

Sheet SNB_2E
A1: Banque nationale suisse
A2: Bulletin mensuel de statistiques bancaires août 2014
A3: Opérations fiduciaires
A4: 2E En comptes suisses (périmètre de consolidation: comptoir)
A5: Toutes banques (mensuel)
A7: Remarque: Pour bien comprendre les données du présent fichier, il est
A8: nécessaire de consulter le document correspondant de la publication.
A9: Ce fichier ne contient aucune information sur des indices,
A10: des notes de bas de page, etc. Pour accéder au document
A11: correspondant disponible en format PDF, activez le lien qui figure à la page
A12: web précédant celle-ci.
A13: Droits d'auteur: des restrictions sont apportées au téléchargement
... A15: un "x" symbolise les chiffres inaccessibles.
A17: Légende: | B17: M (missing) est représenté par "." dans la publication;
B18: Z (zero) est représenté par "-" dans la publication.
A20: Ruptures dans la série: | B20: Toutes les banques Raiffeisen. De plus amples informations figurent dans le Bulletin mensuel de statistiques économiques, édition de mars 2007 (Informations afférentes aux statistiques de la BNS).
B22: Actifs à titre fiduciaire | H22: Passifs à titre fiduciaire | N22: Nombre d'établissements
B23: Total | C23: CHF | D23: USD | E23: EUR | F23: Autres monnaies | G23: Métaux précieux | H23: Total | I23: CHF | J23: USD | K23: EUR | L23: Autres monnaies | M23: Métaux précieux
A25: 32142 | B25: 2283 | C25: 1683 | D25: 91 | E25: 108 | F25: 84 | G25: 317 | H25: 47905 | I25: 16573 | J25: 16692 | K25: 6261 | L25: 8375 | M25: 4 | N25: M
A26: 32173 | B26: 2134 | C26: 1494 | D26: 124 | E26: 108 | F26: 89 | G26: 319 | H26: 46944 | I26: 13890 | J26: 18061 | K26: 6311 | L26: 8678 | M26: 4 | N26: M
A27: 32202 | B27: 1958 | C27: 1318 | D27: 113 | E27: 110 | F27: 112 | G27: 305 | H27: 45104 | I27: 11267 | J27: 18702 | K27: 6061 | L27: 9070 | M27: 4 | N27: M
A28: 32233 | B28: 1974 | C28: 1291 | D28: 96 | E28: 127 | F28: 142 | G28: 318 | H28: 45421 | I28: 10454 | J28: 19166 | K28: 6037 | L28: 9760 | M28: 4 | N28: M
A29: 32263 | B29: 1987 | C29: 1293 | D29: 113 | E29: 142 | F29: 120 | G29: 319 | H29: 46094 | I29: 10170 | J29: 19929 | K29: 5917 | L29: 10071 | M29: 7 | N29: M
A30: 32294 | B30: 2402 | C30: 1432 | D30: 269 | E30: 198 | F30: 158 | G30: 345 | H30: 48155 | I30: 10552 | J30: 20866 | K30: 6133 | L30: 10595 | M30: 9 | N30: M
A31: 32324 | B31: 2127 | C31: 1327 | D31: 219 | E31: 128 | F31: 107 | G31: 346 | H31: 49774 | I31: 10944 | J31: 22280 | K31: 6021 | L31: 10520 | M31: 9 | N31: M
A32: 32355 | B32: 2107 | C32: 1325 | D32: 173 | E32: 129 | F32: 126 | G32: 354 | H32: 52295 | I32: 12225 | J32: 23068 | K32: 6072 | L32: 10921 | M32: 9 | N32: M
A33: 32386 | B33: 2079 | C33: 1310 | D33: 148 | E33: 140 | F33: 124 | G33: 357 | H33: 54185 | I33: 12802 | J33: 23522 | K33: 6467 | L33: 11384 | M33: 10 | N33: M
A34: 32416 | B34: 2084 | C34: 1310 | D34: 122 | E34: 156 | F34: 103 | G34: 393 | H34: 55557 | I34: 13251 | J34: 23685 | K34: 6826 | L34: 11785 | M34: 10 | N34: M
A35: 32447 | B35: 2040 | C35: 1301 | D35: 105 | E35: 147 | F35: 102 | G35: 385 | H35: 54921 | I35: 13419 | J35: 22683 | K35: 6570 | L35: 12239 | M35: 10 | N35: M
A36: 32477 | B36: 2062 | C36: 1342 | D36: 104 | E36: 141 | F36: 95 | G36: 380 | H36: 58129 | I36: 14009 | J36: 24299 | K36: 6637 | L36: 13175 | M36: 9 | N36: M
... A96: 34303 | B96: 2537 | C96: 1758 | D96: 214 | E96: 128 | F96: 181 | G96: 256 | H96: 83431 | I96: 27701 | J96: 23844 | K96: 12314 | L96: 19434 | M96: 138 | N96: M
A97: 34334 | B97: 3163 | C97: 2248 | D97: 233 | E97: 147 | F97: 277 | G97: 258 | H97: 82441 | I97: 28052 | J97: 23522 | K97: 11860 | L97: 18864 | M97: 143 | N97: 344
A98: 34365 | B98: 3233 | C98: 2334 | D98: 241 | E98: 165 | F98: 239 | G98: 254 | H98: 81884 | I98: 28080 | J98: 23184 | K98: 11334 | L98: 19148 | M98: 138 | N98: 337
A99: 34393 | B99: 2907 | C99: 2043 | D99: 266 | E99: 148 | F99: 203 | G99: 247 | H99: 80529 | I99: 27604 | J99: 22903 | K99: 11170 | L99: 18716 | M99: 136 | N99: 337
A100: 34424 | B100: 2972 | C100: 2055 | D100: 228 | E100: 149 | F100: 291 | G100: 249 | H100: 80946 | I100: 28113 | J100: 23200 | K100: 11177 | L100: 18319 | M100: 137 | N100: 336
A101: 34454 | B101: 2670 | C101: 1870 | D101: 204 | E101: 100 | F101: 251 | G101: 245 | H101: 80882 | I101: 27832 | J101: 23422 | K101: 11367 | L101: 18129 | M101: 132 | N101: 334
A102: 34485 | B102: 2557 | C102: 1840 | D102: 182 | E102: 117 | F102: 173 | G102: 245 | H102: 81162 | I102: 28254 | J102: 23688 | K102: 11390 | L102: 17695 | M102: 135 | N102: 332
A103: 34515 | B103: 2609 | C103: 1972 | D103: 190 | E103: 113 | F103: 113 | G103: 221 | H103: 79961 | I103: 28320 | J103: 22895 | K103: 11060 | L103: 17553 | M103: 133 | N103: 331
A104: 34546 | B104: 2710 | C104: 2046 | D104: 135 | E104: 144 | F104: 170 | G104: 215 | H104: 80138 | I104: 28211 | J104: 23812 | K104: 10938 | L104: 17047 | M104: 130 | N104: 331
A105: 34577 | B105: 2775 | C105: 2081 | D105: 161 | E105: 177 | F105: 143 | G105: 213 | H105: 80755 | I105: 28463 | J105: 24307 | K105: 10819 | L105: 17038 | M105: 128 | N105: 330
A106: 34607 | B106: 2804 | C106: 2159 | D106: 198 | E106: 156 | F106: 106 | G106: 185 | H106: 80217 | I106: 28641 | J106: 23785 | K106: 10811 | L106: 16854 | M106: 126 | N106: 329
A107: 34638 | B107: 2760 | C107: 2096 | D107: 174 | E107: 157 | F107: 166 | G107: 167 | H107: 79465 | I107: 28444 | J107: 23513 | K107: 10998 | L107: 16388 | M107: 122 | N107: 327
A108: 34668 | B108: 2691 | C108: 1993 | D108: 194 | E108: 154 | F108: 175 | G108: 175 | H108: 80923 | I108: 28095 | J108: 24977 | K108: 11072 | L108: 16652 | M108: 127 | N108: 327
... A215: 37925 | B215: 2250 | C215: 1346 | D215: 409 | E215: 345 | F215: 88 | G215: 62 | H215: 70349 | I215: 10071 | J215: 25455 | K215: 29183 | L215: 5640 | M215: 0 | N215: 270
A216: 37955 | B216: 2887 | C216: 1310 | D216: 731 | E216: 683 | F216: 100 | G216: 63 | H216: 68622 | I216: 10044 | J216: 24464 | K216: 28332 | L216: 5782 | M216: Z | N216: 270
A217: 37986 | B217: 2913 | C217: 1353 | D217: 765 | E217: 628 | F217: 104 | G217: 63 | H217: 65254 | I217: 8633 | J217: 23107 | K217: 27502 | L217: 6012 | M217: Z | N217: 268
A218: 38017 | B218: 2510 | C218: 1362 | D218: 480 | E218: 522 | F218: 85 | G218: 61 | H218: 66773 | I218: 8716 | J218: 24154 | K218: 27758 | L218: 6145 | M218: 0 | N218: 264
A219: 38046 | B219: 2230 | C219: 1339 | D219: 438 | E219: 332 | F219: 64 | G219: 57 | H219: 67093 | I219: 8887 | J219: 24145 | K219: 27713 | L219: 6348 | M219: 0 | N219: 264
A220: 38077 | B220: 2262 | C220: 1283 | D220: 457 | E220: 340 | F220: 121 | G220: 61 | H220: 66754 | I220: 8450 | J220: 24028 | K220: 27360 | L220: 6916 | M220: 0 | N220: 264
A221: 38107 | B221: 2387 | C221: 1388 | D221: 471 | E221: 388 | F221: 83 | G221: 57 | H221: 68726 | I221: 8940 | J221: 24818 | K221: 27947 | L221: 6997 | M221: 24 | N221: 264
A222: 38138 | B222: 2320 | C222: 1380 | D222: 423 | E222: 369 | F222: 92 | G222: 56 | H222: 67275 | I222: 9201 | J222: 23816 | K222: 27346 | L222: 6912 | M222: 0 | N222: 264
A223: 38168 | B223: 2306 | C223: 1382 | D223: 429 | E223: 321 | F223: 118 | G223: 56 | H223: 66257 | I223: 9115 | J223: 23855 | K223: 26355 | L223: 6932 | M223: 0 | N223: 264
A224: 38199 | B224: 2233 | C224: 1361 | D224: 409 | E224: 316 | F224: 90 | G224: 57 | H224: 68715 | I224: 9567 | J224: 24964 | K224: 27132 | L224: 7052 | M224: Z | N224: 264
A225: 38230 | B225: 2259 | C225: 1377 | D225: 395 | E225: 330 | F225: 98 | G225: 59 | H225: 68730 | I225: 9677 | J225: 24864 | K225: 27116 | L225: 7073 | M225: Z | N225: 264
A226: 38260 | B226: 2247 | C226: 1366 | D226: 396 | E226: 269 | F226: 157 | G226: 59 | H226: 68270 | I226: 10272 | J226: 24170 | K226: 26816 | L226: 7012 | M226: Z | N226: 264
A227: 38291 | B227: 2783 | C227: 1927 | D227: 386 | E227: 327 | F227: 85 | G227: 58 | H227: 68879 | I227: 11498 | J227: 23635 | K227: 26961 | L227: 6785 | M227: Z | N227: 263
A228: 38321 | B228: 2857 | C228: 1929 | D228: 411 | E228: 383 | F228: 76 | G228: 58 | H228: 67579 | I228: 11703 | J228: 22704 | K228: 26159 | L228: 7013 | M228: Z | N228: 263
A229: 38352 | B229: 2619 | C229: 1889 | D229: 399 | E229: 234 | F229: 41 | G229: 56 | H229: 67347 | I229: 12016 | J229: 22489 | K229: 25980 | L229: 6861 | M229: 1 | N229: 265
A230: 38383 | B230: 2657 | C230: 1907 | D230: 371 | E230: 280 | F230: 42 | G230: 57 | H230: 69914 | I230: 12480 | J230: 24501 | K230: 25808 | L230: 7121 | M230: 4 | N230: 262
A231: 38411 | B231: 2609 | C231: 1894 | D231: 302 | E231: 301 | F231: 55 | G231: 57 | H231: 69398 | I231: 13309 | J231: 23846 | K231: 25222 | L231: 7020 | M231: 1 | N231: 262
A232: 38442 | B232: 2836 | C232: 1851 | D232: 475 | E232: 385 | F232: 67 | G232: 58 | H232: 71020 | I232: 13596 | J232: 24599 | K232: 25363 | L232: 7462 | M232: 0 | N232: 261
A233: 38472 | B233: 2813 | C233: 1854 | D233: 447 | E233: 394 | F233: 59 | G233: 59 | H233: 73283 | I233: 13424 | J233: 24923 | K233: 26657 | L233: 8279 | M233: 0 | N233: 261
A234: 38503 | B234: 2627 | C234: 1850 | D234: 318 | E234: 339 | F234: 61 | G234: 59 | H234: 75765 | I234: 14270 | J234: 26064 | K234: 27038 | L234: 8393 | M234: 0 | N234: 260
A235: 38533 | B235: 2568 | C235: 1869 | D235: 230 | E235: 290 | F235: 115 | G235: 64 | H235: 77069 | I235: 14262 | J235: 26881 | K235: 27098 | L235: 8828 | M235: 0 | N235: 260
A236: 38564 | B236: 2649 | C236: 1847 | D236: 272 | E236: 334 | F236: 133 | G236: 63 | H236: 80572 | I236: 14627 | J236: 27389 | K236: 29277 | L236: 9279 | M236: 0 | N236: 259
A237: 38595 | B237: 2869 | C237: 1820 | D237: 364 | E237: 496 | F237: 127 | G237: 62 | H237: 80465 | I237: 14945 | J237: 27029 | K237: 28977 | L237: 9514 | M237: 0 | N237: 259
A238: 38625 | B238: 2666 | C238: 1809 | D238: 330 | E238: 291 | F238: 167 | G238: 69 | H238: 81740 | I238: 15231 | J238: 27974 | K238: 28974 | L238: 9561 | M238: 0 | N238: 259
A239: 38656 | B239: 2552 | C239: 1769 | D239: 288 | E239: 292 | F239: 134 | G239: 69 | H239: 83853 | I239: 15811 | J239: 28678 | K239: 29696 | L239: 9668 | M239: Z | N239: 259
A240: 38686 | B240: 2633 | C240: 1787 | D240: 342 | E240: 290 | F240: 140 | G240: 74 | H240: 85652 | I240: 15677 | J240: 29747 | K240: 30735 | L240: 9493 | M240: Z | N240: 259
A241: 38717 | B241: 2569 | C241: 1765 | D241: 308 | E241: 263 | F241: 156 | G241: 77 | H241: 85927 | I241: 16688 | J241: 29866 | K241: 30191 | L241: 9182 | M241: Z | N241: 259
A242: 38748 | B242: 2514 | C242: 1693 | D242: 326 | E242: 254 | F242: 158 | G242: 83 | H242: 86081 | I242: 16541 | J242: 29396 | K242: 30852 | L242: 9292 | M242: Z | N242: 257
A243: 38776 | B243: 2630 | C243: 1740 | D243: 407 | E243: 286 | F243: 114 | G243: 83 | H243: 88144 | I243: 16695 | J243: 30206 | K243: 31442 | L243: 9801 | M243: Z | N243: 256
A244: 38807 | B244: 2571 | C244: 1773 | D244: 397 | E244: 246 | F244: 68 | G244: 87 | H244: 89461 | I244: 17069 | J244: 30672 | K244: 31882 | L244: 9833 | M244: 5 | N244: 255
A245: 38837 | B245: 2591 | C245: 1707 | D245: 337 | E245: 307 | F245: 148 | G245: 92 | H245: 89190 | I245: 17354 | J245: 29985 | K245: 32116 | L245: 9735 | M245: Z | N245: 254
A246: 38868 | B246: 2736 | C246: 1791 | D246: 443 | E246: 263 | F246: 150 | G246: 89 | H246: 91713 | I246: 19079 | J246: 29697 | K246: 32699 | L246: 10238 | M246: Z | N246: 253
A247: 38898 | B247: 2915 | C247: 1722 | D247: 660 | E247: 281 | F247: 180 | G247: 72 | H247: 91916 | I247: 19252 | J247: 29434 | K247: 32938 | L247: 10292 | M247: Z | N247: 252
A248: 38929 | B248: 2978 | C248: 1748 | D248: 575 | E248: 441 | F248: 125 | G248: 89 | H248: 96203 | I248: 20518 | J248: 30164 | K248: 34900 | L248: 10621 | M248: Z | N248: 252
A249: 38960 | B249: 3200 | C249: 1786 | D249: 659 | E249: 481 | F249: 186 | G249: 88 | H249: 97650 | I249: 20246 | J249: 30884 | K249: 35547 | L249: 10968 | M249: 5 | N249: 252
A250: 38990 | B250: 2845 | C250: 1726 | D250: 516 | E250: 379 | F250: 139 | G250: 85 | H250: 101001 | I250: 20475 | J250: 31821 | K250: 37904 | L250: 10796 | M250: 5 | N250: 252
A251: 39021 | B251: 2994 | C251: 1754 | D251: 454 | E251: 475 | F251: 226 | G251: 85 | H251: 105116 | I251: 21958 | J251: 34048 | K251: 38278 | L251: 10827 | M251: 5 | N251: 251
A252: 39051 | B252: 3032 | C252: 1648 | D252: 591 | E252: 534 | F252: 171 | G252: 88 | H252: 106323 | I252: 22903 | J252: 33926 | K252: 37891 | L252: 11597 | M252: 6 | N252: 249
A253: 39082 | B253: 4097 | C253: 1718 | D253: 1029 | E253: 1093 | F253: 183 | G253: 74 | H253: 109939 | I253: 22955 | J253: 34999 | K253: 39228 | L253: 12747 | M253: 10 | N253: 278
A254: 39113 | B254: 3515 | C254: 1741 | D254: 800 | E254: 773 | F254: 108 | G254: 93 | H254: 109073 | I254: 23475 | J254: 33931 | K254: 39759 | L254: 11902 | M254: 6 | N254: 274
